Workbook
Name ACTION: #REF!
Name ACTION: #REF!

Sheet Cover
B2: TEST REPORT DOCUMENT
A4: Project Name | B4: Developing TikoSmart – a frozen food warehouse management system for TIKOVIA Trading and Service Co., Ltd. using ReactJS, React Native and NodeJS. | E4: Creator
A5: Project Code | B5: TSW | E5: Issue Date | F5: 46090
A6: Document Code | B6: =B5&"_"&"Test Report"&"_"&"v1.0" -> TSW_Test Report_v1.0 | E6: Version | F6: 1
A9: Record of change
A10: Effective Date | B10: Version | C10: Change Item | D10: *A,D,M | E10: Change description | F10: Reference
A11: 46090 | B11: 1.0 | C11: Initial Draft | D11: A | E11: Created the initial test document.
A12: 46091 | B12: 1.1 | C12: New Section | D12: M | E12: Add test case to document

Sheet Test Statistics
B1: TEST STATISTICS
B3: Project Name | C3: Developing VALOParking – A smart vehicle automated location organizer using ReactJS, NodeJS, AI YOLOv11 and IoT ESP32. | E3: Creator
B4: Project Code | C4: VALO | E4: Reviewer/Approver
B5: Document Code | C5: =C4&"_"&"Test Report"&"_"&"v1.0" -> VALO_Test Report_v1.0 | E5: Issue Date | H5: =Cover!F5 -> 46090
B6: Notes
B10: No | C10: Module code | D10: Passed | E10: Failed | F10: Pending | G10: N/A | H10: Number of test cases
B11: 1 | C11: Kiosk Check-in & Check-out | D11: ='1. Kiosk Check-in & Check-out'!B6 -> 19 | E11: ='1. Kiosk Check-in & Check-out'!C6 -> 7 | F11: ='1. Kiosk Check-in & Check-out'!D6 -> 0 | G11: ='1. Kiosk Check-in & Check-out'!E6 -> 0 | H11: ='1. Kiosk Check-in & Check-out'!B4 -> 26
B12: 2 | C12: Staff Gate & Barrier Control | D12: ='2. Staff Gate & Barrier Control'!B6 -> 17 | E12: ='2. Staff Gate & Barrier Control'!C6 -> 0 | F12: ='2. Staff Gate & Barrier Control'!D6 -> 0 | G12: ='2. Staff Gate & Barrier Control'!E6 -> 0 | H12: ='2. Staff Gate & Barrier Control'!B4 -> 17
B13: 3 | C13: IoT Barrier Integration | D13: ='3. IoT Barrier Integration'!B6 -> 22 | E13: ='3. IoT Barrier Integration'!C6 -> 3 | F13: ='3. IoT Barrier Integration'!D6 -> 0 | G13: ='3. IoT Barrier Integration'!E6 -> 0 | H13: ='3. IoT Barrier Integration'!B4 -> 25
B14: 4 | C14: IoT QR Code & Scanner | D14: ='4. IoT QR Code & Scanner'!B6 -> 18 | E14: ='4. IoT QR Code & Scanner'!C6 -> 2 | F14: ='4. IoT QR Code & Scanner'!D6 -> 0 | G14: ='4. IoT QR Code & Scanner'!E6 -> 0 | H14: ='4. IoT QR Code & Scanner'!B4 -> 20
B15: 5 | C15: AI Slot Surveillance & ALPR | D15: ='5. AI Slot Surveillance & ALPR'!B6 -> 30 | E15: ='5. AI Slot Surveillance & ALPR'!C6 -> 1 | F15: ='5. AI Slot Surveillance & ALPR'!D6 -> 0 | G15: ='5. AI Slot Surveillance & ALPR'!E6 -> 0 | H15: ='5. AI Slot Surveillance & ALPR'!B4 -> 31
B16: 6 | C16: 2D Parking Map & Slot Grid | D16: ='6. 2D Parking Map & Slot Grid'!B6 -> 31 | E16: ='6. 2D Parking Map & Slot Grid'!C6 -> 2 | F16: ='6. 2D Parking Map & Slot Grid'!D6 -> 0 | G16: ='6. 2D Parking Map & Slot Grid'!E6 -> 0 | H16: ='6. 2D Parking Map & Slot Grid'!B4 -> 33
B17: 7 | C17: Profile | D17: ='7. Profile '!B7 -> 44 | E17: ='7. Profile '!C7 -> 6 | F17: ='7. Profile '!D7 -> 0 | G17: ='7. Profile '!E7 -> 0
B18: 8 | C18: Account Management | D18: ='8. Account Management'!B8 -> 52 | E18: ='8. Account Management'!C8 -> 0 | F18: ='7. Profile '!D8 -> 0 | G18: ='7. Profile '!E8 -> 0
B19: 9 | C19: Parking Services | D19: ='9. Parking Services'!B6 -> 24
B20: 10 | C20: Ticket Package
B21: 11 | C21: Subscription Management
B22: 12 | C22: VALO AI
C38: Sub total | D38: =SUM(D10:D22) -> 257 | E38: =SUM(E10:E22) -> 21 | F38: =SUM(F10:F22) -> 0 | G38: =SUM(G10:G22) -> 0 | H38: =SUM(H10:H22) -> 152
C40: Test coverage | E40: =(D38+E38)*100/(H38-G38) -> 182.89474 | F40: %
C41: Test successful coverage | E41: =D38*100/(H38-G38) -> 169.07895 | F41: %
C43: HO SY HUNG (HUNGHS) — SPRINT 1 & SPRINT 2
C44: HSH summary uses Round 2 draft statuses; dates/results are retrospective and not historical execution evidence.
B45: 27 | C45: login | D45: ='27. login'!B7 -> 9 | E45: ='27. login'!C7 -> 0 | F45: ='27. login'!D7 -> 0 | G45: ='27. login'!E7 -> 0 | H45: ='27. login'!B4 -> 9
B46: 28 | C46: googleLogin | D46: ='28. googleLogin'!B7 -> 9 | E46: ='28. googleLogin'!C7 -> 0 | F46: ='28. googleLogin'!D7 -> 0 | G46: ='28. googleLogin'!E7 -> 0 | H46: ='28. googleLogin'!B4 -> 9
B47: 29 | C47: forgotResetPassword | D47: ='29. forgotResetPassword'!B7 -> 10 | E47: ='29. forgotResetPassword'!C7 -> 0 | F47: ='29. forgotResetPassword'!D7 -> 0 | G47: ='29. forgotResetPassword'!E7 -> 0 | H47: ='29. forgotResetPassword'!B4 -> 10
B48: 30 | C48: walletService | D48: ='30. walletService'!B7 -> 10 | E48: ='30. walletService'!C7 -> 0 | F48: ='30. walletService'!D7 -> 0 | G48: ='30. walletService'!E7 -> 0 | H48: ='30. walletService'!B4 -> 10
B49: 31 | C49: uploadAvatar | D49: ='31. uploadAvatar'!B7 -> 6 | E49: ='31. uploadAvatar'!C7 -> 0 | F49: ='31. uploadAvatar'!D7 -> 1 | G49: ='31. uploadAvatar'!E7 -> 0 | H49: ='31. uploadAvatar'!B4 -> 7
B50: 32 | C50: violationController | D50: ='32. violationController'!B7 -> 9 | E50: ='32. violationController'!C7 -> 0 | F50: ='32. violationController'!D7 -> 1 | G50: ='32. violationController'!E7 -> 0 | H50: ='32. violationController'!B4 -> 10
B51: 33 | C51: adminActionLog | D51: ='33. adminActionLog'!B7 -> 8 | E51: ='33. adminActionLog'!C7 -> 0 | F51: ='33. adminActionLog'!D7 -> 1 | G51: ='33. adminActionLog'!E7 -> 0 | H51: ='33. adminActionLog'!B4 -> 9
B52: 34 | C52: notificationSocket | D52: ='34. notificationSocket'!B7 -> 6 | E52: ='34. notificationSocket'!C7 -> 0 | F52: ='34. notificationSocket'!D7 -> 4 | G52: ='34. notificationSocket'!E7 -> 0 | H52: ='34. notificationSocket'!B4 -> 10
B53: 35 | C53: checkVIPSubscriptions | D53: ='35. checkVIPSubscriptions'!B7 -> 5 | E53: ='35. checkVIPSubscriptions'!C7 -> 0 | F53: ='35. checkVIPSubscriptions'!D7 -> 4 | G53: ='35. checkVIPSubscriptions'!E7 -> 0 | H53: ='35. checkVIPSubscriptions'!B4 -> 9
B54: 36 | C54: OAuthCallback | D54: ='36. OAuthCallback'!B7 -> 6 | E54: ='36. OAuthCallback'!C7 -> 0 | F54: ='36. OAuthCallback'!D7 -> 0 | G54: ='36. OAuthCallback'!E7 -> 0 | H54: ='36. OAuthCallback'!B4 -> 6
B55: 37 | C55: createBooking | D55: ='37. createBooking'!B7 -> 7 | E55: ='37. createBooking'!C7 -> 0 | F55: ='37. createBooking'!D7 -> 3 | G55: ='37. createBooking'!E7 -> 0 | H55: ='37. createBooking'!B4 -> 10
B56: 38 | C56: checkVietQRStatus | D56: ='38. checkVietQRStatus'!B7 -> 6 | E56: ='38. checkVietQRStatus'!C7 -> 0 | F56: ='38. checkVietQRStatus'!D7 -> 3 | G56: ='38. checkVietQRStatus'!E7 -> 0 | H56: ='38. checkVietQRStatus'!B4 -> 9
B57: 39 | C57: cancelBooking | D57: ='39. cancelBooking'!B7 -> 8 | E57: ='39. cancelBooking'!C7 -> 0 | F57: ='39. cancelBooking'!D7 -> 2 | G57: ='39. cancelBooking'!E7 -> 0 | H57: ='39. cancelBooking'!B4 -> 10
B58: 40 | C58: renewSubscription | D58: ='40. renewSubscription'!B7 -> 6 | E58: ='40. renewSubscription'!C7 -> 0 | F58: ='40. renewSubscription'!D7 -> 4 | G58: ='40. renewSubscription'!E7 -> 0 | H58: ='40. renewSubscription'!B4 -> 10
B59: 41 | C59: saveParkingLayout | D59: ='41. saveParkingLayout'!B7 -> 7 | E59: ='41. saveParkingLayout'!C7 -> 0 | F59: ='41. saveParkingLayout'!D7 -> 3 | G59: ='41. saveParkingLayout'!E7 -> 0 | H59: ='41. saveParkingLayout'!B4 -> 10
B60: 42 | C60: ServiceList | D60: ='42. ServiceList'!B7 -> 8 | E60: ='42. ServiceList'!C7 -> 0 | F60: ='42. ServiceList'!D7 -> 1 | G60: ='42. ServiceList'!E7 -> 0 | H60: ='42. ServiceList'!B4 -> 9
B61: 43 | C61: AuthScreen | D61: ='43. AuthScreen'!B7 -> 5 | E61: ='43. AuthScreen'!C7 -> 0 | F61: ='43. AuthScreen'!D7 -> 4 | G61: ='43. AuthScreen'!E7 -> 0 | H61: ='43. AuthScreen'!B4 -> 9
B62: 44 | C62: LoginScreen | D62: ='44. LoginScreen'!B7 -> 4 | E62: ='44. LoginScreen'!C7 -> 0 | F62: ='44. LoginScreen'!D7 -> 5 | G62: ='44. LoginScreen'!E7 -> 0 | H62: ='44. LoginScreen'!B4 -> 9
B63: 45 | C63: RegisterScreen | D63: ='45. RegisterScreen'!B7 -> 5 | E63: ='45. RegisterScreen'!C7 -> 0 | F63: ='45. RegisterScreen'!D7 -> 4 | G63: ='45. RegisterScreen'!E7 -> 0 | H63: ='45. RegisterScreen'!B4 -> 9
B64: 46 | C64: ForgotPasswordScreen | D64: ='46. ForgotPasswordScreen'!B7 -> 4 | E64: ='46. ForgotPasswordScreen'!C7 -> 0 | F64: ='46. ForgotPasswordScreen'!D7 -> 5 | G64: ='46. ForgotPasswordScreen'!E7 -> 0 | H64: ='46. ForgotPasswordScreen'!B4 -> 9
B65: 47 | C65: ResetPasswordScreen | D65: ='47. ResetPasswordScreen'!B7 -> 3 | E65: ='47. ResetPasswordScreen'!C7 -> 0 | F65: ='47. ResetPasswordScreen'!D7 -> 5 | G65: ='47. ResetPasswordScreen'!E7 -> 0 | H65: ='47. ResetPasswordScreen'!B4 -> 8
B66: 48 | C66: VehicleManagementScreen | D66: ='48. VehicleManagementScreen'!B7 -> 6 | E66: ='48. VehicleManagementScreen'!C7 -> 0 | F66: ='48. VehicleManagementScreen'!D7 -> 4 | G66: ='48. VehicleManagementScreen'!E7 -> 0 | H66: ='48. VehicleManagementScreen'!B4 -> 10
B67: 49 | C67: PoliciesScreens | D67: ='49. PoliciesScreens'!B7 -> 5 | E67: ='49. PoliciesScreens'!C7 -> 0 | F67: ='49. PoliciesScreens'!D7 -> 4 | G67: ='49. PoliciesScreens'!E7 -> 0 | H67: ='49. PoliciesScreens'!B4 -> 9
B68: 50 | C68: ServiceListScreen | D68: ='50. ServiceListScreen'!B7 -> 4 | E68: ='50. ServiceListScreen'!C7 -> 0 | F68: ='50. ServiceListScreen'!D7 -> 4 | G68: ='50. ServiceListScreen'!E7 -> 0 | H68: ='50. ServiceListScreen'!B4 -> 8
B69: 51 | C69: NotificationsScreen | D69: ='51. NotificationsScreen'!B7 -> 6 | E69: ='51. NotificationsScreen'!C7 -> 0 | F69: ='51. NotificationsScreen'!D7 -> 4 | G69: ='51. NotificationsScreen'!E7 -> 0 | H69: ='51. NotificationsScreen'!B4 -> 10
B70: 52 | C70: ParkingHistoryScreen | D70: ='52. ParkingHistoryScreen'!B7 -> 5 | E70: ='52. ParkingHistoryScreen'!C7 -> 0 | F70: ='52. ParkingHistoryScreen'!D7 -> 4 | G70: ='52. ParkingHistoryScreen'!E7 -> 0 | H70: ='52. ParkingHistoryScreen'!B4 -> 9
B71: 53 | C71: StaffDashboardScreen | D71: ='53. StaffDashboardScreen'!B7 -> 7 | E71: ='53. StaffDashboardScreen'!C7 -> 0 | F71: ='53. StaffDashboardScreen'!D7 -> 2 | G71: ='53. StaffDashboardScreen'!E7 -> 0 | H71: ='53. StaffDashboardScreen'!B4 -> 9
B72: 54 | C72: CustomerManagementScreen | D72: ='54. CustomerManagementScreen'!B7 -> 7 | E72: ='54. CustomerManagementScreen'!C7 -> 0 | F72: ='54. CustomerManagementScreen'!D7 -> 4 | G72: ='54. CustomerManagementScreen'!E7 -> 0 | H72: ='54. CustomerManagementScreen'!B4 -> 11
B73: 55 | C73: StaffSubscriptionsScreen | D73: ='55. StaffSubscriptionsScreen'!B7 -> 7 | E73: ='55. StaffSubscriptionsScreen'!C7 -> 0 | F73: ='55. StaffSubscriptionsScreen'!D7 -> 2 | G73: ='55. StaffSubscriptionsScreen'!E7 -> 0 | H73: ='55. StaffSubscriptionsScreen'!B4 -> 9
B74: 56 | C74: StaffTicketPackagesScreen | D74: ='56. StaffTicketPackagesScreen'!B7 -> 5 | E74: ='56. StaffTicketPackagesScreen'!C7 -> 0 | F74: ='56. StaffTicketPackagesScreen'!D7 -> 3 | G74: ='56. StaffTicketPackagesScreen'!E7 -> 0 | H74: ='56. StaffTicketPackagesScreen'!B4 -> 8
C75: HSH subtotal | D75: =SUM(D45:D74) -> 193 | E75: =SUM(E45:E74) -> 0 | F75: =SUM(F45:F74) -> 81 | G75: =SUM(G45:G74) -> 0 | H75: =SUM(H45:H74) -> 274
C77: HSH test coverage | E77: =(D75+E75)*100/(H75-G75) -> 70.437956 | F77: %
C78: HSH successful coverage | E78: =D75*100/(H75-G75) -> 70.437956 | F78: %
C80: Current-code automated checks — 07 Oct 2026
C81: Backend selected suites: 30 passed, 0 failed; full suite: 283 passed, 1 failed
C82: Frontend Node tests: 96 passed, 0 failed
C83: Backend failure: AI Copilot revenue metrics, outside these HSH cases; no historical case-level inference.

Sheet Test Cases
D1: TEST CASE LIST
B3: Project Name | D3: Developing VALOParking – A smart vehicle automated location organizer using ReactJS, NodeJS, AI YOLOv11 and IoT ESP32.
B4: Project Code | D4: VALO PARKING
B5: Test Environment Setup Description | D5: 1. VALOParking Backend Server: http://localhost:5000 2. VALOParking Frontend Server: http://localhost:5173 3. AI Service: http://localhost:8000 (FastAPI YOLOv11) 4. Database: MongoDB 5. Hardware: ESP32 Barrier Controller, IR Sensors, Webcams, QR Scanners 6. Web browsers: Google Chrome, Microsoft Edge 7. Devices: Kiosk Touchscreen, Laptop, Mobile
B8: No | C8: Function Name | D8: Sheet Name | E8: Description | F8: Pre-Condition
B9: 1 | C9: Kiosk Check-in/Check-out & IoT | D9: Kiosk Check-in & Check-out | E9: Verify complete automated check-in, check-out flows, PayOS payment, and real-time IoT hardware automation (ESP32 Barrier, IR sensors, Socket.io sync). | F9: Backend, Frontend, AI Service, and IoT barrier services are operational.
B10: 2 | C10: Staff Gate & Barrier Control | D10: Staff Gate & Barrier Control | E10: Verify staff portal: multi-camera enumeration, AI blurred plate resolution (confusable pairs & fuzzy match), manual check-in/out, security double-check, cash collection, and Auto-Pilot mode. | F10: Staff authenticated, IoT ESP32 barrier and camera streams online.
B11: 3 | C11: IoT Barrier Integration | D11: IoT Barrier Integration | E11: Verify real-world hardware & firmware integration: ESP32 dual I2C LCD 1602 marquee displays, servo PWM timers, IR auto-calibration & anti-smash safety, 30s open timeout, Python serial bridge (115200 baud), and bidirectional backend synchronization. | F11: ESP32 microcontroller connected via USB, dual servos, dual IR sensors, dual LCDs, Python serial bridge and backend server running.
B12: 4 | C12: IoT QR Code & Scanner | D12: IoT QR Code & Scanner | E12: Verify GM65 USB HID keyboard hardware scanner buffer listener, camera video QR fallback, HMAC-SHA256 signature security, multi-payload resolver (JWT, ObjectId, JSON, Plate), and AI plate cross-check verification. | F12: GM65 hardware scanner connected, Kiosk video camera active, Backend QR crypto service running.
B13: 5 | C13: AI Slot Surveillance & ALPR | D13: AI Slot Surveillance & ALPR | E13: Comprehensive end-to-end testing: YOLOv8-Seg polygon segmentation (27 slanted perspective slots), offline EasyOCR, Gemini 2.5 Flash hybrid fusion, camera misalignment scene validation, diorama plate normalization, 1080p full-res letterboxing compensation, auto-detect floor grid, audio siren alert, 8s background polling, and 1-Click Fast Reassign. | F13: YOLOv8-Seg model loaded, Gemini API key configured, CCTV camera feed online, MongoDB Floor collection active.
B14: 6 | C14: 2D Parking Map Designer & Slot Grid Management | D14: 2D Parking Map & Slot Grid | E14: Verify 2D visual parking lot layout designer, smart grid generator matrix, auto-fill naming algorithms, multi-element alignment/distribution, 50-level undo/redo, VIP entitlement and parked vehicle deletion guards, MongoDB spatial zone mapping, floor switching, and batch slot synchronization. | F14: Backend, MongoDB ParkingFloor and Slot collections, and Frontend Admin builder operational.
B15: 7 | C15: Profile | D15: Profile | E15: Verify customer profile viewing and management, including profile data loading, name/phone update validation, password change, authentication and error handling. | F15: Customer account exists and is active; customer is authenticated with a valid session/access token; VALO backend and database are available.
B16: 8 | C16: Account Management | D16: Account Management | E16: Verify Staff/Admin account management including account listing, search/filter/sort/pagination, account editing, block/unblock, Admin delete, validation and error handling. | F16: Active Staff/Admin account is authenticated with a valid access token; Account Management backend and database are available; target accounts exist where required.
B17: 9 | C17: Parking Services | D17: Parking Services | E17: Verify Admin parking service management including service catalog viewing, create, image upload/replacement, edit, activate/deactivate, delete, validation and authorization. | F17: Active Admin account is authenticated; Parking Service backend/database are available; service/image storage dependencies are available for relevant operations.
B18: 10 | C18: Ticket Package | D18: Ticket Package | E18: Verify Ticket Package functions across guest, customer, staff and admin, including catalog access, Admin package management, package selection, slot eligibility, Wallet/PayOS purchase and membership activation. | F18: Required role/session is available; protected flows use an active authenticated account; package, vehicle, slot, wallet/payment and membership data/services are available as required.
B19: 11 | C19: Subscription | D19: Subscription | E19: Verify Staff/Admin subscription management including subscription list, refresh, search/filter/display and Admin-only membership transfer review, approve/reject and validation. | F19: Active Staff/Admin account is authenticated with a valid access token; subscription data is available; Admin transfer-review dependencies exist for approve/reject scenarios.
B20: 12 | C20: VALO AI | D20: VALO AI | E20: Verify VALO AI for Admin and Staff including Gemini-backed chat, role-based tools, grounded draft creation/approval, notifications, AI actions and deterministic operational monitors. | F20: Active Admin/Staff account is authenticated; VALO AI backend and database are available; Gemini configuration is available for generative chat and relevant monitoring/data sources exist.
... B64: 56 | C64: StaffTicketPackagesScreen | D64: 56. StaffTicketPackagesScreen | E64: Staff read-only ticket-package catalog | F64: StaffTicketPackagesScreen and package API are mocked; Authenticated Staff has read-only package access

Sheet 1. Kiosk Check-in & Check-out
A2: Feature | B2: Kiosk Check-in & Check-out Management | R2: Passed
A3: Test requirement | B3: To verify end-to-end self-service check-in (AI LPR, FastPass QR, slot allocation), check-out (PayOS QR, cash/staff escalation), and real-time IoT hardware automation (ESP32 Barrier, IR sensors, Socket.io sync, emergency override). | R3: Failed
A4: Number of TCs | B4: =COUNTIF(A12:A41, "TC-*") -> 26 | R4: Pending
A5: Testing Round | B5: Passed | C5: Failed | D5: Pending | E5: N/A | R5: N/A
A6: Round 1 | B6: =COUNTIF(F11:F41, B5) -> 19 | C6: =COUNTIF(F11:F41, C5) -> 7 | D6: =COUNTIF(F11:F41, D5) -> 0 | E6: =COUNTIF(F11:F41, E5) -> 0
A7: Round 2 | B7: =COUNTIF(I11:I41, B5) -> 23 | C7: =COUNTIF(I11:I41, C5) -> 3 | D7: =COUNTIF(I11:I41, D5) -> 0 | E7: =COUNTIF(I11:I41, E5) -> 0
A8: Round 3 | B8: =COUNTIF(L11:L41, B5) -> 26 | C8: =COUNTIF(L11:L41, C5) -> 0 | D8: =COUNTIF(L11:L41, D5) -> 0 | E8: =COUNTIF(L11:L41, E5) -> 0
A10: Test Case ID | B10: Test Case Description | C10: Test Case Procedure | D10: Expected Results | E10: Pre-conditions | F10: Round 1 | G10: Test date | H10: Tester | I10: Round 2 | J10: Test date | K10: Tester | L10: Round 3 | M10: Test date | N10: Tester | O10: Note
A11: Function 1: Vehicle Entry & Kiosk Check-In Flow
A12: TC-KIOSK-IN-01 | B12: Check-in attempt when parking capacity is completely full | C12: 1. Vehicle approaches Entry Gate Kiosk. 2. System calls /api/sessions/check-full. 3. Evaluates total occupied slots vs capacity. | D12: - Displays "Parking Full" alert dialog. - "Create Ticket" action is disabled. - Entry barrier remains locked down. | E12: Total available slots in DB = 0 | F12: Passed | G12: 46255 | H12: VyVD | I12: Passed | J12: 46273 | K12: VyVD | L12: Passed | M12: 46297 | N12: VyVD
A13: TC-KIOSK-IN-02 | B13: AI License Plate Recognition on vehicle approach (Happy Path) | C13: 1. Vehicle triggers entry lane camera. 2. Frame captured and sent to YOLOv11 AI service. 3. Optical character recognition extracts plate. | D13: - Plate text extracted with >90% confidence. - Auto-fills plate box on Step 1 screen. - Displays vehicle snapshot preview. | E13: Camera lens unobstructed, standard VN license plate | F13: Passed | G13: 46255 | H13: VyVD | I13: Passed | J13: 46273 | K13: VyVD | L13: Passed | M13: 46297 | N13: VyVD
A14: TC-KIOSK-IN-03 | B14: Manual editing of license plate characters upon OCR error | C14: 1. AI misidentifies blurry character. 2. User taps on plate input field. 3. Edits characters and clicks "Continue". | D14: - Input field allows alphanumeric editing. - System validates format and navigates to Step 2. | E14: User is on Kiosk Step 1 screen | F14: Passed | G14: 46256 | H14: VyVD | I14: Passed | J14: 46274 | K14: VyVD | L14: Passed | M14: 46298 | N14: VyVD
A15: TC-KIOSK-IN-04 | B15: Validation for empty or malformed plate number | C15: 1. Clear the plate input field or enter special characters (!@#). 2. Tap "Continue". | D15: - Displays inline error: "Please enter a valid license plate". - Navigation to next step is blocked. | E15: Kiosk Step 1 active | F15: Passed | G15: 46256 | H15: VyVD | I15: Passed | J15: 46274 | K15: VyVD | L15: Passed | M15: 46298 | N15: VyVD
A16: TC-KIOSK-IN-05 | B16: Rejection of duplicate check-in (Vehicle already inside) | C16: 1. Submit plate number belonging to an active unclosed session. 2. Tap "Continue". | D16: - System rejects entry with alert: "Vehicle already inside parking lot". - No duplicate session created in DB. | E16: Vehicle license plate has active session status in DB | F16: Failed | G16: 46257 | H16: VyVD | I16: Failed | J16: 46275 | K16: VyVD | L16: Passed | M16: 46299 | N16: VyVD | O16: Case-insensitive regex bug fixed in R3 build
A17: TC-KIOSK-IN-06 | B17: FastPass QR check-in for pre-registered / monthly subscription | C17: 1. Driver taps "FastPass / Scan QR". 2. Presents valid FastPass QR to USB scanner. | D17: - System decodes QR token via /api/sessions/kiosk-verify-qr. - Matches registered plate & subscription. - Auto-creates session & sends barrier trigger. | E17: User possesses active subscription QR code | F17: Failed | G17: 46258 | H17: VyVD | I17: Passed | J17: 46276 | K17: VyVD | L17: Passed | M17: 46299 | N17: VyVD | O17: USB scanner raw input buffer delimiter fixed in R2
A18: TC-KIOSK-IN-07 | B18: FastPass check-in with expired, corrupted, or fake QR code | C18: 1. Scan expired or altered QR code on scanner. | D18: - Error dialog: "Invalid or expired FastPass QR code". - Kiosk prompts user to proceed with standard entry ticket. | E18: QR code token is invalid or expired | F18: Passed | G18: 46258 | H18: VyVD | I18: Passed | J18: 46276 | K18: VyVD | L18: Passed | M18: 46299 | N18: VyVD
A19: TC-KIOSK-IN-08 | B19: Vehicle type and parking service selection (Self-Park vs Valet) | C19: 1. On Step 2, select Vehicle Type (Car / Motorbike). 2. Select Parking Mode (Self-Parking / Valet). 3. Tap "Proceed to Confirmation". | D19: - State updates with selected vehicle and mode. - Pricing formula dynamically calculates base rate. | E19: Step 1 validated successfully | F19: Passed | G19: 46259 | H19: VyVD | I19: Passed | J19: 46277 | K19: VyVD | L19: Passed | M19: 46300 | N19: VyVD
A20: TC-KIOSK-IN-09 | B20: Finalize Check-in, assign available slot, and issue QR ticket | C20: 1. Confirm summary on Step 3. 2. Tap "Confirm & Enter". | D20: - Creates new Active session record in MongoDB. - Allocates matching available slot (e.g., A-05). - Renders QR check-in receipt modal on Kiosk. | E20: Available slots exist matching vehicle category | F20: Passed | G20: 46259 | H20: VyVD | I20: Passed | J20: 46277 | K20: VyVD | L20: Passed | M20: 46300 | N20: VyVD
A21: Function 2: Vehicle Exit & Kiosk Check-Out Flow
A22: TC-KIOSK-OUT-01 | B22: Exit camera license plate recognition & session retrieval | C22: 1. Vehicle approaches Kiosk Exit 1. 2. Camera captures plate & calls /api/sessions/kiosk-exit-scan. | D22: - Retrieves active session by plate. - Displays vehicle check-in image, duration, rate, and total fee on invoice screen. | E22: Vehicle has active session in system | F22: Passed | G22: 46260 | H22: VyVD | I22: Passed | J22: 46279 | K22: VyVD | L22: Passed | M22: 46301 | N22: VyVD
A23: TC-KIOSK-OUT-02 | B23: Check-out identification via physical/digital QR ticket scan | C23: 1. Driver holds QR ticket receipt under scanner at Kiosk Out. | D23: - Scanner reads session ID from QR. - Bypasses plate recognition and navigates directly to invoice payment screen. | E23: Valid QR ticket generated from check-in | F23: Passed | G23: 46260 | H23: VyVD | I23: Passed | J23: 46279 | K23: VyVD | L23: Passed | M23: 46301 | N23: VyVD
A24: TC-KIOSK-OUT-03 | B24: Exit process for active monthly subscription (Zero payment) | C24: 1. Scan plate or QR belonging to active monthly plan. | D24: - Total payment due displays 0 VND. - Marks session completed immediately. - Displays "Safe Trip" farewell screen and opens barrier. | E24: Customer has active paid subscription | F24: Passed | G24: 46261 | H24: VyVD | I24: Passed | J24: 46280 | K24: VyVD | L24: Passed | M24: 46303 | N24: VyVD
A25: TC-KIOSK-OUT-04 | B25: Online payment via PayOS dynamic VietQR (Happy Path) | C25: 1. On invoice screen, select "Pay with PayOS VietQR". 2. Kiosk requests PayOS orderCode and displays VietQR. 3. Driver transfers exact amount via mobile banking app. | D25: - PayOS webhook/polling detects status PAID. - Kiosk updates to Success screen in <3 seconds. - Dispatches barrier open signal. | E25: Network connected, PayOS API credentials active | F25: Failed | G25: 46261 | H25: VyVD | I25: Failed | J25: 46281 | K25: VyVD | L25: Passed | M25: 46303 | N25: VyVD | O25: Webhook latency caused checkout timeout; added 2s polling fallback in R3
A26: TC-KIOSK-OUT-05 | B26: Cancel PayOS transaction or QR countdown timeout | C26: 1. Generate VietQR payment code. 2. Tap "Cancel Payment" or let countdown timer expire. | D26: - PayOS order is safely cancelled. - Kiosk safely returns to payment method selection screen without hanging. | E26: VietQR modal currently displayed | F26: Passed | G26: 46262 | H26: VyVD | I26: Passed | J26: 46283 | K26: VyVD | L26: Passed | M26: 46304 | N26: VyVD
A27: TC-KIOSK-OUT-06 | B27: Cash payment assistance / Staff escalation from Kiosk | C27: 1. Driver taps "Pay Cash / Need Assistance". 2. Kiosk dispatches emergency assistance request to staff. | D27: - Kiosk switches to "Waiting for Staff Confirmation" state. - Staff clicks "Confirm Cash Collected" on Staff Dashboard. - Kiosk receives event and completes checkout. | E27: Staff is logged in on Staff Portal | F27: Passed | G27: 46262 | H27: VyVD | I27: Passed | J27: 46283 | K27: VyVD | L27: Passed | M27: 46304 | N27: VyVD
A28: TC-KIOSK-OUT-07 | B28: Unregistered plate / Lost ticket check-out handling | C28: 1. Scan plate not recorded in DB or damaged ticket. | D28: - Kiosk alerts: "No active session found. Please contact staff for assistance". - Exit barrier remains strictly locked. | E28: No active parking session found for given credentials | F28: Passed | G28: 46263 | H28: VyVD | I28: Passed | J28: 46284 | K28: VyVD | L28: Passed | M28: 46305 | N28: VyVD
A29: TC-KIOSK-OUT-08 | B29: Automatic slot de-allocation and capacity increment upon exit | C29: 1. Checkout completes successfully and vehicle departs. | D29: - Session status updates to "completed". - Assigned slot status reverts from "occupied" to "available". - Live capacity incremented by +1 in DB. | E29: Vehicle successfully completed checkout | F29: Failed | G29: 46263 | H29: VyVD | I29: Passed | J29: 46284 | K29: VyVD | L29: Passed | M29: 46305 | N29: VyVD | O29: Fixed MongoDB slot status atomic update concurrency in R2
A30: Function 3: IoT Barrier & Hardware Controller Integration
A31: TC-KIOSK-IOT-01 | B31: Automated Barrier Open trigger on check-in entry (ENTRY_1) | C31: 1. Driver completes Step 3 check-in confirmation. 2. Backend executes triggerBarrierOpen('ENTRY_1'). 3. Checks /api/iot/barrier-status?gate=ENTRY_1. | D31: - open state switches to true. - triggerId generated with current timestamp. - ESP32 servo motor raises gate arm to 90 degrees. | E31: ESP32 controller connected to Wi-Fi / LAN | F31: Passed | G31: 46264 | H31: VyVD | I31: Passed | J31: 46286 | K31: VyVD | L31: Passed | M31: 46306 | N31: VyVD
A32: TC-KIOSK-IOT-02 | B32: Automated Barrier Open trigger on check-out payment success (EXIT_1) | C32: 1. PayOS payment completes or staff approves cash exit. 2. Backend executes triggerBarrierOpen('EXIT_1'). | D32: - open state for EXIT_1 switches to true. - Exit barrier raises gate arm to 90 degrees. - Kiosk displays farewell animation. | E32: Exit barrier controller online | F32: Passed | G32: 46264 | H32: VyVD | I32: Passed | J32: 46286 | K32: VyVD | L32: Passed | M32: 46306 | N32: VyVD
A33: TC-KIOSK-IOT-03 | B33: Infrared (IR) safety sensor anti-smash & auto-close | C33: 1. Barrier opens for vehicle. 2. Vehicle drives through; IR beam is broken. 3. Vehicle fully clears IR beam. | D33: - When IR beam is broken, barrier arm holds position. - Once vehicle clears beam, system triggers auto-close after 3-second safety delay. | E33: IR obstacle sensor calibrated and operational | F33: Failed | G33: 46265 | H33: VyVD | I33: Passed | J33: 46287 | K33: VyVD | L33: Passed | M33: 46307 | N33: VyVD | O33: IR debounce threshold adjusted in ESP32 firmware
A34: TC-KIOSK-IOT-04 | B34: Hold Barrier Mode (Pause barrier & disable IR auto-close) | C34: 1. Staff sends POST /api/iot/hold-barrier with hold: true. 2. Checks barrier response. | D34: - holdOpen state transitions to true. - IR auto-close sensor is disabled. - Barrier remains open indefinitely until release command. | E34: Staff has administrative override privilege | F34: Passed | G34: 46265 | H34: VyVD | I34: Passed | J34: 46287 | K34: VyVD | L34: Passed | M34: 46307 | N34: VyVD
A35: TC-KIOSK-IOT-05 | B35: Force Close Barrier command | C35: 1. Send POST /api/iot/close-barrier for ENTRY_1. 2. Inspect ESP32 servo command. | D35: - open set to false, forceClose set to true. - Barrier immediately lowers to 0-degree position. | E35: Barrier is currently in raised state | F35: Passed | G35: 46266 | H35: VyVD | I35: Passed | J35: 46288 | K35: VyVD | L35: Passed | M35: 46308 | N35: VyVD
A36: Function 4: Real-time Socket Synchronization & Fail-safe
A37: TC-KIOSK-SYNC-01 | B37: Real-time WebSocket event emission on barrier state change | C37: 1. Trigger barrier open or close on Kiosk. 2. Listen for socket event 'gate:barrier_control' on Staff Dashboard. | D37: - WebSocket dispatches updated gateStates JSON instantly (<200ms). - Staff Live Monitor gate status reflects changes in real time. | E37: Socket.io server running and client connected | F37: Passed | G37: 46266 | H37: VyVD | I37: Passed | J37: 46288 | K37: VyVD | L37: Passed | M37: 46308 | N37: VyVD
A38: TC-KIOSK-SYNC-02 | B38: ESP32 offline / network disconnect polling resilience | C38: 1. Disconnect ESP32 from Wi-Fi for 30 seconds. 2. Reconnect ESP32. 3. Poll /api/iot/barrier-status. | D38: - ESP32 reconnects automatically without board restart. - Syncs last triggerId without missing gate open requests. | E38: Hardware test bench connected | F38: Failed | G38: 46267 | H38: VyVD | I38: Failed | J38: 46289 | K38: VyVD | L38: Passed | M38: 46309 | N38: VyVD | O38: Reconnection loop stalled on DNS cache; fixed with exponential backoff in R3
A39: TC-KIOSK-SYNC-03 | B39: AI Service camera stream disconnection recovery | C39: 1. Disconnect entry webcam USB cable during active Kiosk session. 2. Reconnect USB camera. | D39: - Kiosk displays "Camera Reconnecting..." fallback UI. - Auto-recovers video stream without browser page reload. | E39: Kiosk running on touchscreen terminal | F39: Failed | G39: 46267 | H39: VyVD | I39: Passed | J39: 46289 | K39: VyVD | L39: Passed | M39: 46309 | N39: VyVD | O39: Added navigator.mediaDevices.ondevicechange event listener in R2
A40: TC-KIOSK-SYNC-04 | B40: Simultaneous dual-gate check-in and check-out operation | C40: 1. Vehicle checks in at ENTRY_1 while another vehicle checks out at EXIT_1. 2. Trigger both gates simultaneously. | D40: - gateStates.ENTRY_1 and gateStates.EXIT_1 update independently without mutex race conditions. - Both barriers operate concurrently. | E40: Two concurrent sessions active | F40: Passed | G40: 46268 | H40: VyVD | I40: Passed | J40: 46290 | K40: VyVD | L40: Passed | M40: 46309 | N40: VyVD

Sheet 2. Staff Gate & Barrier Control
A2: Feature | B2: Staff Gate & Barrier Control Management | R2: Passed
A3: Test requirement | B3: To verify real-world staff station capabilities: multi-device camera streaming, AI blurred/occluded plate resolution (fuzzy match & Gemini Vision), manual entry check-in, exit security double-check, cash collection confirmation, hardware barrier controls, and autonomous Auto-Pilot mode. | R3: Failed
A4: Number of TCs | B4: =COUNTIF(A12:A33, "TC-*") -> 17 | R4: Pending
A5: Testing Round | B5: Passed | C5: Failed | D5: Pending | E5: N/A | R5: N/A
A6: Round 1 | B6: =COUNTIF(F11:F33, B5) -> 17 | C6: =COUNTIF(F11:F33, C5) -> 0 | D6: =COUNTIF(F11:F33, D5) -> 0 | E6: =COUNTIF(F11:F33, E5) -> 0
A7: Round 2 | B7: =COUNTIF(I11:I33, B5) -> 15 | C7: =COUNTIF(I11:I33, C5) -> 2 | D7: =COUNTIF(I11:I33, D5) -> 0 | E7: =COUNTIF(I11:I33, E5) -> 0
A8: Round 3 | B8: =COUNTIF(L11:L33, B5) -> 17 | C8: =COUNTIF(L11:L33, C5) -> 0 | D8: =COUNTIF(L11:L33, D5) -> 0 | E8: =COUNTIF(L11:L33, E5) -> 0
A10: Test Case ID | B10: Test Case Description | C10: Test Case Procedure | D10: Expected Results | E10: Pre-conditions | F10: Round 1 | G10: Test date | H10: Tester | I10: Round 2 | J10: Test date | K10: Tester | L10: Round 3 | M10: Test date | N10: Tester | O10: Note
A11: Function 1: Multi-Camera Device Enumeration & Live Station Feeds
A12: TC-GATE-CAM-01 | B12: Enumerate connected video input devices and assign to lanes | C12: 1. Connect dual USB webcams to staff station. 2. Open Gate Control page. 3. Call enumerateAllCameras(). | D12: - navigator.mediaDevices detects all videoinput devices. - Auto-assigns Device 1 to valo_entry_cam and Device 2 to valo_exit_cam in localStorage. - Populates dropdown list on both lanes. | E12: Staff logged in with active permissions; cameras connected | F12: Passed | G12: 46256 | H12: VyVD | I12: Passed | J12: 46273 | K12: VyVD | L12: Passed | M12: 46297 | N12: VyVD
A13: TC-GATE-CAM-02 | B13: Switch camera source device dynamically via lane dropdown | C13: 1. Click camera device dropdown on Entry Lane. 2. Select alternative webcam source. | D13: - Stops current video stream tracks. - Starts new MediaStream with exact selected deviceId constraint. - Live feed updates instantly without full page refresh. | E13: At least two distinct webcam devices connected | F13: Passed | G13: 46257 | H13: VyVD | I13: Passed | J13: 46273 | K13: VyVD | L13: Passed | M13: 46297 | N13: VyVD
A14: TC-GATE-CAM-03 | B14: Capture snapshot frame from live video canvas | C14: 1. Click "Capture & AI Scan" on Entry or Exit station. 2. Video frame draws to hidden canvas element. | D14: - Canvas extracts image/jpeg base64 data URL at 0.85 quality. - Snapshot thumbnail renders over video preview with "Live Camera" toggle button. | E14: Camera video stream is currently active | F14: Passed | G14: 46257 | H14: VyVD | I14: Passed | J14: 46274 | K14: VyVD | L14: Passed | M14: 46298 | N14: VyVD
A15: Function 2: AI Blurred / Occluded Plate Resolution Assistant
A16: TC-GATE-AI-01 | B16: Open AI Plate Assistant modal and transfer lane snapshot | C16: 1. Click "AI Blurred Plate Assistant" button under Entry or Exit lane. 2. Observe modal initial state. | D16: - AIPlateResolutionModal opens over screen with backdrop blur. - Passes captured snapshot and current plate string into modal state. - Displays vehicle image preview. | E16: User on Gate Control page with snapshot captured | F16: Passed | G16: 46258 | H16: VyVD | I16: Passed | J16: 46274 | K16: VyVD | L16: Passed | M16: 46298 | N16: VyVD
A17: TC-GATE-AI-02 | B17: Resolve plate using Confusable Pairs & Weighted Levenshtein | C17: 1. Enter blurred plate "51F-88B.99" (B instead of 8). 2. Click "Resolve Plate" calling /api/ai/resolve-unclear-plate. | D17: - Backend plateResolutionService computes weighted distance with CONFUSABLE_PAIRS (8-B cost 0.4). - Fuzzy matches active VIP subscriptions and today's bookings. - Returns candidate plate "51F-888.99" with confidence score and source badge. | E17: Matching booking or registered vehicle exists in database | F17: Passed | G17: 46259 | H17: VyVD | I17: Failed | J17: 46275 | K17: VyVD | L17: Passed | M17: 46299 | N17: VyVD | O17: Passed in R1, but in R2 regex change in normalizeLicensePlate stripped dot separators causing fuzzy distance mismatch; fixed in R3
A18: TC-GATE-AI-03 | B18: Select suggested candidate plate and auto-populate lane form | C18: 1. In AI Resolution modal results, click on candidate card "51F-888.99". 2. Trigger onSelectPlate callback. | D18: - Modal closes. - Selected plate auto-populates entryPlate or exitPlate input box. - Auto-triggers verifyEntryPlate() or lookupExitSession() with verified badge. | E18: Candidate results displayed in modal | F18: Passed | G18: 46259 | H18: VyVD | I18: Passed | J18: 46275 | K18: VyVD | L18: Passed | M18: 46299 | N18: VyVD
A19: Function 3: Staff Assisted Vehicle Check-In & Slot Allocation
A20: TC-GATE-IN-01 | B20: Verify plate and display classification badges (VIP, Booking, Active) | C20: 1. Enter license plate into Entry Lane and blur input. 2. Calls /api/sessions/verify-plate. | D20: - Shows purple badge for Monthly VIP, amber for Pre-Booking, or green for Walk-in. - Displays red error banner: "WARNING: Vehicle currently has an ACTIVE session inside!" if active. | E20: Database has pre-populated test vehicles | F20: Passed | G20: 46260 | H20: VyVD | I20: Passed | J20: 46276 | K20: VyVD | L20: Passed | M20: 46300 | N20: VyVD
A21: TC-GATE-IN-02 | B21: Manual Floor and Slot designation override by staff | C21: 1. Select Floor from dropdown (populated via getAllFloors). 2. Type custom slot code (e.g. "B1-08"). 3. Click "Check-in & Open Barrier". | D21: - Sends POST /api/sessions/kiosk-entry with custom floorId and parkingSlot. - Creates session in DB, executes triggerBarrier('open', 'ENTRY_1'), and resets entry form. | E21: Floor exists with open capacity | F21: Passed | G21: 46260 | H21: VyVD | I21: Passed | J21: 46276 | K21: VyVD | L21: Passed | M21: 46300 | N21: VyVD
A22: TC-GATE-IN-03 | B22: Validation check when clicking Check-In with empty plate | C22: 1. Leave plate input empty. 2. Click "Check-in & Open Barrier". | D22: - Toast notification: "Please enter or scan vehicle license plate". - Check-in API is not dispatched. | E22: Plate input is empty | F22: Passed | G22: 46261 | H22: VyVD | I22: Passed | J22: 46277 | K22: VyVD | L22: Passed | M22: 46300 | N22: VyVD
A23: Function 4: Staff Assisted Vehicle Check-Out & Cash Collection
A24: TC-GATE-OUT-01 | B24: Quick-select vehicle from active sessions dropdown list | C24: 1. In Exit Lane, click "Active vehicles in lot" dropdown. 2. Pick a license plate from active sessions list. | D24: - Immediately populates exitPlate input. - Automatically calls lookupExitSession(plate) and retrieves invoice breakdown. | E24: At least one active session in parking lot | F24: Passed | G24: 46262 | H24: VyVD | I24: Passed | J24: 46279 | K24: VyVD | L24: Passed | M24: 46301 | N24: VyVD
A25: TC-GATE-OUT-02 | B25: Security Double-Check: Side-by-side Entry vs Exit photos | C25: 1. Lookup active exit session. 2. Inspect Security Double-Check panel. | D25: - Displays Check-in photo (from session.entryImage) on the left with check-in time. - Displays current Exit snapshot on the right for visual comparison of plate & vehicle model. | E25: Session has valid entryImage recorded | F25: Passed | G25: 46262 | H25: VyVD | I25: Passed | J25: 46279 | K25: VyVD | L25: Passed | M25: 46301 | N25: VyVD
A26: TC-GATE-OUT-03 | B26: Cash collection confirmation checkbox and checkout dispatch | C26: 1. For fee > 0 VND, tick checkbox "Cash collected directly from customer". 2. Click "Check-out & Open Barrier". | D26: - Sends paymentMethod: "CASH" to /api/sessions/kiosk-checkout. - Backend marks session paymentStatus: "paid". - Triggers triggerBarrier('open', 'EXIT_1') and resets exit form. | E26: Active invoice with positive amount due | F26: Passed | G26: 46263 | H26: VyVD | I26: Passed | J26: 46280 | K26: VyVD | L26: Passed | M26: 46303 | N26: VyVD
A27: TC-GATE-OUT-04 | B27: Checkout button disabled state when no invoice is loaded | C27: 1. Clear exit lane data. 2. Inspect "Check-out & Open Barrier" button state. | D27: - Button has disabled attribute and opacity-50 class. - Clicking button does not trigger any network request. | E27: exitInvoiceData is null | F27: Passed | G27: 46263 | H27: VyVD | I27: Passed | J27: 46280 | K27: VyVD | L27: Passed | M27: 46303 | N27: VyVD
A28: Function 5: Manual Barrier Overrides & Autonomous Auto-Pilot Mode
A29: TC-GATE-OVR-01 | B29: Direct hardware barrier manual control (Open, Hold, Close) | C29: 1. Click "Open Exit Barrier" -> triggers /api/iot/open-barrier. 2. Click "Pause Barrier" -> triggers /api/iot/hold-barrier. 3. Click "Lock Barrier" -> triggers /api/iot/close-barrier. | D29: - API executes successfully with target gate (EXIT_1). - Socket broadcasts gate:barrier_control event. - Barrier status badge toggles between "OPEN" (emerald) and "CLOSED" (red). | E29: Backend IoT routes operational | F29: Passed | G29: 46264 | H29: VyVD | I29: Passed | J29: 46283 | K29: VyVD | L29: Passed | M29: 46304 | N29: VyVD
A30: TC-GATE-OVR-02 | B30: Autonomous Auto-Pilot Mode for VIP & Pre-booking vehicles | C30: 1. Toggle Auto-Pilot switch to ON. 2. Vehicle with Monthly Pass (isMonthly: true) or Pre-booking is scanned at entry lane. | D30: - Auto-pilot automatically calls handleEntryCheckIn(plate, verifyData) without staff manual click. - Opens barrier and logs transaction. | E30: Auto-Pilot toggle active, vehicle has valid subscription | F30: Passed | G30: 46265 | H30: VyVD | I30: Failed | J30: 46284 | K30: VyVD | L30: Passed | M30: 46305 | N30: VyVD | O30: Passed in R1, but in R2 autoPilot state was in closure stale state when interval re-rendered; fixed with functional state ref in R3
A31: TC-GATE-OVR-03 | B31: Auto-Pilot automatic zero-fee exit for monthly subscribers | C31: 1. Toggle Auto-Pilot to ON. 2. Scan exit vehicle with active subscription (totalAmount === 0). | D31: - lookupExitSession detects totalAmount === 0 and autoPilot === true. - Automatically dispatches handleExitCheckOut(data) and raises exit barrier. | E31: Monthly subscriber at exit gate with 0 VND balance due | F31: Passed | G31: 46266 | H31: VyVD | I31: Passed | J31: 46286 | K31: VyVD | L31: Passed | M31: 46306 | N31: VyVD
A32: TC-GATE-OVR-04 | B32: Telemetry polling and ESP32 bridge connection indicator | C32: 1. System runs setInterval(fetchBarrierStatus, 2000). 2. Simulate server/bridge offline. | D32: - When fetch fails, isEspOnline switches to false. - Header badge displays "DISCONNECTED" with red radio icon; displays "ONLINE (115200 BAUD)" with green pulse when connected. | E32: Staff dashboard open | F32: Passed | G32: 46266 | H32: VyVD | I32: Passed | J32: 46286 | K32: VyVD | L32: Passed | M32: 46306 | N32: VyVD

Sheet 3. IoT Barrier Integration
A2: Feature | B2: IoT Dual-Gate Barrier & ESP32 Integration | R2: Passed
A3: Test requirement | B3: To verify end-to-end hardware & firmware integration: ESP32 dual I2C LCD 1602 marquee displays, servo PWM timers, IR auto-calibration & anti-smash safety, 30s open timeout, Python serial bridge (115200 baud), and backend bidirectional synchronization. | R3: Failed
A4: Number of TCs | B4: =COUNTIF(A12:A42, "TC-*") -> 25 | R4: Pending
A5: Testing Round | B5: Passed | C5: Failed | D5: Pending | E5: N/A | R5: N/A
A6: Round 1 | B6: =COUNTIF(F11:F42, B5) -> 22 | C6: =COUNTIF(F11:F42, C5) -> 3 | D6: =COUNTIF(F11:F42, D5) -> 0 | E6: =COUNTIF(F11:F42, E5) -> 0
A7: Round 2 | B7: =COUNTIF(I11:I42, B5) -> 22 | C7: =COUNTIF(I11:I42, C5) -> 3 | D7: =COUNTIF(I11:I42, D5) -> 0 | E7: =COUNTIF(I11:I42, E5) -> 0
A8: Round 3 | B8: =COUNTIF(L11:L42, B5) -> 25 | C8: =COUNTIF(L11:L42, C5) -> 0 | D8: =COUNTIF(L11:L42, D5) -> 0 | E8: =COUNTIF(L11:L42, E5) -> 0
A10: Test Case ID | B10: Test Case Description | C10: Test Case Procedure | D10: Expected Results | E10: Pre-conditions | F10: Round 1 | G10: Test date | H10: Tester | I10: Round 2 | J10: Test date | K10: Tester | L10: Round 3 | M10: Test date | N10: Tester | O10: Note
A11: Function 1: ESP32 Boot, Power Brownout & Dual-Gate Self-Test
A12: TC-IOT-BOOT-01 | B12: Brownout detection disable and initial boot handshake | C12: 1. Power on ESP32 board via USB. 2. Verify RTC_CNTL_BROWN_OUT_REG is set to 0. 3. Monitor UART boot log at 115200 baud. | D12: - Prevents sudden reset loops caused by voltage drop during servo startup. - Serial monitor outputs "ESP32_BARRIER_READY" and header banner. | E12: ESP32 connected to USB port on host terminal | F12: Passed | G12: 46256 | H12: VyVD | I12: Passed | J12: 46273 | K12: VyVD | L12: Passed | M12: 46297 | N12: VyVD
A13: TC-IOT-BOOT-02 | B13: Hardware Self-Test sequence on power-up (0 -> 90 -> 0 degrees) | C13: 1. Connect ESP32 to power. 2. Observe entryGate.selfTest() and exitGate.selfTest() execution. | D13: - Entry servo smoothly sweeps 0 to 90 degrees (15ms delay per 5 deg), holds 600ms, sweeps back to 0 degrees. - Exit servo executes same self-test sequentially after 300ms pause. | E13: Servos attached to PIN 13 (Entry) and PIN 17 (Exit) | F13: Passed | G13: 46256 | H13: VyVD | I13: Passed | J13: 46273 | K13: VyVD | L13: Passed | M13: 46297 | N13: VyVD
A14: TC-IOT-BOOT-03 | B14: ESP32PWM 4-Timer hardware allocation stability | C14: 1. Verify ESP32PWM::allocateTimer(0..3) call in setup(). 2. Attach and sweep both servos simultaneously. | D14: - All 4 hardware timers allocated without PWM frequency clash (50Hz, 500-2400us pulse width). - Servo motors operate without jitter. | E14: ESP32Servo library initialized | F14: Passed | G14: 46257 | H14: VyVD | I14: Passed | J14: 46274 | K14: VyVD | L14: Passed | M14: 46298 | N14: VyVD
A15: Function 2: Dual Independent I2C Bus & LCD 1602 Safe Controllers
A16: TC-IOT-LCD-01 | B16: Independent Dual-I2C wire bus communication (Wire0 vs Wire1) | C16: 1. Initialize I2C_Entry on SDA 21, SCL 22 at 100kHz. 2. Initialize I2C_Exit on SDA 25, SCL 26 at 100kHz. 3. Send text commands to both LCDs. | D16: - Both LCD 1602 displays initialize independently at I2C address 0x27 without bus contention. - Entry and Exit screens display distinct text. | E16: Two separate 1602 LCD modules wired to designated GPIOs | F16: Passed | G16: 46258 | H16: VyVD | I16: Passed | J16: 46274 | K16: VyVD | L16: Passed | M16: 46298 | N16: VyVD
A17: TC-IOT-LCD-02 | B17: SafeI2CLCD disconnection recovery without ESP32 crash | C17: 1. Disconnect I2C SDA wire on Exit LCD while system is running. 2. Send print command through SafeI2CLCD class. | D17: - _wire->endTransmission() returns non-zero error. - _isAvailable flag switches to false. - Code bypasses I2C writes silently without locking I2C bus or freezing MCU. | E17: SafeI2CLCD wrapper active | F17: Failed | G17: 46258 | H17: VyVD | I17: Passed | J17: 46275 | K17: VyVD | L17: Passed | M17: 46299 | N17: VyVD | O17: Wire timeout lockup fixed in SafeI2CLCD error check in R2
A18: TC-IOT-LCD-03 | B18: 250ms Marquee text scrolling on LCD Row 2 | C18: 1. Assign message >16 chars: "WELCOME TO VALO PARKING - HAVE A GREAT DAY!". 2. Observe handleMarquee() over 10 seconds. | D18: - String automatically cycles charPos = (marqueeIndex + i) % msgLen every 250ms. - Text scrolls smoothly across 16-character window without flickering Row 1. | E18: LCD Row 1 static; Row 2 marquee active | F18: Passed | G18: 46259 | H18: VyVD | I18: Passed | J18: 46275 | K18: VyVD | L18: Passed | M18: 46299 | N18: VyVD
A19: TC-IOT-LCD-04 | B19: Display personalized assigned slot on Entry LCD | C19: 1. Send serial command: OPEN|51K-999.88|B2-04|ENTRY_1. 2. Inspect LCD display. | D19: - Line 1 renders: "VAO: 51K-999.88". - Row 2 marquee renders: "XIN CHAO! O DO CUA BAN LA: B2-04 - VUI LONG DO DUNG VI TRI - CHUC MOT NGAY TOT LANH!". | E19: Entry gate open command with slot code | F19: Passed | G19: 46259 | H19: VyVD | I19: Passed | J19: 46276 | K19: VyVD | L19: Passed | M19: 46300 | N19: VyVD
A20: Function 3: Infrared (IR) Sensor Auto-Calibration & Anti-Smash Logic
A21: TC-IOT-IR-01 | B21: Dynamic baseline auto-calibration (Ambient light compensation) | C21: 1. Barrier opens; system waits 800ms to settle mechanical vibration. 2. System reads sensorPin (PIN 19/27) to establish sensorBaseline. | D21: - Successfully samples ambient baseline (0 or 1) depending on active-low/high sensor type. - Detects obstacle when pinVal != sensorBaseline. | E21: IR sensor connected to PIN 19 (Entry) and PIN 27 (Exit) | F21: Passed | G21: 46260 | H21: VyVD | I21: Passed | J21: 46276 | K21: VyVD | L21: Passed | M21: 46300 | N21: VyVD
A22: TC-IOT-IR-02 | B22: Vehicle obstruction detection: Transition to GATE_CAR_UNDER | C22: 1. Barrier is in GATE_OPEN_WAITING state. 2. Vehicle drives under gate, breaking IR beam (pinVal != baseline). | D22: - State immediately transitions to GATE_CAR_UNDER. - Serial outputs: "DA CAT TIA HONG NGOAI: XE DANG QUA CONG!". - Barrier remains held at 90 degrees. | E22: Gate arm in raised 90-degree position | F22: Passed | G22: 46260 | H22: VyVD | I22: Passed | J22: 46277 | K22: VyVD | L22: Passed | M22: 46301 | N22: VyVD
A23: TC-IOT-IR-03 | B23: Anti-Smash protection: Indefinite hold while obstacle remains | C23: 1. Vehicle stops directly under gate, keeping IR beam blocked for 120 seconds. | D23: - clearDetectionStart counter is continuously reset to 0. - Barrier NEVER drops onto vehicle roof regardless of duration held. | E23: Obstacle continuously present in sensor beam | F23: Passed | G23: 46261 | H23: VyVD | I23: Passed | J23: 46277 | K23: VyVD | L23: Passed | M23: 46301 | N23: VyVD
A24: TC-IOT-IR-04 | B24: 80ms debounce filter when vehicle clears IR beam | C24: 1. Vehicle clears sensor beam. 2. Simulate momentary 30ms light reflection glitch. | D24: - System requires uninterrupted clear signal for >= 80ms before advancing to GATE_CAR_PASSED. - Prevents false departure triggers from flickering light. | E24: Vehicle exiting beam zone | F24: Passed | G24: 46261 | H24: VyVD | I24: Failed | J24: 46279 | K24: VyVD | L24: Passed | M24: 46301 | N24: VyVD | O24: Passed in R1, but in R2 reducing debounce from 80ms to 20ms caused fluttering close on truck trailers; reverted to 80ms in R3
A25: TC-IOT-IR-05 | B25: 1.0-second departure countdown and automatic gate lowering | C25: 1. State enters GATE_CAR_PASSED. 2. Keep sensor beam clear for 1000ms. | D25: - After 1000ms delay, system calls close(). - Servo sweeps 90 down to 0 degrees in 5-degree increments (15ms delay). - LCD displays "DANG DONG CONG" then returns to idle banner. | E25: Vehicle has fully cleared sensor beam | F25: Passed | G25: 46262 | H25: VyVD | I25: Passed | J25: 46279 | K25: VyVD | L25: Passed | M25: 46303 | N25: VyVD
A26: TC-IOT-IR-06 | B26: Safety re-open abort: Obstacle re-enters during 1s close countdown | C26: 1. Gate enters GATE_CAR_PASSED. 2. A pedestrian or trailing vehicle breaks IR beam at 500ms into countdown. | D26: - Immediate safety interrupt: reverts state back to GATE_CAR_UNDER. - Serial outputs: "CO VAT CAN TRO LAI -> GIU NGUYEN CONG MO AN TOAN!". - Barrier remains open at 90 degrees. | E26: Countdown timer running (carPassedAt < 1000ms) | F26: Passed | G26: 46262 | H26: VyVD | I26: Passed | J26: 46280 | K26: VyVD | L26: Passed | M26: 46303 | N26: VyVD
A27: TC-IOT-IR-07 | B27: 30-second unattended safety auto-close timeout | C27: 1. Open barrier for vehicle, but driver changes mind and does not enter (beam never broken). 2. Wait 30 seconds. | D27: - After millis() - barrierOpenedAt >= 30000, system triggers safety auto-close. - Serial logs: "HET 30S KHONG CO XE -> TU DONG DONG CONG AN TOAN!". | E27: Barrier open in GATE_OPEN_WAITING state without obstacle | F27: Passed | G27: 46263 | H27: VyVD | I27: Passed | J27: 46280 | K27: VyVD | L27: Passed | M27: 46304 | N27: VyVD
A28: Function 4: Serial Command Protocol Parsing (UART 115200)
A29: TC-IOT-PRT-01 | B29: Parse multi-parameter command: OPEN|plate|slot|gate | C29: 1. Transmit string: OPEN|29A-123.45|A-01|ENTRY_1 over UART. 2. Observe ESP32 token extraction. | D29: - Substring tokenization extracts plate: "29A-123.45", slot: "A-01", gate: "ENTRY_1". - Triggers entryGate.open() with designated slot text. | E29: Serial communication established at 115200 baud | F29: Passed | G29: 46263 | H29: VyVD | I29: Passed | J29: 46281 | K29: VyVD | L29: Passed | M29: 46304 | N29: VyVD
A30: TC-IOT-PRT-02 | B30: Parse standalone CHECKIN and CHECKOUT shorthand commands | C30: 1. Transmit "CHECKIN ". 2. Transmit "CHECKOUT ". | D30: - "CHECKIN" opens Entry gate with default greeting. - "CHECKOUT" opens Exit gate with default farewell message. | E30: ESP32 listening on loop() | F30: Passed | G30: 46264 | H30: VyVD | I30: Passed | J30: 46281 | K30: VyVD | L30: Passed | M30: 46305 | N30: VyVD
A31: TC-IOT-PRT-03 | B31: Parse PAUSE and RESUME maintenance commands | C31: 1. Transmit "PAUSE " or "HOLD ". 2. Inspect gateState. 3. Transmit "RESUME ". | D31: - PAUSE sets state to GATE_HOLD_MAINTENANCE, disables sensor checks, and renders LCD warning. - RESUME restores servo to previous position and reactivates sensor. | E31: Target gate operational | F31: Passed | G31: 46264 | H31: VyVD | I31: Passed | J31: 46283 | K31: VyVD | L31: Passed | M31: 46305 | N31: VyVD
A32: TC-IOT-PRT-04 | B32: Parse FORCE_CLOSE / CLOSE immediate shutdown command | C32: 1. Send "FORCE_CLOSE " while gate is in open or maintenance mode. | D32: - Immediately halts pending routines and lowers servo arm to 0 degrees. - Emits "GATE_CLOSED_GATE_NAME" and "GATE_CLOSED" via UART. | E32: Gate arm in open state | F32: Passed | G32: 46265 | H32: VyVD | I32: Passed | J32: 46283 | K32: VyVD | L32: Passed | M32: 46306 | N32: VyVD
A33: Function 5: Python Bridge Port Discovery, Resiliency & Concurrency
A34: TC-IOT-BRG-01 | B34: Auto-discover ESP32 USB device descriptor in Python Bridge | C34: 1. Connect ESP32 using CH340 or CP210 USB cable. 2. Execute find_esp32_port(). | D34: - serial.tools.list_ports matches device string and returns active COM/tty port without manual user configuration. | E34: Host computer running iot_barrier_bridge.py | F34: Passed | G34: 46266 | H34: VyVD | I34: Passed | J34: 46284 | K34: VyVD | L34: Passed | M34: 46306 | N34: VyVD
A35: TC-IOT-BRG-02 | B35: Automatic UART reconnection loop upon USB cable pull | C35: 1. Disconnect ESP32 USB cable while bridge is actively polling. 2. Reconnect USB cable after 5 seconds. | D35: - Catches SerialException / OSError. - Enters 2-second reconnect loop without terminating process. - Automatically re-establishes connection and resets buffers. | E35: Python bridge running | F35: Failed | G35: 46266 | H35: VyVD | I35: Passed | J35: 46284 | K35: VyVD | L35: Passed | M35: 46307 | N35: VyVD | O35: Unhandled Bad file descriptor crash on macOS fixed in R2
A36: TC-IOT-BRG-03 | B36: Independent dual-gate trigger dispatch in single polling cycle | C36: 1. Update triggerId on both ENTRY_1 and EXIT_1 in backend within same 300ms cycle. 2. Observe serial transmission order. | D36: - Bridge iterates gates dictionary and serializes commands for both gates sequentially. - Both gates actuate without dropping packets. | E36: Both gates triggered simultaneously | F36: Passed | G36: 46267 | H36: VyVD | I36: Failed | J36: 46286 | K36: VyVD | L36: Passed | M36: 46307 | N36: VyVD | O36: Passed in R1, but in R2 last_trigger_ids dictionary shallow copy caused race condition in concurrent updates; fixed in R3
A37: TC-IOT-BRG-04 | B37: Bridge resilience during temporary backend server crash / restart | C37: 1. Stop NodeJS backend for 20 seconds while bridge is active. 2. Restart NodeJS backend. | D37: - Requests exception is caught silently. - Bridge continues serial monitoring and resumes synchronization upon server recovery. | E37: Backend server stopped | F37: Passed | G37: 46267 | H37: VyVD | I37: Passed | J37: 46287 | K37: VyVD | L37: Passed | M37: 46308 | N37: VyVD
A38: Function 6: Bidirectional Hardware-to-Backend State Synchronization
A39: TC-IOT-SYN-01 | B39: Sync Entry Gate closure from ESP32 to Backend /api/iot/close-barrier | C39: 1. Car clears Entry sensor; ESP32 closes gate and prints "GATE_CLOSED_ENTRY_1". 2. Bridge receives serial string. | D39: - Bridge posts to BACKEND_CLOSE_URL with fromBridge=true and gate='ENTRY_1'. - Backend updates ENTRY_1 state.open = false and emits Socket.io event. | E39: Vehicle finished entry pass | F39: Passed | G39: 46268 | H39: VyVD | I39: Passed | J39: 46288 | K39: VyVD | L39: Passed | M39: 46308 | N39: VyVD
A40: TC-IOT-SYN-02 | B40: Sync Exit Gate closure from ESP32 to Backend /api/iot/close-barrier | C40: 1. Car clears Exit sensor; ESP32 closes gate and prints "GATE_CLOSED_EXIT_1". 2. Bridge receives serial string. | D40: - Bridge posts to BACKEND_CLOSE_URL with fromBridge=true and gate='EXIT_1'. - Updates last_trigger_ids['EXIT_1'] with backend response to prevent trigger loop. | E40: Vehicle finished exit pass | F40: Passed | G40: 46268 | H40: VyVD | I40: Passed | J40: 46288 | K40: VyVD | L40: Passed | M40: 46309 | N40: VyVD
A41: TC-IOT-SYN-03 | B41: Initial triggerId synchronization on bridge startup | C41: 1. Start Python bridge while backend already has an active open barrier. 2. Inspect last_trigger_ids initialization. | D41: - If gate should_open on startup, sets last_trigger_ids to -1 to force immediate open command dispatch. - If gate closed, sets last_trigger_ids to current triggerId to avoid duplicate firing. | E41: Backend has active trigger before bridge launches | F41: Failed | G41: 46269 | H41: VyVD | I41: Failed | J41: 46289 | K41: VyVD | L41: Passed | M41: 46309 | N41: VyVD | O41: Initial triggerId=0 caused missed barrier open on bridge startup; resolved in R3 with -1 seed

Sheet 4. IoT QR Code & Scanner
A2: Feature | B2: IoT QR Scanner & Security Verification | R2: Passed
A3: Test requirement | B3: To verify end-to-end QR code scanner hardware and cryptographic verification: GM65 USB HID keyboard scanner listener (rapid keystroke buffer <400ms, debounce 350ms, Enter termination), camera video stream QR scanner fallback, HMAC-SHA256 signature validation (5-minute expiration, one-time use), multi-payload resolution (JWT, MongoDB ObjectId, JSON, Plate string), and AI camera plate cross-check matching. | R3: Failed
A4: Number of TCs | B4: =COUNTIF(A12:A36, "TC-*") -> 20 | R4: Pending
A5: Testing Round | B5: Passed | C5: Failed | D5: Pending | E5: N/A | R5: N/A
A6: Round 1 | B6: =COUNTIF(F11:F36, B5) -> 18 | C6: =COUNTIF(F11:F36, C5) -> 2 | D6: =COUNTIF(F11:F36, D5) -> 0 | E6: =COUNTIF(F11:F36, E5) -> 0
A7: Round 2 | B7: =COUNTIF(I11:I36, B5) -> 17 | C7: =COUNTIF(I11:I36, C5) -> 3 | D7: =COUNTIF(I11:I36, D5) -> 0 | E7: =COUNTIF(I11:I36, E5) -> 0
A8: Round 3 | B8: =COUNTIF(L11:L36, B5) -> 20 | C8: =COUNTIF(L11:L36, C5) -> 0 | D8: =COUNTIF(L11:L36, D5) -> 0 | E8: =COUNTIF(L11:L36, E5) -> 0
A10: Test Case ID | B10: Test Case Description | C10: Test Case Procedure | D10: Expected Results | E10: Pre-conditions | F10: Round 1 | G10: Test date | H10: Tester | I10: Round 2 | J10: Test date | K10: Tester | L10: Round 3 | M10: Test date | N10: Tester | O10: Note
A11: Function 1: GM65 Hardware Barcode/QR Scanner (USB HID Keyboard Hook)
A12: TC-QR-HW-01 | B12: GM65 rapid keystroke buffer capture (<400ms interval) | C12: 1. Scan physical QR code with GM65 barcode/QR scanner module. 2. Hook useQrScannerListener intercepts window keydown events. 3. Verify keystroke interval. | D12: - Scanner emits characters rapidly (<50ms per key). - All characters accumulate in bufferRef without loss. - Prevents buffer clearing when timeDiff <= MAX_INTERVAL_MS (400ms). | E12: GM65 hardware scanner connected via USB in HID POS Keyboard mode | F12: Passed | G12: 46257 | H12: VyVD | I12: Passed | J12: 46273 | K12: VyVD | L12: Passed | M12: 46297 | N12: VyVD
A13: TC-QR-HW-02 | B13: Hardware scanner Enter / Tab key immediate trigger | C13: 1. GM65 scans QR string and appends suffix Enter key code (0x0D). 2. Listen for event.key === "Enter". | D13: - Detects Enter key, prevents default form submit action via event.preventDefault(). - Triggers triggerScan() immediately without waiting for debounce timer. | E13: QR scanner listener hook enabled | F13: Passed | G13: 46257 | H13: VyVD | I13: Passed | J13: 46273 | K13: VyVD | L13: Passed | M13: 46297 | N13: VyVD
A14: TC-QR-HW-03 | B14: Ignore human slow manual keyboard typing | C14: 1. User types characters manually with key interval > 400ms on terminal keyboard. 2. Check bufferRef. | D14: - timeDiff exceeds MAX_INTERVAL_MS (400ms). - Buffer resets automatically. - Does not trigger false positive QR scan on human typing. | E14: Application focused on text input | F14: Passed | G14: 46258 | H14: VyVD | I14: Passed | J14: 46274 | K14: VyVD | L14: Passed | M14: 46298 | N14: VyVD
A15: TC-QR-HW-04 | B15: Fallback 350ms debounce auto-trigger without trailing Enter | C15: 1. Configure scanner to omit carriage return Enter. 2. Scan QR string >= 8 characters. | D15: - Buffer accumulates >= 8 chars. - 350ms debounceTimer fires triggerScan() automatically upon silence. - Logs: "[GM65 Scanner] Full QR Received". | E15: Scanner configured in non-Enter suffix mode | F15: Failed | G15: 46258 | H15: VyVD | I15: Passed | J15: 46274 | K15: VyVD | L15: Passed | M15: 46298 | N15: VyVD | O15: Timer cancellation race condition fixed in R2
A16: TC-QR-HW-05 | B16: Filter modifier keys (Shift, Control, Alt, Meta, CapsLock) | C16: 1. Press Shift + character or CapsLock while scanning. 2. Inspect handleKeyDown evaluation. | D16: - Modifier keys are filtered out without appending text or corrupting the scanner payload string. | E16: Keyboard event listener active | F16: Passed | G16: 46259 | H16: VyVD | I16: Passed | J16: 46275 | K16: VyVD | L16: Passed | M16: 46299 | N16: VyVD
A17: Function 2: Camera Video Stream QR Scanner Fallback (Software Decoder)
A18: TC-QR-CAM-01 | B18: Open KioskQrScannerModal with camera user-facing constraint | C18: 1. Driver clicks "Scan VIP / Booking QR" on touchscreen. 2. Modal renders with Scanner component from @yudiel/react-qr-scanner. | D18: - Modal displays corner brackets overlay with #FFDF00 border styling. - Video stream initializes with scanDelay={300} and facingMode: "user". | E18: Front-facing camera permission available | F18: Passed | G18: 46260 | H18: VyVD | I18: Passed | J18: 46276 | K18: VyVD | L18: Passed | M18: 46300 | N18: VyVD
A19: TC-QR-CAM-02 | B19: Camera permission denial error handling (NotAllowedError) | C19: 1. Deny browser camera permission prompt. 2. Attempt to open scanner modal. | D19: - handleError catches error.name === "NotAllowedError". - Alerts: "Camera access denied! Please allow camera access in your browser settings.". - UI does not crash. | E19: Camera permission set to Block | F19: Passed | G19: 46260 | H19: VyVD | I19: Passed | J19: 46276 | K19: VyVD | L19: Passed | M19: 46300 | N19: VyVD
A20: TC-QR-CAM-03 | B20: Software QR code extraction from live video feed | C20: 1. Present QR code in front of camera lens. 2. Component decodes rawValue at result[0].rawValue. | D20: - Calls handleScan(result) and invokes onScan callback with decoded payload string. - Closes modal automatically upon successful capture. | E20: KioskQrScannerModal open and camera streaming | F20: Passed | G20: 46261 | H20: VyVD | I20: Failed | J20: 46277 | K20: VyVD | L20: Passed | M20: 46301 | N20: VyVD | O20: Passed in R1, but in R2 updating react-qr-scanner package altered result array schema; fixed in R3
A21: Function 3: HMAC-SHA256 Cryptographic Token Security & Anti-Replay
A22: TC-QR-SEC-01 | B22: Generate secure dynamic QR token with HMAC-SHA256 signature | C22: 1. Customer requests QR via POST /api/qr/generate. 2. Server creates 16-byte random token, expireTime (Date.now + 5 mins), and HMAC-SHA256 signature. | D22: - Server saves record in QrToken collection. - Returns userId, token, expireTime, and valid hex signature. - Status 200 OK. | E22: Customer authenticated with valid JWT token | F22: Passed | G22: 46262 | H22: VyVD | I22: Passed | J22: 46279 | K22: VyVD | L22: Passed | M22: 46301 | N22: VyVD
A23: TC-QR-SEC-02 | B23: Validate tamper-proof HMAC-SHA256 signature at Kiosk | C23: 1. Send POST /api/qr/verify with altered userId or manipulated token. | D23: - Server re-computes generateSignature(userId, token, expireTime). - Signature mismatch detected. - Returns status 400: "Signature is invalid, tampering detected". | E23: QR verification endpoint accessible | F23: Passed | G23: 46262 | H23: VyVD | I23: Passed | J23: 46279 | K23: VyVD | L23: Passed | M23: 46303 | N23: VyVD
A24: TC-QR-SEC-03 | B24: Reject expired dynamic QR code (> 5 minutes validity window) | C24: 1. Wait 5 minutes 1 second after QR generation. 2. Scan QR token at Kiosk. | D24: - Server checks Date.now() > Number(expireTime). - Rejects with status 400: "QR code has expired (5-minute limit)". - Barrier remains closed. | E24: QR code generated > 5 mins ago | F24: Passed | G24: 46263 | H24: VyVD | I24: Passed | J24: 46280 | K24: VyVD | L24: Passed | M24: 46303 | N24: VyVD
A25: TC-QR-SEC-04 | B25: Anti-Replay Attack: Enforce single-use dynamic QR token in DB | C25: 1. Scan valid dynamic QR code at Entry gate (qrRecord.used = true). 2. Attempt to scan the exact same QR code a second time. | D25: - Server queries QrToken.findOne({ userId, token }). - Detects qrRecord.used === true. - Returns status 400: "This QR code has already been used". | E25: QR token previously verified once | F25: Failed | G25: 46263 | H25: VyVD | I25: Failed | J25: 46281 | K25: VyVD | L25: Passed | M25: 46304 | N25: VyVD | O25: Database concurrency race condition allowed duplicate scan within 100ms in R1 & R2; resolved with atomic findOneAndUpdate in R3
A26: Function 4: Multi-Format Payload Resolver (/api/sessions/kiosk-verify-qr)
A27: TC-QR-RES-01 | B27: Resolve encrypted JWT / FastPass Token payload | C27: 1. Scan QR containing signed JWT token (header.payload.signature). 2. Send to /api/sessions/kiosk-verify-qr. 3. Server verifies token via jwt.verify(). | D27: - Decodes bookingId, subscriptionId, or licensePlate. - Returns resolved type: "BOOKING" or "MEMBERSHIP" with assignedSlot and floorId. | E27: Valid FastPass QR token issued to customer | F27: Passed | G27: 46264 | H27: VyVD | I27: Passed | J27: 46283 | K27: VyVD | L27: Passed | M27: 46304 | N27: VyVD
A28: TC-QR-RES-02 | B28: Resolve direct 24-character hexadecimal MongoDB ObjectId | C28: 1. Scan ticket containing raw 24-hex ObjectId. 2. Server checks mongoose.Types.ObjectId.isValid(trimmedPayload). 3. Queries Booking, Subscription, User, and Session in sequence. | D28: - Successfully resolves booking details if valid booking ID. - Resolves active entitlement slotCode if subscription ID. - Resolves session plate if check-in session ID. | E28: Target entity exists in MongoDB database | F28: Passed | G28: 46265 | H28: VyVD | I28: Passed | J28: 46284 | K28: VyVD | L28: Passed | M28: 46305 | N28: VyVD
A29: TC-QR-RES-03 | B29: Resolve serialized JSON string payload with bookingId or licensePlate | C29: 1. Scan QR with payload: {"bookingId":"64f1a2b...","licensePlate":"51G-888.88"}. 2. Server parses JSON. | D29: - Safely parses JSON string. - Extracts bookingId and licensePlate. - Populates vehicle and slot allocation data. | E29: Valid JSON formatted QR code | F29: Passed | G29: 46265 | H29: VyVD | I29: Passed | J29: 46284 | K29: VyVD | L29: Passed | M29: 46305 | N29: VyVD
A30: TC-QR-RES-04 | B30: Resolve raw vehicle license plate string (6 to 12 chars) | C30: 1. Scan QR containing plain plate string "51K-999.88". 2. Server checks cleanPlate.length >= 6 && cleanPlate.length <= 12. | D30: - Resolves type: "PLATE" with licensePlate: "51K-999.88". - Formats plate display and passes to check-in flow. | E30: Standard Vietnamese vehicle plate string in QR | F30: Passed | G30: 46266 | H30: VyVD | I30: Passed | J30: 46286 | K30: VyVD | L30: Passed | M30: 46306 | N30: VyVD
A31: TC-QR-RES-05 | B31: Reject unknown foreign QR codes not belonging to Valo Parking | C31: 1. Scan a personal vCard, Wi-Fi configuration, or foreign URL QR code at Kiosk. | D31: - Fails all 5 resolution parsers (JWT, ObjectId, JSON, Plate). - Returns status 400: "QR code does not belong to Valo Parking system". | E31: Foreign QR code scanned | F31: Passed | G31: 46266 | H31: VyVD | I31: Passed | J31: 46286 | K31: VyVD | L31: Passed | M31: 46306 | N31: VyVD
A32: Function 5: AI Camera Cross-Check & Plate Mismatch Security Verification
A33: TC-QR-CHK-01 | B33: Automated cross-check: QR plate matches AI camera detected plate | C33: 1. Present FastPass QR for "51K-999.88". 2. Camera sends entryImageBase64 to AI Service (/scan). 3. AI extracts detectedPlate: "51K-999.88". 4. Execute arePlatesMatching(). | D33: - isPlateMatched returns true, hasDetectedPlate returns true. - Returns status 200 OK and proceeds with automated check-in and barrier trigger. | E33: Vehicle license plate matches QR registration | F33: Passed | G33: 46267 | H33: VyVD | I33: Passed | J33: 46287 | K33: VyVD | L33: Passed | M33: 46307 | N33: VyVD
A34: TC-QR-CHK-02 | B34: Plate mismatch detection: Security fraud prevention | C34: 1. Driver holds FastPass QR for plate "51K-999.88", but drives different car "59B-123.45". 2. AI detects mismatch. | D34: - isPlateMatched returns false. - mismatchReason returns: "Actual vehicle plate does not match QR registration info!". - Kiosk opens PlateMismatchModal and refuses entry. | E34: Vehicle plate differs from QR code | F34: Passed | G34: 46267 | H34: VyVD | I34: Passed | J34: 46287 | K34: VyVD | L34: Passed | M34: 46307 | N34: VyVD
A35: TC-QR-CHK-03 | B35: Missing vehicle plate in front of camera during QR scan | C35: 1. User scans QR code but standing alone without vehicle in camera view (entryImageBase64 has no plate). 2. AI returns no detected plate. | D35: - hasDetectedPlate returns false, isPlateMatched returns false. - mismatchReason: "No license plate detected in front of camera! Please stop vehicle in lane and rescan.". | E35: No vehicle in camera lane | F35: Passed | G35: 46268 | H35: VyVD | I35: Failed | J35: 46288 | K35: VyVD | L35: Passed | M35: 46308 | N35: VyVD | O35: Passed in R1, but in R2 empty detectedPlate condition bypassed mismatchReason null check; fixed in R3

Sheet 5. AI Slot Surveillance & ALPR
A2: Feature | B2: AI Smart Parking Slot Surveillance & Deep Vision ALPR | R2: Passed
A3: Test requirement | B3: Comprehensive end-to-end testing of autonomous parking lot computer vision: YOLOv8-Seg polygon segmentation (27 slanted perspective slots), offline EasyOCR, Gemini 2.5 Flash hybrid fusion, camera misalignment scene validation, diorama plate normalization, 1080p full-res letterboxing compensation, auto-detect floor grid, audio siren alert, 8s background polling, and 1-Click Fast Reassign violation recovery. | R3: Failed
A4: Number of TCs | B4: =COUNTIF(A12:A52, "TC-*") -> 31 | R4: Pending
A5: Testing Round | B5: Passed | C5: Failed | D5: Pending | E5: N/A | R5: N/A
A6: Round 1 | B6: =COUNTIF(F11:F52, B5) -> 30 | C6: =COUNTIF(F11:F52, C5) -> 1 | D6: =COUNTIF(F11:F52, D5) -> 0 | E6: =COUNTIF(F11:F52, E5) -> 0
A7: Round 2 | B7: =COUNTIF(I11:I52, B5) -> 28 | C7: =COUNTIF(I11:I52, C5) -> 3 | D7: =COUNTIF(I11:I52, D5) -> 0 | E7: =COUNTIF(I11:I52, E5) -> 0
A8: Round 3 | B8: =COUNTIF(L11:L52, B5) -> 31 | C8: =COUNTIF(L11:L52, C5) -> 0 | D8: =COUNTIF(L11:L52, D5) -> 0 | E8: =COUNTIF(L11:L52, E5) -> 0
A10: Test Case ID | B10: Test Case Description | C10: Test Case Procedure | D10: Expected Results | E10: Pre-conditions | F10: Round 1 | G10: Test date | H10: Tester | I10: Round 2 | J10: Test date | K10: Tester | L10: Round 3 | M10: Test date | N10: Tester | O10: Note
A11: Function 1: Overhead Surveillance Camera Device Selection & Memory
A12: TC-AI-DEV-01 | B12: Enumerate video devices and auto-prioritize external USB webcam | C12: 1. Connect Logitech C270 / USB webcam to Mac/PC. 2. Open SlotCameraMonitorModal. 3. Verify loadCameras() selection. | D12: - Filters out built-in "facetime" camera. - Automatically selects external USB camera deviceId and persists in localStorage (valo_selected_camera_id). | E12: External USB webcam connected to system | F12: Passed | G12: 46258 | H12: VyVD | I12: Passed | J12: 46273 | K12: VyVD | L12: Passed | M12: 46297 | N12: VyVD
A13: TC-AI-DEV-02 | B13: 1080p FHD resolution constraints with 720p fallback | C13: 1. Request camera stream with ideal width: 1920, height: 1080, min: 1280x720. 2. Verify videoRef track settings. | D13: - Video stream acquires 1080p at 30fps if camera supports FHD; falls back cleanly to 720p on entry-level cameras without throwing errors. | E13: Camera supports at least 720p resolution | F13: Passed | G13: 46258 | H13: VyVD | I13: Passed | J13: 46273 | K13: VyVD | L13: Passed | M13: 46297 | N13: VyVD
A14: Function 2: YOLOv8-Seg Physical Slanted Slot Segmentation (27 Polygons)
A15: TC-AI-YOLO-01 | B15: Segment 27 physical slanted parking slot polygons (r0=10, r1=7, r2=10) | C15: 1. Transmit overhead frame to /scan-slots. 2. YOLOv8-Seg model parking_slots_yolo.pt extracts bounding polygons. | D15: - Identifies 27 distinct slanted parking slot contours. - Groups into 3 physical rows: Row 0 has 10 slots, Row 1 has 7 slots, Row 2 has 10 slots. - Model inference completes in <1.5s. | E15: YOLOv8-Seg model active on port 8000 | F15: Passed | G15: 46259 | H15: VyVD | I15: Passed | J15: 46274 | K15: VyVD | L15: Passed | M15: 46298 | N15: VyVD
A16: TC-AI-YOLO-02 | B16: Auto-calibrate canvas slot contours from detected physical polygons | C16: 1. Receive calibratedSlots array from AI scan response. 2. Update slotRois state in monitor modal. | D16: - Updates canvas polygons to match real physical vehicle stall markings. - Automatically caches updated polygon matrix to localStorage (valo_slot_roi_floor_ID). | E16: Valid response received from /scan-slots | F16: Passed | G16: 46259 | H16: VyVD | I16: Passed | J16: 46274 | K16: VyVD | L16: Passed | M16: 46298 | N16: VyVD
A17: Function 3: 4-Corner Bilinear Perspective Interpolation & Grid Alignment
A18: TC-AI-GRID-01 | B18: Bilinear interpolation coordinate mapping from 4 board corner points | C18: 1. Position corner anchors [TL, TR, BR, BL] around parking floor board. 2. Execute generateSlotsFromCorners(). | D18: - Bilinear algorithm calculates perspective quadrilateral for each slot based on normalized (u, v) space. - Corrects optical keystone angle distortion. | E18: Staff calibration tool opened in modal | F18: Passed | G18: 46260 | H18: VyVD | I18: Passed | J18: 46275 | K18: VyVD | L18: Passed | M18: 46299 | N18: VyVD
A19: TC-AI-GRID-02 | B19: Global Move and Global Scale transformation of all 27 slots | C19: 1. Click arrow buttons (Left, Right, Up, Down) to execute handleGlobalMove(dx, dy). 2. Click Zoom In / Zoom Out (handleGlobalScale). | D19: - Moves all 27 polygons synchronously by delta offset without shape distortion. - Scales all slot boxes relative to board center centroid point. | E19: Board corners defined | F19: Passed | G19: 46260 | H19: VyVD | I19: Passed | J19: 46275 | K19: VyVD | L19: Passed | M19: 46299 | N19: VyVD
A20: TC-AI-GRID-03 | B20: Independent width and height slot dimension scaling (scale.x, scale.y) | C20: 1. Adjust Width Scale (+/- 5%) and Height Scale (+/- 5%). 2. Call handleSlotDimensionScale(factorX, factorY). | D20: - Expands or shrinks bounding box margins to eliminate slot bleeding into adjacent parking spaces. - Values clamped safely between 0.5x and 1.8x. | E20: Calibration controls panel expanded | F20: Passed | G20: 46261 | H20: VyVD | I20: Failed | J20: 46276 | K20: VyVD | L20: Passed | M20: 46299 | N20: VyVD | O20: Passed in R1, but in R2 scale factor floating point rounding caused polygon vertex distortion; fixed with toFixed(3) in R3
A21: TC-AI-GRID-04 | B21: AI Auto-Detect Floor Grid calling /api/ai/auto-detect-grid | C21: 1. Click "Auto Align Grid" button with magic wand icon. 2. Capture full-resolution frame and submit to backend. | D21: - Backend analyzes camera view, locates parking perimeter, and returns 4 corners. - Automatically re-aligns all 27 slot polygons in <2 seconds. | E21: Overhead camera frame active | F21: Passed | G21: 46261 | H21: VyVD | I21: Passed | J21: 46276 | K21: VyVD | L21: Passed | M21: 46299 | N21: VyVD
A22: Function 4: Local Edge ALPR & Cropped ROI OCR Execution (0 Token, Offline)
A23: TC-AI-OCR-01 | B23: Crop individual slot bounding boxes and run offline EasyOCR | C23: 1. Vehicle card placed in Slot A3 (plate: 13C-343.21). 2. Edge AI crops polygon ROI. 3. Runs EasyOCR engine on CPU/MPS. | D23: - Extracts license plate characters locally without internet or cloud tokens. - Reports confidence Conf=0.92. - Total scan time < 7.8s for 27 slots. | E23: Local Python AI service running | F23: Passed | G23: 46262 | H23: VyVD | I23: Passed | J23: 46277 | K23: VyVD | L23: Passed | M23: 46300 | N23: VyVD
A24: TC-AI-OCR-02 | B24: Optical background hash caching for unchanged empty slots | C24: 1. Run continuous scanning loop over static scene. 2. Observe log: "27 slots, 17 OCRd, 10 cached". | D24: - Computes structural hash of slot pixel region. - Bypasses EasyOCR for empty unchanged slots, saving >45% CPU cycles per cycle. | E24: Continuous scanning active | F24: Passed | G24: 46262 | H24: VyVD | I24: Failed | J24: 46277 | K24: VyVD | L24: Passed | M24: 46300 | N24: VyVD | O24: Passed in R1, but in R2 hash threshold was too strict causing vehicle departures to be missed; recalibrated in R3
A25: TC-AI-OCR-03 | B25: Filter painted floor numbers and OCR noise strings | C25: 1. Scan empty parking slots with painted numbers on ground (E1..E10, F1..F7, H1..H5). 2. Filter through ALL_SLOT_CODES set. | D25: - Discards painted floor labels and UI keywords (CHUA, CHECKIN, CKIN, VAOO, CANHBAO). - Prevents false positive "Occupied" triggers on empty painted slots. | E25: Painted numbers present in slot area | F25: Passed | G25: 46263 | H25: VyVD | I25: Passed | J25: 46279 | K25: VyVD | L25: Passed | M25: 46301 | N25: VyVD
A26: Function 5: Hybrid Multimodal Fusion Trigger with Gemini 2.5 Flash
A27: TC-AI-HYB-01 | B27: Hybrid trigger activation on incomplete local edge read | C27: 1. Dim ambient lighting or cast severe shadow over rear slot row. 2. Local AI detects <80% of occupied vehicles. | D27: - Backend logs: "[AI Slot Scan] Hybrid trigger: Incomplete local read. Fusing with Gemini 2.5 Flash Vision...". - Calls Gemini 2.5 Flash API seamlessly. | E27: GEMINI_API_KEY configured in backend .env | F27: Passed | G27: 46263 | H27: VyVD | I27: Passed | J27: 46279 | K27: VyVD | L27: Passed | M27: 46301 | N27: VyVD
A28: TC-AI-HYB-02 | B28: Gemini 2.5 Flash concurrent extraction across all 27 slots | C28: 1. Transmit 1080p surveillance image to Gemini 2.5 Flash. 2. Prompt requests structured JSON for all 27 slots. | D28: - Gemini returns JSON array for all 27 slots simultaneously. - Identifies occupied status, plate numbers, vehicle types (car/ev/moto), and visual confidence. | E28: Gemini multimodal model responsive | F28: Passed | G28: 46264 | H28: VyVD | I28: Passed | J28: 46280 | K28: VyVD | L28: Passed | M28: 46303 | N28: VyVD
A29: TC-AI-HYB-03 | B29: Handle Gemini API 429 Quota Exceeded error with local fallback | C29: 1. Simulate rate limit / quota exhaustion (HTTP 429) on Gemini API. 2. Check isQuotaError() handling. | D29: - Backend catches error, extracts retry-after delay seconds. - Seamlessly falls back to local edge AI results without returning 500 error to user. | E29: Gemini API key quota depleted | F29: Failed | G29: 46264 | H29: VyVD | I29: Failed | J29: 46280 | K29: VyVD | L29: Passed | M29: 46303 | N29: VyVD | O29: Fallback response object structure was malformed in R1 & R2; resolved in R3 build
A30: Function 6: Camera Misalignment & Scene Validation Engine
A31: TC-AI-SCN-01 | B31: Detect displaced camera facing user face or room environment | C31: 1. Turn camera away from parking floor towards user face or office ceiling. 2. Trigger scan. | D31: - Backend detects isCameraMisaligned: true. - Returns warning: "Camera is facing user face or room environment instead of the parking lot!". - Suppresses false slot updates. | E31: Camera pointing at invalid scene | F31: Passed | G31: 46265 | H31: VyVD | I31: Passed | J31: 46281 | K31: VyVD | L31: Passed | M31: 46303 | N31: VyVD
A32: TC-AI-SCN-02 | B32: Audio warning and visual warning banner on misaligned scene | C32: 1. When isCameraMisaligned is received from backend. 2. Verify modal UI reaction. | D32: - Modal displays bright yellow warning banner across top of video feed. - Clears false slot overlays and triggers alert sound tone. | E32: Monitor modal active | F32: Passed | G32: 46265 | H32: VyVD | I32: Passed | J32: 46281 | K32: VyVD | L32: Passed | M32: 46304 | N32: VyVD
A33: Function 7: Smart Plate Normalization & Diorama Test Card Normalization
A34: TC-AI-NORM-01 | B34: Auto-correct blurry plate for Floor 1 Slot A3 (13C-343.21) | C34: 1. Supply OCR fragments: "34321", "I3C343", or "13C". 2. Call cleanAndNormalizePlate(). | D34: - Maps blurry optical character confusion to standard format: "13C-343.21". - Backend logs: "[AI Smart Inference] Auto-corrected blurry plate 13C-343.21". | E34: Test card placed in Slot A3 | F34: Passed | G34: 46266 | H34: VyVD | I34: Passed | J34: 46283 | K34: VyVD | L34: Passed | M34: 46304 | N34: VyVD
A35: TC-AI-NORM-02 | B35: Auto-correct blurry plate for Floor 1 Slot B1 (43B-204.04) | C35: 1. Supply OCR fragments: "438204", "20404", or "43D". 2. Call cleanAndNormalizePlate(). | D35: - Corrects 8-to-B confusion and returns clean plate: "43B-204.04". | E35: Test card placed in Slot B1 | F35: Passed | G35: 46266 | H35: VyVD | I35: Passed | J35: 46283 | K35: VyVD | L35: Passed | M35: 46304 | N35: VyVD
A36: TC-AI-NORM-03 | B36: Auto-correct blurry plate for Floor 1 Slot C4 (19H-438.99) | C36: 1. Supply OCR fragments: "43899", "49890", or "19H". 2. Call cleanAndNormalizePlate(). | D36: - Corrects 498-to-438 distortion and returns clean plate: "19H-438.99". | E36: Test card placed in Slot C4 | F36: Passed | G36: 46267 | H36: VyVD | I36: Passed | J36: 46284 | K36: VyVD | L36: Passed | M36: 46305 | N36: VyVD
A37: TC-AI-NORM-04 | B37: Auto-correct blurry plate for Floor 2 Slot E4 (55H-443.23) | C37: 1. Supply OCR fragments: "SSH443", "5514412", or "SOH". 2. Call cleanAndNormalizePlate(). | D37: - Corrects S-to-5 and 1-to-H distortion and returns clean plate: "55H-443.23". | E37: Test card placed in Slot E4 | F37: Passed | G37: 46267 | H37: VyVD | I37: Passed | J37: 46284 | K37: VyVD | L37: Passed | M37: 46305 | N37: VyVD
A38: TC-AI-NORM-05 | B38: Auto-correct blurry plate for Floor 2 Slot E9 (99C-643.99) | C38: 1. Supply OCR fragments: "64399", "43199", or "19C643". 2. Call cleanAndNormalizePlate(). | D38: - Corrects 19-to-99 distortion and returns clean plate: "99C-643.99". | E38: Test card placed in Slot E9 | F38: Passed | G38: 46267 | H38: VyVD | I38: Passed | J38: 46284 | K38: VyVD | L38: Passed | M38: 46305 | N38: VyVD
A39: TC-AI-NORM-06 | B39: Auto-correct blurry plate for Floor 2 Slot F4 (90A-280.96) | C39: 1. Supply OCR fragments: "28096", "SOA280", or "22096". 2. Call cleanAndNormalizePlate(). | D39: - Corrects S-to-9 and 22-to-90 optical noise and returns clean plate: "90A-280.96". | E39: Test card placed in Slot F4 | F39: Passed | G39: 46268 | H39: VyVD | I39: Passed | J39: 46286 | K39: VyVD | L39: Passed | M39: 46306 | N39: VyVD
A40: TC-AI-NORM-07 | B40: Auto-correct blurry plate for Floor 2 Slot H2 (22B-123.45) | C40: 1. Supply OCR fragments: "12345", "22B123", "41145", or "22813345". 2. Call cleanAndNormalizePlate(). | D40: - Returns clean plate: "22B-123.45". | E40: Test card placed in Slot H2 | F40: Passed | G40: 46268 | H40: VyVD | I40: Passed | J40: 46286 | K40: VyVD | L40: Passed | M40: 46306 | N40: VyVD
A41: TC-AI-NORM-08 | B41: Standard Vietnamese 5-digit (3+2 dot) and 4-digit plate regex parser | C41: 1. Pass raw strings "51F88899" and "29A1234" to general regex parser. | D41: - 5-digit regex formats to: "51F-888.99". - 4-digit regex formats to: "29A-1234". | E41: General alphanumeric plate input | F41: Passed | G41: 46268 | H41: VyVD | I41: Passed | J41: 46286 | K41: VyVD | L41: Passed | M41: 46306 | N41: VyVD
A42: Function 8: Precise Video Letterboxing Elimination & Resize Handling
A43: TC-AI-RSZ-01 | B43: getVideoRenderRect calculation to eliminate black bar offset errors | C43: 1. Open monitor modal on different viewport aspect ratios (16:9, 4:3, ultra-wide). 2. Execute getVideoRenderRect(). | D43: - Calculates exact rendered video rectangle inside container (offset left, top, width, height). - Ensures canvas overlays align pixel-perfectly with video stream without letterbox drift. | E43: Video stream loaded with aspect ratio letterboxing | F43: Passed | G43: 46269 | H43: VyVD | I43: Passed | J43: 46287 | K43: VyVD | L43: Passed | M43: 46307 | N43: VyVD
A44: TC-AI-RSZ-02 | B44: Window resize and modal fullscreen toggle canvas re-draw | C44: 1. Resize browser window or click Maximize2 button in header. 2. Observe canvas overlay. | D44: - Canvas width and height re-synchronize to container dimensions immediately. - Redraws all 27 slot polygons without polygon stretching or offset shift. | E44: Fullscreen modal toggle active | F44: Passed | G44: 46269 | H44: VyVD | I44: Passed | J44: 46287 | K44: VyVD | L44: Passed | M44: 46307 | N44: VyVD
A45: Function 9: Real-time Audio Siren Alert & Background Polling Loop
A46: TC-AI-SND-01 | B46: AudioContext sound tone on parking violation detection | C46: 1. Unmute audio by toggling Volume2 button. 2. Introduce parking violation (WRONG_SLOT_VIOLATION or UNAUTHORIZED_PARKING). | D46: - System generates distinct cyber warning audio tone via Web AudioContext oscillator. - Suppresses continuous audio looping via lastAlertedViolationsRef comparison. | E46: Audio enabled in monitor modal | F46: Passed | G46: 46269 | H46: VyVD | I46: Passed | J46: 46288 | K46: VyVD | L46: Passed | M46: 46308 | N46: VyVD
A47: TC-AI-SND-02 | B47: 8-second background auto-scan loop interval management | C47: 1. Toggle "Auto Scan" switch to ON in monitor mode. 2. Monitor console for 60 seconds. | D47: - captureAndScanSlots() executes reliably every 8000ms. - Automatically clears interval timer when modal closes to prevent memory leaks. | E47: Auto-scan switch toggled ON | F47: Passed | G47: 46270 | H47: VyVD | I47: Passed | J47: 46288 | K47: VyVD | L47: Passed | M47: 46308 | N47: VyVD
A48: Function 10: 1-Click Fast Reassign & Live Map Floor Synchronization
A49: TC-AI-MAP-01 | B49: 1-Click Fast Reassign to resolve wrong-slot violations | C49: 1. Vehicle 22B-123.45 parked in Slot H2 instead of assigned Slot H1. 2. Staff clicks "Quick Reassign to H2". 3. Calls POST /api/sessions/:id/reassign-slot. | D49: - Backend updates session.parkingSlot to H2. - Status transitions from WRONG_SLOT_VIOLATION to OCCUPIED_VALID. - Audio plays success chime and refreshes Live Grid. | E49: Violation detected and displayed on sidebar | F49: Passed | G49: 46270 | H49: VyVD | I49: Passed | J49: 46289 | K49: VyVD | L49: Passed | M49: 46309 | N49: VyVD
A50: TC-AI-MAP-02 | B50: Cross-floor slot state isolation and bleeding prevention | C50: 1. Scan Floor 1 while Floor 2 has identical slot identifiers. 2. Check floorScanResultsMap state. | D50: - Floor scan results map strictly under floorId key. - Strips duplicate license plates from other floors. - Prevents ghost vehicle duplicates on other floor maps. | E50: Multi-floor facility with Floor 1 and Floor 2 configured | F50: Passed | G50: 46271 | H50: VyVD | I50: Passed | J50: 46289 | K50: VyVD | L50: Passed | M50: 46309 | N50: VyVD
A51: TC-AI-MAP-03 | B51: Socket.io real-time broadcast of slot state updates to Dashboard | C51: 1. Surveillance scan finishes with 5 occupied slots. 2. onSlotStatusUpdate callback emits to dashboard. 3. Open Staff Live Grid monitor on separate terminal. | D51: - Live Map grid renders green slots for Available and blue slots for Occupied within <300ms. - Total statistics counters update synchronously. | E51: Dashboard open in second browser tab | F51: Passed | G51: 46271 | H51: VyVD | I51: Passed | J51: 46290 | K51: VyVD | L51: Passed | M51: 46309 | N51: VyVD

Sheet 6. 2D Parking Map & Slot Grid
A2: Feature | B2: AI Smart Parking Slot Surveillance & Deep Vision ALPR | R2: Passed
A3: Test requirement | B3: Comprehensive end-to-end testing of autonomous parking lot computer vision: YOLOv8-Seg polygon segmentation (27 slanted perspective slots), offline EasyOCR, Gemini 2.5 Flash hybrid fusion, camera misalignment scene validation, diorama plate normalization, 1080p full-res letterboxing compensation, auto-detect floor grid, audio siren alert, 8s background polling, and 1-Click Fast Reassign violation recovery. | R3: Failed
A4: Number of TCs | B4: =COUNTIF(A12:A52, "TC-*") -> 33 | R4: Pending
A5: Testing Round | B5: Passed | C5: Failed | D5: Pending | E5: N/A | R5: N/A
A6: Round 1 | B6: =COUNTIF(F11:F52, B5) -> 31 | C6: =COUNTIF(F11:F52, C5) -> 2 | D6: =COUNTIF(F11:F52, D5) -> 0 | E6: =COUNTIF(F11:F52, E5) -> 0
A7: Round 2 | B7: =COUNTIF(I11:I52, B5) -> 29 | C7: =COUNTIF(I11:I52, C5) -> 4 | D7: =COUNTIF(I11:I52, D5) -> 0 | E7: =COUNTIF(I11:I52, E5) -> 0
A8: Round 3 | B8: =COUNTIF(L11:L52, B5) -> 33 | C8: =COUNTIF(L11:L52, C5) -> 0 | D8: =COUNTIF(L11:L52, D5) -> 0 | E8: =COUNTIF(L11:L52, E5) -> 0
A10: Test Case ID | B10: Test Case Description | C10: Test Case Procedure | D10: Expected Results | E10: Pre-conditions | F10: Round 1 | G10: Test date | H10: Tester | I10: Round 2 | J10: Test date | K10: Tester | L10: Round 3 | M10: Test date | N10: Tester | O10: Note
A11: Function 1: Visual Canvas Navigation, Coordinate Space & Drag-and-Drop (Zoom, Pan, Rnd Resizing)
A12: TC-MAP-CANVAS-01 | B12: Canvas pan via mouse drag and coordinate space translation | C12: 1. Click and hold canvas background area in ParkingLotsBuilder. 2. Drag mouse across X and Y axes. 3. Verify pan state {x, y} translation. | D12: - Canvas pan offset updates smoothly without lag. - Elements maintain relative spatial positions. - Canvas boundaries prevent infinite off-screen drift. | E12: ParkingLotsBuilder open with floor layout loaded | F12: Passed | G12: 46178 | H12: VyVD | I12: Passed | J12: 46219 | K12: VyVD | L12: Passed | M12: 46287 | N12: VyVD
A13: TC-MAP-CANVAS-02 | B13: Smooth mouse wheel zoom in/out with dynamic scale limits (0.4x - 2.5x) | C13: 1. Focus cursor over canvas. 2. Scroll mouse wheel up to zoom in, scroll down to zoom out. 3. Verify scale factor clamp. | D13: - Zooms smoothly centered at cursor position. - Minimum zoom clamp enforced at 0.4x (overview). - Maximum zoom clamp enforced at 2.5x (precision editing). - No canvas jitter or NaN coordinates. | E13: Canvas initialized with layout elements | F13: Passed | G13: 46178 | H13: VyVD | I13: Passed | J13: 46219 | K13: VyVD | L13: Passed | M13: 46287 | N13: VyVD
A14: TC-MAP-CANVAS-03 | B14: Freeform drag-and-drop repositioning of layout elements using React-Rnd | C14: 1. Select a slot or amenity element on canvas. 2. Drag element to new coordinate. 3. Release mouse click. | D14: - React-Rnd tracks drag coordinates smoothly. - Element position {x, y} updates in elements state. - Selection outline remains active during and after drag. | F14: Passed | G14: 46179 | H14: VyVD | I14: Passed | J14: 46219 | K14: VyVD | L14: Passed | M14: 46287 | N14: VyVD
A15: TC-MAP-CANVAS-04 | B15: Dynamic element rotation toggle (0° vertical vs 90° horizontal) preserving aspect ratio | C15: 1. Select vertical parking slot (50x100px, rot: 0). 2. Toggle orientation to Horizontal (rot: 90). 3. Verify dimensions and visual render. | D15: - Slot dimensions flip cleanly to 100x50px. - Visual text label and vehicle icon orient correctly. - Coordinate anchor point does not cause slot to jump outside zone. | E15: Slot element selected in right inspector panel | F15: Passed | G15: 46179 | H15: VyVD | I15: Passed | J15: 46219 | K15: VyVD | L15: Passed | M15: 46287 | N15: VyVD
A16: Function 2: Parametric Smart Grid Matrix Generator (handleGenerateGrid)
A17: TC-MAP-GRID-01 | B17: Generate 2x5 vertical slot grid matrix inside parking zone | C17: 1. Select a Zone container element. 2. Set gridConfig: rows=2, cols=5, angle=0, prefix='A', start=1. 3. Click 'Generate Grid'. | D17: - Generates exactly 10 vertical slots (50x100px) with 10px uniform spacing. - Automatically assigns names A1 through A10. - Sets parentId of all slots to current Zone id. | E17: Empty or editable Zone element selected | F17: Passed | G17: 46181 | H17: VyVD | I17: Passed | J17: 46220 | K17: VyVD | L17: Passed | M17: 46288 | N17: VyVD
A18: TC-MAP-GRID-02 | B18: Generate 90° rotated horizontal slot array with automatic dimension swap | C18: 1. Select Zone. 2. Configure gridConfig with angle=90, rows=3, cols=4, prefix='B', start=1. 3. Click 'Generate Grid'. | D18: - Slots generated with slotW=100px, slotH=50px. - Names B1 to B12 assigned sequentially. - Horizontal parking markings (=) rendered cleanly. | E18: Zone element selected | F18: Passed | G18: 46181 | H18: VyVD | I18: Passed | J18: 46220 | K18: VyVD | L18: Passed | M18: 46288 | N18: VyVD
A19: TC-MAP-GRID-03 | B19: Dynamic zone boundary auto-expansion based on generated slot array dimensions | C19: 1. Configure grid matrix with 4 rows and 6 columns. 2. Trigger handleGenerateGrid. 3. Inspect zone dimensions (newZoneW, newZoneH). | D19: - Zone width automatically expands to cols * slotW + (cols + 1) * spacing. - Zone height expands to rows * slotH + (rows + 1) * spacing. - All generated slots fit perfectly inside zone padding with zero boundary clipping. | E19: Zone element active in builder | F19: Passed | G19: 46182 | H19: VyVD | I19: Failed | J19: 46220 | K19: VyVD | L19: Passed | M19: 46288 | N19: VyVD | O19: Passed in R1, but in R2 off-by-one 10px spacing calculation on horizontal angle caused boundary overflow; resolved in R3 build
A20: TC-MAP-GRID-04 | B20: Auto-indexing and prefixing custom starting offset (start: 11 -> A11 to A20) | C20: 1. Set prefix='A', start=11, rows=2, cols=5. 2. Generate grid inside Zone A2. 3. Verify slot naming sequence. | D20: - Slots named A11, A12, A13 ... A20 in sequential order. - Prefix uppercase normalization enforced automatically. - No gaps or numbering duplication. | E20: Zone selected | F20: Passed | G20: 46182 | H20: VyVD | I20: Passed | J20: 46221 | K20: VyVD | L20: Passed | M20: 46288 | N20: VyVD
A21: TC-MAP-GRID-05 | B21: Overwrite existing zone slots upon regenerating with updated matrix parameters | C21: 1. Zone already contains 6 slots (A1-A6). 2. Change matrix configuration to rows=2, cols=4 (8 slots). 3. Click 'Generate Grid'. | D21: - Filters out old slots where parentId === zone.id. - Replaces cleanly with 8 new slots without duplicate ghost elements in layoutData. - Zone dimensions update to accommodate new layout. | E21: Zone containing pre-existing slots | F21: Passed | G21: 46183 | H21: VyVD | I21: Passed | J21: 46221 | K21: VyVD | L21: Passed | M21: 46288 | N21: VyVD
A22: Function 3: Sequential Auto-Fill & Zone Renaming Algorithm (handleAutoFillZone, generateNextName)
A23: TC-MAP-FILL-01 | B23: Sequential auto-numbering from seed slot name (A1 -> A2... A10) | C23: 1. Add multiple unnamed slots inside a Zone. 2. Set seed slot name to 'A1'. 3. Click 'Auto-Fill Zone'. | D23: - Sequentially assigns names A2, A3, A4 ... across all sibling slots. - Ordering follows geometric spatial positioning. - Auto-fill notification confirms successful numbering. | E23: Zone contains seed named slot and multiple unnamed slots | F23: Passed | G23: 46184 | H23: VyVD | I23: Passed | J23: 46222 | K23: VyVD | L23: Passed | M23: 46289 | N23: VyVD
A24: TC-MAP-FILL-02 | B24: Zero-padded slot code propagation (B01 -> B02... B12) via regex | C24: 1. Set seed slot name to 'B01'. 2. Trigger handleAutoFillZone. 3. Verify generated names in zone inspector. | D24: - generateNextName regex preserves two-digit zero-padding format. - Slots named B02, B03 ... B09, B10, B11, B12. - Does not truncate or distort leading zeros. | E24: Seed slot with zero-padded number | F24: Passed | G24: 46184 | H24: VyVD | I24: Failed | J24: 46222 | K24: VyVD | L24: Passed | M24: 46289 | N24: VyVD | O24: Passed in R1, but in R2 regex stripped leading zero when reaching double digits (B09->B10); fixed zero-padding preservation in R3
A25: TC-MAP-FILL-03 | B25: Sibling slot geometric spatial sorting (top-to-bottom, left-to-right) | C25: 1. Arrange slots haphazardly within Zone with small vertical variations (<20px). 2. Execute Auto-Fill Zone. 3. Verify numbering sequence. | D25: - Slots within 20px Y-threshold sorted by X coordinate (row order). - Lower slots sorted into subsequent rows. - Human-intuitive physical walking order achieved. | E25: Multiple unordered slots in Zone | F25: Passed | G25: 46185 | H25: VyVD | I25: Passed | J25: 46223 | K25: VyVD | L25: Passed | M25: 46289 | N25: VyVD
A26: TC-MAP-FILL-04 | B26: Duplicate naming collision prevention with existing elements across the floor | C26: 1. Floor already contains an existing slot named 'A2'. 2. Seed slot 'A1' triggers auto-fill on new zone. 3. Check generated name progression. | D26: - generateNextName detects collision with existingElements. - Skips duplicate name 'A2' and advances to 'A3' or unique increment. - Prevents database duplicate key constraint violations. | E26: Pre-existing slot on floor with overlapping name | F26: Passed | G26: 46185 | H26: VyVD | I26: Passed | J26: 46223 | K26: VyVD | L26: Passed | M26: 46289 | N26: VyVD
A27: Function 4: Multi-Element Alignment & Equal Distribution Engine (handleAlign, handleDistribute)
A28: TC-MAP-ALIGN-01 | B28: Multi-selection left alignment against leftmost element boundary | C28: 1. Select 4 slots scattered horizontally (Shift+Click). 2. Click 'Align Left' tool. 3. Verify X coordinates. | D28: - Calculates minX across all selected elements. - Updates all selected elements' X coordinates to minX. - Slots align in a perfectly straight vertical line. | E28: At least 2 elements selected | F28: Passed | G28: 46187 | H28: VyVD | I28: Passed | J28: 46224 | K28: VyVD | L28: Passed | M28: 46290 | N28: VyVD
A29: TC-MAP-ALIGN-02 | B29: Multi-selection vertical centering (middle) alignment across selected items | C29: 1. Select 3 slots with varying heights/positions. 2. Click 'Align Middle'. 3. Verify Y coordinates. | D29: - Computes bounding box vertical center (minY + (maxY - minY)/2 - h/2). - Aligns all items horizontally centered along their middle horizontal axis. | E29: Multiple elements selected | F29: Passed | G29: 46187 | H29: VyVD | I29: Passed | J29: 46224 | K29: VyVD | L29: Passed | M29: 46290 | N29: VyVD
A30: TC-MAP-ALIGN-03 | B30: Horizontal equidistant distribution across 3+ selected parking slots | C30: 1. Select 5 slots in a row with irregular spacing. 2. Click 'Distribute Horizontally'. 3. Verify inter-slot gaps. | D30: - Calculates totalDistance = last.x - first.x. - Computes step = totalDistance / (n - 1). - Gaps between each adjacent slot become exactly equal in pixels. | E30: At least 3 elements selected along X axis | F30: Passed | G30: 46188 | H30: VyVD | I30: Passed | J30: 46225 | K30: VyVD | L30: Passed | M30: 46290 | N30: VyVD
A31: TC-MAP-ALIGN-04 | B31: Vertical equidistant distribution with auto-rounded pixel offsets | C31: 1. Select 4 vertical elements. 2. Click 'Distribute Vertically'. 3. Verify integer rounding of Y coordinates. | D31: - Equal vertical spacing applied. - Math.round prevents fractional pixel sub-pixel blurring. - Visual crispness maintained at 100% canvas zoom. | E31: At least 3 elements selected along Y axis | F31: Passed | G31: 46188 | H31: VyVD | I31: Passed | J31: 46225 | K31: VyVD | L31: Passed | M31: 46290 | N31: VyVD
A32: Function 5: State History Stack & Keyboard Ergonomics (Undo/Redo & Shortcuts)
A33: TC-MAP-HIST-01 | B33: 50-level Undo/Redo stack navigation on canvas mutations (Ctrl+Z, Ctrl+Y) | C33: 1. Perform 5 consecutive layout actions (add slot, move, rename, rotate, align). 2. Press Ctrl+Z 3 times, then Ctrl+Y 2 times. 3. Verify layout integrity. | D33: - History stack rewinds exactly 3 states on Ctrl+Z. - History reapplies cleanly on Ctrl+Y. - Deep JSON cloning prevents state mutation leaks. - Maximum 50 states capped in memory to prevent browser lag. | E33: Canvas active with multiple actions performed | F33: Passed | G33: 46190 | H33: VyVD | I33: Passed | J33: 46226 | K33: VyVD | L33: Passed | M33: 46291 | N33: VyVD
A34: TC-MAP-HIST-02 | B34: Clipboard copy (Ctrl+C) and paste (Ctrl+V) with 20px positional offset | C34: 1. Select an element and press Ctrl+C. 2. Press Ctrl+V on canvas. 3. Verify pasted element position and attributes. | D34: - Clones selected element with unique generated ID. - Offsets pasted position by x+20, y+20 for visual clarity. - Automatically selects newly pasted element for immediate movement. | E34: Element selected on canvas | F34: Passed | G34: 46190 | H34: VyVD | I34: Passed | J34: 46226 | K34: VyVD | L34: Passed | M34: 46291 | N34: VyVD
A35: TC-MAP-HIST-03 | B35: Element duplication (Ctrl+D) with auto-generated unique ID (createElementId) | C35: 1. Select slot 'A1' and press Ctrl+D. 2. Check ID and properties of duplicate. 3. Verify collision-free UUID suffix. | D35: - Creates instant duplicate with new ID `${type}-${Date.now()}-${random}`. - Position offset by 15px. - Preserves color, rotation, and dimensions. | E35: Element selected | F35: Passed | G35: 46191 | H35: VyVD | I35: Passed | J35: 46227 | K35: VyVD | L35: Passed | M35: 46291 | N35: VyVD
A36: TC-MAP-HIST-04 | B36: Keyboard input field immunity (ignoring hotkeys inside input/textarea tags) | C36: 1. Focus cursor inside slot name text input field. 2. Type 'Delete', 'Backspace', or 'Ctrl+Z'. 3. Verify canvas ignores hotkeys. | D36: - Hotkey listener checks `e.target.tagName === 'INPUT' || 'TEXTAREA'`. - Normal text editing occurs without deleting canvas elements or triggering canvas undo. | E36: Input text field focused in sidebar | F36: Passed | G36: 46191 | H36: VyVD | I36: Passed | J36: 46227 | K36: VyVD | L36: Passed | M36: 46291 | N36: VyVD
A37: Function 6: Active Business Entity Protection & Deletion Safety Guard
A38: TC-MAP-PROT-01 | B38: Block deletion of slot with active VIP subscription entitlement (Frontend warning modal) | C38: 1. In ParkingLotsBuilder, select slot 'VIP-01' which has active monthly entitlement in dbSlots. 2. Press Delete key. 3. Verify system response. | D38: - handleRemoveElements detects dbSlot.subscriptionType. - Aborts deletion and triggers deleteWarning modal displaying slot name and active package. - Slot remains safely on canvas. | E38: Floor contains slot bound to active VIP customer subscription | F38: Passed | G38: 46193 | H38: VyVD | I38: Passed | J38: 46228 | K38: VyVD | L38: Passed | M38: 46292 | N38: VyVD
A39: TC-MAP-PROT-02 | B39: Backend HTTP 400 rejection on attempt to delete slot with parked vehicle | C39: 1. Slot 'A05' has active parking session (status: 'active') in MongoDB. 2. Admin modifies layout omitting 'A05' and clicks Save. 3. Inspect PUT /api/parking-floors/:id/layout response. | D39: - Backend verifies active sessions via Session.find({ status: 'active', parkingSlot: { $in: deletedSlots } }). - Returns HTTP 400 with message 'Lỗi Hệ Thống: Không thể xoá các ô đỗ (A05) vì đang có xe đậu tại các ô này.'. - Database transaction rolls back. | E39: Vehicle currently parked in target slot | F39: Failed | G39: 46193 | H39: VyVD | I39: Failed | J39: 46228 | K39: VyVD | L39: Passed | M39: 46292 | N39: VyVD | O39: Failed in R1 & R2 as backend deleted slot despite active parked vehicle leaving orphaned session; added strict Session.find guard in R3
A40: TC-MAP-PROT-03 | B40: Cascading deletion of child slots when parent Zone is safely deleted | C40: 1. Select Zone containing 5 available slots without VIP or active sessions. 2. Delete Zone. 3. Verify child slot cleanup. | D40: - Deletes Zone and all elements with parentId === zone.id simultaneously. - Clean removal from elements state and selection IDs. | E40: Zone with only available, unreserved slots | F40: Passed | G40: 46194 | H40: VyVD | I40: Passed | J40: 46229 | K40: VyVD | L40: Passed | M40: 46292 | N40: VyVD
A41: TC-MAP-PROT-04 | B41: Safe deletion of unassigned/available standard slot without business conflicts | C41: 1. Select unassigned standard slot 'B08'. 2. Press Delete or click Trash icon. 3. Verify element removal. | D41: - Element removed instantly from canvas. - Added to undo history stack. - No warning modals displayed. | E41: Available slot with no bookings or sessions | F41: Passed | G41: 46194 | H41: VyVD | I41: Passed | J41: 46229 | K41: VyVD | L41: Passed | M41: 46292 | N41: VyVD
A42: Function 7: Spatial Geometric Intersection & Database Upsert (updateFloorLayout)
A43: TC-MAP-SYNC-01 | B43: Automatic zone ID resolution based on slot 2D spatial coordinate intersection (zoneDocsMap) | C43: 1. Drag slot 'C01' inside Zone C bounding box (x, y, w, h). 2. Save floor layout. 3. Inspect MongoDB Slot document. | D43: - Backend calculates spatial intersection: sEl.x >= zEl.x and sEl.y >= zEl.y. - Slot.zoneID automatically populated with MongoDB Zone._id. - Relational link established without manual zone assignment. | E43: Floor layout with configured Zones and Slots | F43: Passed | G43: 46195 | H43: VyVD | I43: Failed | J43: 46229 | K43: VyVD | L43: Passed | M43: 46293 | N43: VyVD | O43: Passed in R1, but in R2 slot placed on exact zone boundary line was missed by strict greater-than check; added boundary tolerance in R3
A44: TC-MAP-SYNC-02 | B44: Unnamed slot filtering to prevent database clutter while preserving builder display | C44: 1. Place 3 template slots on canvas but leave their names blank. 2. Save floor layout. 3. Query MongoDB Slot collection for this floor. | D44: - Backend optimization executes: if (!sEl.name || sEl.name.trim() === '') continue. - Unnamed slots saved in layoutData for UI editing but excluded from Slot collection. - Prevents customer booking errors. | E44: Builder canvas with unnamed draft slots | F44: Passed | G44: 46195 | H44: VyVD | I44: Passed | J44: 46230 | K44: VyVD | L44: Passed | M44: 46293 | N44: VyVD
A45: TC-MAP-SYNC-03 | B45: High-performance batch synchronization via MongoDB bulkWrite operations | C45: 1. Layout contains 60 slots. 2. Save floor layout. 3. Monitor database query execution time. | D45: - Single Slot.bulkWrite executes all upsert operations in one roundtrip. - Execution finishes in <250ms for 60 slots. - Eliminates sequential N+1 query bottlenecks. | E45: Floor with high slot density | F45: Passed | G45: 46196 | H45: VyVD | I45: Passed | J45: 46230 | K45: VyVD | L45: Passed | M45: 46293 | N45: VyVD
A46: TC-MAP-SYNC-04 | B46: Database cleanup of orphaned slots removed from canvas layoutData ($nin: validSlotNames) | C46: 1. Previously saved floor has slots A1-A10. 2. In builder, delete slots A9 and A10 and save. 3. Inspect MongoDB Slot collection. | D46: - Slot.deleteMany({ floorID: id, slotNumber: { $nin: validSlotNames } }) executes. - Slots A9 and A10 removed from database. - Active floor capacity count updates immediately. | E46: Floor with previously persisted slots | F46: Passed | G46: 46196 | H46: VyVD | I46: Passed | J46: 46230 | K46: VyVD | L46: Passed | M46: 46293 | N46: VyVD
A47: Function 8: Floor Lifecycle & Intelligent Layout Duplication (ParkingLots.jsx)
A48: TC-MAP-FLOOR-01 | B48: Create new parking floor with automatic floor number increment and uniqueness check | C48: 1. Current highest floor is Floor 2. 2. Click 'Add Floor'. 3. Verify default floorNumber, then attempt to create duplicate Floor 2. | D48: - getNextFloorNumber pre-fills floorNumber = 3. - Duplicate floorNumber attempt returns HTTP 400 'Floor number already exists'. - AdminActionLog records 'Created Parking Lot'. | E48: Admin authenticated in ParkingLots management page | F48: Passed | G48: 46197 | H48: VyVD | I48: Passed | J48: 46231 | K48: VyVD | L48: Passed | M48: 46294 | N48: VyVD
A49: TC-MAP-FLOOR-02 | B49: Clone existing floor layout with intelligent slot prefix transformation ('A' -> 'B') | C49: 1. Select Floor 1 (slots with prefix 'A'). 2. Click 'Duplicate Floor'. 3. Inspect cloned floor elements and slot numbers. | D49: - Layout duplicated with new floorNumber. - renameSlotPrefix maps slot codes from 'A1' to 'B1', 'A2' to 'B2'. - Zones renamed from 'Zone A' to 'Zone B'. - Element IDs regenerated to avoid ID clashes. | E49: Floor 1 populated with complete layout | F49: Failed | G49: 46197 | H49: VyVD | I49: Passed | J49: 46231 | K49: VyVD | L49: Passed | M49: 46294 | N49: VyVD | O49: Failed in R1 as floor duplication kept original slot IDs causing cross-floor overwrites; fixed with createElementId UUID regeneration in R2 & R3
A50: TC-MAP-FLOOR-03 | B50: Admin audit trail logging on floor creation and layout modifications (AdminActionLog) | C50: 1. Create or modify a floor layout. 2. Check AdminActionLog collection in MongoDB. 3. Verify log record fields. | D50: - Log entry created with adminId, action: 'Created Parking Lot' or 'Updated Layout', target: floor name, timestamp. | E50: Admin user logged in | F50: Passed | G50: 46198 | H50: VyVD | I50: Passed | J50: 46232 | K50: VyVD | L50: Passed | M50: 46294 | N50: VyVD
A51: TC-MAP-FLOOR-04 | B51: Delete floor with safety check against active parking sessions across all slots | C51: 1. Floor contains 1 active parked vehicle. 2. Admin attempts to delete floor. 3. Verify safety confirmation and execution guard. | D51: - Deletion blocked while active sessions exist. - On empty floor, deleteFloor cascades: deletes floor, Slot.deleteMany, and Zone.deleteMany cleanly. | E51: Floor with active and empty states tested | F51: Passed | G51: 46198 | H51: VyVD | I51: Passed | J51: 46232 | K51: VyVD | L51: Passed | M51: 46294 | N51: VyVD
A52: Function 9: Real-Time Slot Maintenance Mode & Hazard Visualization
A53: TC-MAP-MAINT-01 | B53: Toggle slot status to Maintenance mode with automated maintenance log recording | C53: 1. In ParkingLots floor card, click slot 'A03'. 2. Toggle status to 'Maintenance'. 3. Check SlotMaintenanceLog collection. | D53: - Slot status updates to 'maintenance'. - Creates SlotMaintenanceLog entry with status 'in_progress', startTime: now, reason: 'Staff toggle'. - WebSocket event emits status update to all connected clients. | E53: Admin or Staff logged in with slot management permission | F53: Passed | G53: 46199 | H53: VyVD | I53: Passed | J53: 46233 | K53: VyVD | L53: Passed | M53: 46296 | N53: VyVD
A54: TC-MAP-MAINT-02 | B54: Render visual hazard stripe overlay pattern on maintenance slots in 2D grid | C54: 1. Set slot to maintenance. 2. View slot in ParkingMapGrid. 3. Inspect rendered CSS style. | D54: - SlotElement applies maintenanceStyle: repeating-linear-gradient(45deg, rgba(239, 68, 68, 0.2)...). - Distinct red diagonal hazard stripes visually distinguish slot from normal/occupied states. | E54: Slot in maintenance status | F54: Passed | G54: 46199 | H54: VyVD | I54: Passed | J54: 46233 | K54: VyVD | L54: Passed | M54: 46296 | N54: VyVD
A55: TC-MAP-MAINT-03 | B55: Immediate exclusion of maintenance slots from Kiosk assignment and customer booking APIs | C55: 1. Slot 'A03' marked maintenance. 2. Customer requests booking slot list via GET /api/slots/available. 3. Kiosk auto-assigns slot for incoming car. | D55: - GET /api/slots excludes 'A03'. - Kiosk auto-pilot algorithm bypasses 'A03'. - No customer can reserve or park in a maintenance slot. | E55: Slot in maintenance mode | F55: Passed | G55: 46200 | H55: VyVD | I55: Passed | J55: 46233 | K55: VyVD | L55: Passed | M55: 46296 | N55: VyVD
A56: TC-MAP-MAINT-04 | B56: Restore maintenance slot to Available status and close active maintenance log | C56: 1. Toggle maintenance slot back to 'Available'. 2. Inspect SlotMaintenanceLog and live map. 3. Verify slot availability. | D56: - Slot status returns to 'available'. - SlotMaintenanceLog status updated to 'completed' with endTime recorded. - Hazard stripes disappear; slot instantly bookable. | E56: Slot currently in maintenance | F56: Passed | G56: 46200 | H56: VyVD | I56: Passed | J56: 46233 | K56: VyVD | L56: Passed | M56: 46296 | N56: VyVD
A57: Function 10: Unified Live Map Rendering & Multi-Role Status Presentation (ParkingMapGrid.jsx, getLiveMapData)
A58: TC-MAP-LIVE-01 | B58: Unified multi-source slot status aggregation (Session, Booking, Hold, Entitlement) | C58: 1. Request GET /api/parking-floors/live-map. 2. Verify slot status derivation logic across multiple active collections. | D58: - Correctly computes precedence: Maintenance > Occupied (active Session) > Reserved (upcoming Booking, active Hold, or VIP Entitlement) > Available. - Live map data matches physical floor status exactly. | E58: Backend running with active test database fixtures | F58: Passed | G58: 46201 | H58: VyVD | I58: Passed | J58: 46233 | K58: VyVD | L58: Passed | M58: 46297 | N58: VyVD
A59: TC-MAP-LIVE-02 | B59: Multi-role view differentiation (Customer privacy vs Admin license plate visibility) | C59: 1. Open ParkingMap as Guest/Customer. 2. Open LiveGridMonitor as Admin/Staff (canViewLicensePlate = true). 3. Compare slot labels. | D59: - Customer view masks license plates and shows generic Occupied car icon. - Admin/Staff view displays actual vehicle license plate, parked duration, and subscription tier. - Full customer privacy compliance ensured. | E59: Both customer and admin sessions active | F59: Passed | G59: 46201 | H59: VyVD | I59: Passed | J59: 46233 | K59: VyVD | L59: Passed | M59: 46297 | N59: VyVD
A60: TC-MAP-LIVE-03 | B60: Real-time parked duration ticker update (LiveDuration) without full-page re-render | C60: 1. Observe occupied slot on live monitor. 2. Monitor elapsed time timer incrementing every 60s. 3. Check browser performance and component re-renders. | D60: - LiveDuration component updates isolated timer DOM without triggering full canvas layout re-calculation. - React.memo on SlotElement prevents unnecessary virtual DOM diffing. - 60fps canvas panning remains buttery smooth. | E60: Occupied slot displayed on live map | F60: Passed | G60: 46202 | H60: VyVD | I60: Failed | J60: 46233 | K60: VyVD | L60: Passed | M60: 46297 | N60: VyVD | O60: Passed in R1, but in R2 unmemoized LiveDuration ticker triggered virtual DOM re-renders of 100+ slots every second; wrapped in React.memo in R3
A61: TC-MAP-LIVE-04 | B61: Visual highlight and flashing violation border on AI wrong slot detection | C61: 1. AI slot surveillance reports WRONG_SLOT_VIOLATION for slot 'A04'. 2. Inspect slot styling in ParkingMapGrid. 3. Click slot to inspect violation details. | D61: - isWrongSlot evaluates to true. - Slot border flashes high-contrast violation styling with warning badge. - Modal displays detected vehicle plate vs expected plate for fast staff resolution. | E61: AI service reporting unauthorized or wrong slot occupancy | F61: Passed | G61: 46202 | H61: VyVD | I61: Passed | J61: 46233 | K61: VyVD | L61: Passed | M61: 46297 | N61: VyVD

Sheet 7. Profile 
A2: Feature | B2: Profile | R2: Passed
A3: Test requirement | B3: To verify customer Profile functions including profile data viewing, profile update with name/phone validation, and password change with authentication, validation, and error handling. | R3: Failed
A4: Number of TCs | B4: =COUNTIF(A21:A63, "TC-*") -> 41 | R4: Pending
A5: Testing Round | B5: Passed | C5: Failed | D5: Pending | E5: N/A | R5: N/A
A6: Round 1 | B6: =COUNTIF(F11:F63, B5) -> 32 | C6: =COUNTIF(F11:F63, C5) -> 18 | D6: =COUNTIF(F11:F63, D5) -> 0 | E6: =COUNTIF(F11:F63, E5) -> 0
A7: Round 2 | B7: =COUNTIF(I11:I63, B5) -> 44 | C7: =COUNTIF(I11:I63, C5) -> 6 | D7: =COUNTIF(I11:I63, D5) -> 0 | E7: =COUNTIF(I11:I63, E5) -> 0
A8: Round 3 | B8: =COUNTIF(L11:L63, B5) -> 50 | C8: =COUNTIF(L11:L63, C5) -> 0 | D8: =COUNTIF(L11:L63, D5) -> 0 | E8: =COUNTIF(L11:L63, E5) -> 0
A10: Test Case ID | B10: Test Case Description | C10: Test Case Procedure | D10: Expected Results | E10: Pre-conditions | F10: Round 1 | G10: Test date | H10: Tester | I10: Round 2 | J10: Test date | K10: Tester | L10: Round 3 | M10: Test date | N10: Tester | O10: Note
A11: Function 1: View Profile
A12: TC-PROFILE-VIEW-01 | B12: View customer profile with valid authentication | C12: 1. Sign in with an active Customer account. 2. Open /profile. 3. Wait for GET /api/profile to complete. | D12: - Profile page is displayed. - Server profile data replaces cached/default values. - NAME/PHONE/EMAIL/MEMBER SINCE and avatar are rendered from the verified profile response. | E12: Active Customer account; cached user role is customer; valid access token; backend and MongoDB available. | F12: Passed | G12: 46255 | H12: TranPLH | I12: Passed | J12: 46273 | K12: TranPLH | L12: Passed | M12: 46297 | N12: TranPLH
A13: TC-PROFILE-VIEW-02 | B13: Access Profile without cached user session | C13: 1. Remove sessionStorage.valo_user. 2. Navigate to /profile. | D13: - ProtectedRoute redirects to the login page with a return URL. - CustomerProfile page does not mount. | E13: No cached user exists in sessionStorage. | F13: Passed | G13: 46255 | H13: TranPLH | I13: Passed | J13: 46273 | K13: TranPLH | L13: Passed | M13: 46297 | N13: TranPLH
A14: TC-PROFILE-VIEW-03 | B14: Reject access to Customer Profile when cached role is not customer | C14: 1. Use a cached user whose role is not customer. 2. Navigate to /profile. | D14: - ProtectedRoute redirects to /unauthorized. - Customer Profile content is not displayed. | E14: Cached user exists but role is not allowed for /profile. | F14: Failed | G14: 46256 | H14: TranPLH | I14: Passed | J14: 46274 | K14: TranPLH | L14: Passed | M14: 46298 | N14: TranPLH | O14: Role-based access handling passed after R2 retest
A15: TC-PROFILE-VIEW-04 | B15: Profile page behavior when access token is missing | C15: 1. Keep a valid cached customer profile. 2. Remove localStorage.accessToken. 3. Open /profile. | D15: - Cached/default profile state is kept. - CustomerProfile does not send GET /api/profile from its load handler. | E15: Cached Customer data exists; access token is missing or empty. | F15: Failed | G15: 46256 | H15: TranPLH | I15: Failed | J15: 46274 | K15: TranPLH | L15: Passed | M15: 46298 | N15: TranPLH | O15: Missing-token profile handling passed after R3 retest
A16: TC-PROFILE-VIEW-05 | B16: Refresh Profile state and cache after successful server load | C16: 1. Open /profile with cached customer data. 2. Allow GET /api/profile to return success. | D16: - Profile state is replaced by server data. - sessionStorage.valo_user is refreshed with merged profile data. - valo_auth_change event is dispatched. | E16: Active Customer; valid token; GET /api/profile returns success:true with data. | F16: Passed | G16: 46257 | H16: TranPLH | I16: Passed | J16: 46275 | K16: TranPLH | L16: Passed | M16: 46299 | N16: TranPLH
A17: TC-PROFILE-VIEW-06 | B17: Retry Profile load after expired access token | C17: 1. Open /profile with an expired access token and a valid refresh path. 2. Allow the first GET /api/profile to return 401 TOKEN_EXPIRED. | D17: - apiFetch refreshes the access token once. - New access token is stored. - GET /api/profile is retried with the new Bearer token. - Profile updates if the retry succeeds. | E17: Active Customer; expired access token; refresh flow returns a new access token. | F17: Failed | G17: 46257 | H17: TranPLH | I17: Passed | J17: 46275 | K17: TranPLH | L17: Passed | M17: 46299 | N17: TranPLH | O17: Expired-token refresh flow passed after R2 retest
A18: TC-PROFILE-VIEW-07 | B18: Handle failed token refresh while loading Profile | C18: 1. Open /profile with a token that causes 401. 2. Make refresh fail, return no access token, or have no refresh token. | D18: - Auth session is cleared. - Browser is redirected to /login. - Profile is not refreshed with protected server data. | E18: Customer page attempts GET /api/profile; refresh cannot provide a valid new access token. | F18: Passed | G18: 46258 | H18: TranPLH | I18: Passed | J18: 46276 | K18: TranPLH | L18: Passed | M18: 46300 | N18: TranPLH
A19: TC-PROFILE-VIEW-08 | B19: Handle deactivated customer account | C19: 1. Use a valid token for a User whose status is inactive. 2. Request /profile. | D19: - Backend returns HTTP 403 with the deactivated-account message. - apiFetch does not perform the 401 refresh flow. - Existing page state is not replaced by a successful profile response. | E19: JWT is valid; User exists; user.status is falsy. | F19: Passed | G19: 46258 | H19: TranPLH | I19: Passed | J19: 46276 | K19: TranPLH | L19: Passed | M19: 46300 | N19: TranPLH
A20: TC-PROFILE-VIEW-09 | B20: Handle token whose User record no longer exists | C20: 1. Use a JWT that verifies but refers to a missing User. 2. Request GET /api/profile. | D20: - Backend protect middleware returns HTTP 401. - Response indicates the User belonging to the token no longer exists. | E20: JWT is syntactically valid; referenced User record is absent. | F20: Passed | G20: 46259 | H20: TranPLH | I20: Passed | J20: 46277 | K20: TranPLH | L20: Passed | M20: 46301 | N20: TranPLH
A21: TC-PROFILE-VIEW-10 | B21: Load Profile when UserDetail does not exist | C21: 1. Sign in with an active Customer whose UserDetail record is missing. 2. Open /profile. | D21: - GET /api/profile still returns HTTP 200. - Missing detail strings are returned as empty strings and dob as null. - Profile page renders verified fallbacks instead of returning 404 for missing UserDetail. | E21: User account exists and is active; no UserDetail record for current user. | F21: Failed | G21: 46259 | H21: TranPLH | I21: Passed | J21: 46277 | K21: TranPLH | L21: Passed | M21: 46301 | N21: TranPLH | O21: Missing UserDetail fallback passed after R2 retest
A22: TC-PROFILE-VIEW-11 | B22: Fallback profile name when first and last name are missing | C22: 1. Load a profile where firstName and lastName are empty. 2. Observe the displayed name. | D22: - FE falls back to username. - If username is also falsy, FE displays User. | E22: Profile response has no usable firstName/lastName values. | F22: Passed | G22: 46260 | H22: TranPLH | I22: Passed | J22: 46279 | K22: TranPLH | L22: Passed | M22: 46302 | N22: TranPLH
A23: TC-PROFILE-VIEW-12 | B23: Display fallback values for missing phone/email and missing phone prompt | C23: 1. Load Customer Profile with missing/falsy phone and/or email. 2. Observe read-only fields. | D23: - Missing displayed values show —. - Missing phone also triggers the Customer prompt to update phone while not in edit mode. | E23: Customer profile response contains missing/falsy phone and/or email. | F23: Passed | G23: 46260 | H23: TranPLH | I23: Passed | J23: 46279 | K23: TranPLH | L23: Passed | M23: 46302 | N23: TranPLH
A24: TC-PROFILE-VIEW-13 | B24: Display fallback avatar when Customer avatar is missing | C24: 1. Load Customer Profile with avatar missing or empty. 2. Observe the profile avatar area. | D24: - Customer Profile uses the VALO fallback logo instead of an image URL. | E24: Customer profile avatar is falsy. | F24: Passed | G24: 46261 | H24: TranPLH | I24: Passed | J24: 46280 | K24: TranPLH | L24: Passed | M24: 46303 | N24: TranPLH
A25: TC-PROFILE-VIEW-14 | B25: Render active VIP membership and reserved slot banner | C25: 1. Load a Customer whose membership is active VIP. 2. Provide reservedSlots in the profile response. 3. Observe membership UI. | D25: - VIP theme is rendered according to package type. - VIP PASS banner is shown when reservedSlots is non-empty. - floorName and slotNumber are displayed from reserved slot data. | E25: Customer is active VIP and response contains at least one reserved slot. | F25: Failed | G25: 46261 | H25: TranPLH | I25: Failed | J25: 46280 | K25: TranPLH | L25: Passed | M25: 46303 | N25: TranPLH | O25: VIP reserved-slot display passed after R3 retest
A26: TC-PROFILE-VIEW-15 | B26: Keep current Profile state when load request fails | C26: 1. Open /profile with existing cached/default state. 2. Make GET /api/profile fail by network or non-success HTTP response. | D26: - Existing Profile state/cache remains displayed. - No dedicated Profile-load error UI or retry button is shown by the page load handler. | E26: CustomerProfile is mounted; server request fails or returns non-success. | F26: Failed | G26: 46262 | H26: TranPLH | I26: Passed | J26: 46281 | K26: TranPLH | L26: Passed | M26: 46304 | N26: TranPLH | O26: Profile-load failure handling passed after R2 retest
A27: Function 2: Update Profile
A28: TC-PROFILE-UPD-01 | B28: Enter Profile edit mode | C28: 1. Open Customer Profile. 2. Click Edit Profile. | D28: - Edit mode opens. - Current NAME and PHONE are copied into draft. - Existing field errors are cleared. | E28: Customer Profile is displayed. | F28: Passed | G28: 46263 | H28: TranPLH | I28: Passed | J28: 46282 | K28: TranPLH | L28: Passed | M28: 46304 | N28: TranPLH
A29: TC-PROFILE-UPD-02 | B29: Cancel Profile edit without saving | C29: 1. Click Edit Profile. 2. Change NAME/PHONE. 3. Click Cancel. 4. Enter edit mode again. | D29: - Cancel sends no PUT /api/profile. - Saved Profile/cache remain unchanged. - Re-entering edit mode reloads current saved values, not cancelled draft values. | E29: Customer is in Profile edit mode with unsaved changes. | F29: Passed | G29: 46263 | H29: TranPLH | I29: Passed | J29: 46282 | K29: TranPLH | L29: Passed | M29: 46304 | N29: TranPLH
A30: TC-PROFILE-UPD-03 | B30: Validate required NAME | C30: 1. Open Edit Profile. 2. Clear NAME or enter whitespace only. 3. Click Save Changes. | D30: - NAME is trimmed. - Name is required. is shown. - Edit mode remains open. - No PUT request is sent. | E30: Edit mode is open; PHONE is valid. | F30: Passed | G30: 46263 | H30: TranPLH | I30: Passed | J30: 46283 | K30: TranPLH | L30: Passed | M30: 46304 | N30: TranPLH
A31: TC-PROFILE-UPD-04 | B31: Validate minimum NAME length | C31: 1. Enter a 1-character NAME and save. 2. Enter a 2-character NAME with valid PHONE and save. | D31: - Length 1 shows Name must be at least 2 characters. and blocks PUT. - Length 2 passes NAME validation. | E31: Edit mode is open; PHONE is valid. | F31: Failed | G31: 46264 | H31: TranPLH | I31: Passed | J31: 46283 | K31: TranPLH | L31: Passed | M31: 46305 | N31: TranPLH | O31: Name minimum-length validation passed after R2 retest
A32: TC-PROFILE-UPD-05 | B32: Validate required PHONE | C32: 1. Open Edit Profile. 2. Clear PHONE or enter whitespace only. 3. Click Save Changes. | D32: - PHONE is trimmed. - Phone number is required. is shown. - No PUT request is sent. | E32: Edit mode is open; NAME is valid. | F32: Passed | G32: 46264 | H32: TranPLH | I32: Passed | J32: 46283 | K32: TranPLH | L32: Passed | M32: 46305 | N32: TranPLH
A33: TC-PROFILE-UPD-06 | B33: Reject invalid PHONE format | C33: 1. Enter PHONE that is not exactly 10 digits beginning with 0, such as 9 digits, 11 digits, letters, or internal spaces. 2. Save. | D33: - FE regex validation fails. - Invalid phone (e.g. 0905414132). is shown. - No PUT request is sent. | E33: Edit mode is open; NAME is valid. | F33: Failed | G33: 46264 | H33: TranPLH | I33: Passed | J33: 46284 | K33: TranPLH | L33: Passed | M33: 46305 | N33: TranPLH | O33: Phone format validation passed after R2 retest
A34: TC-PROFILE-UPD-07 | B34: Update NAME and PHONE successfully | C34: 1. Enter valid NAME. 2. Enter valid 10-digit PHONE starting with 0. 3. Click Save Changes. | D34: - FE sends PUT /api/profile with firstName, lastName, phone. - Backend updates/upserts UserDetail. - Success response updates Profile state/cache and dispatches auth-change event. - Success toast is shown. | E34: Active authenticated Customer; phone is not linked to another account. | F34: Passed | G34: 46265 | H34: TranPLH | I34: Passed | J34: 46284 | K34: TranPLH | L34: Passed | M34: 46306 | N34: TranPLH
A35: TC-PROFILE-UPD-08 | B35: Trim and split multi-word NAME before save | C35: 1. Enter NAME with outer spaces and multiple words. 2. Enter valid PHONE. 3. Save Profile. | D35: - Outer spaces are trimmed. - NAME is split at the last space into firstName and lastName. - PHONE is trimmed before sending. | E35: Edit mode is open; inputs pass validation. | F35: Passed | G35: 46265 | H35: TranPLH | I35: Passed | J35: 46285 | K35: TranPLH | L35: Passed | M35: 46306 | N35: TranPLH
A36: TC-PROFILE-UPD-09 | B36: Save Profile with single-word NAME | C36: 1. Enter a single-word NAME of at least 2 characters. 2. Enter valid PHONE. 3. Save. | D36: - Entire NAME becomes firstName. - lastName is sent/stored as empty string. - Update can complete successfully. | E36: Customer is editing Profile with valid PHONE. | F36: Passed | G36: 46265 | H36: TranPLH | I36: Passed | J36: 46285 | K36: TranPLH | L36: Passed | M36: 46306 | N36: TranPLH
A37: TC-PROFILE-UPD-10 | B37: Reject PHONE already linked to another account | C37: 1. Enter a valid PHONE whose normalized variant belongs to another UserDetail. 2. Save Profile. | D37: - Backend returns HTTP 400. - Message is This phone number is already linked to another account. - Profile optimistic state is rolled back. - Error toast is displayed. | E37: Another account owns a matching phone variant. | F37: Failed | G37: 46266 | H37: TranPLH | I37: Failed | J37: 46286 | K37: TranPLH | L37: Passed | M37: 46307 | N37: TranPLH | O37: Duplicate-phone handling passed after R3 retest
A38: TC-PROFILE-UPD-11 | B38: Save unchanged Profile values | C38: 1. Enter edit mode. 2. Do not change NAME or PHONE. 3. Click Save Changes. | D38: - No dirty-value guard blocks save. - PUT request is still sent. - Current user's own phone does not trigger duplicate error by itself. | E38: Current Customer has valid saved NAME/PHONE; no other account conflicts. | F38: Passed | G38: 46266 | H38: TranPLH | I38: Passed | J38: 46286 | K38: TranPLH | L38: Passed | M38: 46307 | N38: TranPLH
A39: TC-PROFILE-UPD-12 | B39: Create UserDetail when missing during update | C39: 1. Use authenticated Customer without UserDetail. 2. Submit valid NAME and PHONE. | D39: - Backend uses upsert:true. - New UserDetail is created for current user. - Updated Profile payload is returned. | E39: Active Customer exists; UserDetail does not exist. | F39: Failed | G39: 46266 | H39: TranPLH | I39: Passed | J39: 46287 | K39: TranPLH | L39: Passed | M39: 46307 | N39: TranPLH | O39: UserDetail upsert flow passed after R2 retest
A40: TC-PROFILE-UPD-13 | B40: Update existing UserDetail | C40: 1. Use Customer with existing UserDetail. 2. Change NAME/PHONE to valid values. 3. Save. | D40: - Existing UserDetail is updated for req.user._id. - Profile response contains updated values. - User account fields such as username/role are not changed by this controller. | E40: Existing UserDetail belongs to authenticated Customer. | F40: Passed | G40: 46266 | H40: TranPLH | I40: Passed | J40: 46287 | K40: TranPLH | L40: Passed | M40: 46308 | N40: TranPLH
A41: TC-PROFILE-UPD-14 | B41: Handle missing access token during save | C41: 1. Enter valid NAME/PHONE. 2. Remove localStorage.accessToken before save. 3. Click Save Changes. | D41: - Optimistic Profile values are shown and edit mode closes first. - Not authenticated toast is shown. - PUT request and cache write are not performed. - Optimistic state is not rolled back in this branch. | E41: Customer Profile is mounted; valid inputs; access token missing at save time. | F41: Failed | G41: 46267 | H41: TranPLH | I41: Failed | J41: 46288 | K41: TranPLH | L41: Passed | M41: 46308 | N41: TranPLH | O41: Missing-token save handling passed after R3 retest
A42: TC-PROFILE-UPD-15 | B42: Normalize backend-supported phone formats through direct API | C42: 1. Send authenticated PUT /api/profile directly with backend-supported phone variant such as +84..., 9-digit form, or 10 digits beginning with 0. 2. Inspect response/stored phone. | D42: - Backend normalizes supported phone variants. - Duplicate check and write use normalized phone. - This behavior is broader than Customer UI validation. | E42: Authenticated Customer; direct API request; remaining payload valid. | F42: Passed | G42: 46267 | H42: TranPLH | I42: Passed | J42: 46288 | K42: TranPLH | L42: Passed | M42: 46309 | N42: TranPLH
A43: TC-PROFILE-UPD-16 | B43: Clear PHONE through direct Profile API | C43: 1. Send authenticated direct PUT with PHONE omitted/null/empty. 2. Inspect UserDetail and response. | D43: - Controller resolves falsy phone input to empty string. - Duplicate check/session claim are skipped when normalized phone is falsy. - Customer UI itself blocks empty phone through required validation. | E43: Authenticated Customer; direct API call. | F43: Passed | G43: 46267 | H43: TranPLH | I43: Passed | J43: 46289 | K43: TranPLH | L43: Passed | M43: 46309 | N43: TranPLH
A44: TC-PROFILE-UPD-17 | B44: Roll back Profile when update request fails | C44: 1. Enter valid changed NAME/PHONE. 2. Save. 3. Cause network or non-success server response. | D44: - FE rolls Profile state back to pre-save state. - Draft values remain. - Edit mode stays closed. - Failed update is not written to cache by save handler. - Error toast shows response message or Update failed. | E44: Valid update was submitted but request fails. | F44: Failed | G44: 46267 | H44: TranPLH | I44: Passed | J44: 46290 | K44: TranPLH | L44: Passed | M44: 46309 | N44: TranPLH | O44: Update rollback handling passed after R2 retest
A45: Function 3: Change Password
A46: TC-PROFILE-PWD-01 | B46: Open and cancel Change Password form | C46: 1. Open Customer Profile Security section. 2. Click Change Password. 3. Enter temporary password values. 4. Click Cancel. | D46: - Inline Change Password form opens. - Cancel closes the form. - Password inputs, validation errors, visibility state, and Forgot-password subflow state are reset. | E46: Customer Profile Security section is visible. | F46: Passed | G46: 46261 | H46: TranPLH | I46: Passed | J46: 46282 | K46: TranPLH | L46: Passed | M46: 46305 | N46: TranPLH
A47: TC-PROFILE-PWD-02 | B47: Show current-password input for local-password Customer | C47: 1. Open Change Password using a Customer account with a local password. 2. Observe the form. | D47: - CURRENT PASSWORD input is displayed. - NEW PASSWORD input is displayed. - Submit remains gated by current/new/confirm validity. | E47: Customer has a local password; profile.isGoogleUser is false. | F47: Passed | G47: 46261 | H47: TranPLH | I47: Passed | J47: 46282 | K47: TranPLH | L47: Passed | M47: 46305 | N47: TranPLH
A48: TC-PROFILE-PWD-03 | B48: Hide current-password input for Google Customer without local password | C48: 1. Open Change Password using a Google Customer whose profile.isGoogleUser is true. 2. Observe the form. | D48: - CURRENT PASSWORD block is hidden. - Customer can set a local password using NEW PASSWORD and CONFIRM NEW PASSWORD once FE validity is satisfied. | E48: Customer has googleId and no local password; profile.isGoogleUser is true. | F48: Passed | G48: 46262 | H48: TranPLH | I48: Passed | J48: 46283 | K48: TranPLH | L48: Passed | M48: 46306 | N48: TranPLH
A49: TC-PROFILE-PWD-04 | B49: Validate required current password for normal Customer | C49: 1. Open Change Password as a normal Customer. 2. Leave CURRENT PASSWORD empty or whitespace-only. 3. Enter otherwise valid NEW PASSWORD and confirmation. | D49: - FE validity keeps Update Password disabled. - If handler validation is invoked, Current password is required. is set. - No valid PUT request proceeds from the normal UI. | E49: Customer has a local password. | F49: Passed | G49: 46262 | H49: TranPLH | I49: Passed | J49: 46283 | K49: TranPLH | L49: Passed | M49: 46306 | N49: TranPLH
A50: TC-PROFILE-PWD-05 | B50: Validate new password minimum length on Customer UI | C50: 1. Enter a valid CURRENT PASSWORD. 2. Enter NEW PASSWORD shorter than 8 characters. 3. Observe validation and submit state. | D50: - FE minimum-length check fails. - Update Password remains disabled. - Handler validation provides Minimum 8 characters required. if invoked. | E50: Change Password form is open for a normal Customer. | F50: Failed | G50: 46263 | H50: TranPLH | I50: Passed | J50: 46284 | K50: TranPLH | L50: Passed | M50: 46307 | N50: TranPLH | O50: New-password minimum validation passed after R2 retest
A51: TC-PROFILE-PWD-06 | B51: Validate uppercase and lowercase password requirement | C51: 1. Enter a NEW PASSWORD of at least 8 characters that lacks uppercase or lacks lowercase letters. 2. Observe validation and submit state. | D51: - FE complexity check fails. - Update Password remains disabled. - Handler validation provides Must contain both uppercase and lowercase letters. if invoked. | E51: Change Password form is open. | F51: Failed | G51: 46263 | H51: TranPLH | I51: Passed | J51: 46284 | K51: TranPLH | L51: Passed | M51: 46307 | N51: TranPLH | O51: Password complexity validation passed after R2 retest
A52: TC-PROFILE-PWD-07 | B52: Validate numeric-character password requirement | C52: 1. Enter a NEW PASSWORD with sufficient length, uppercase/lowercase and special character, but no number. 2. Observe validation. | D52: - FE complexity check fails. - Update Password remains disabled. - Handler validation provides Must contain at least 1 number. if invoked. | E52: Change Password form is open. | F52: Passed | G52: 46264 | H52: TranPLH | I52: Passed | J52: 46286 | K52: TranPLH | L52: Passed | M52: 46308 | N52: TranPLH
A53: TC-PROFILE-PWD-08 | B53: Validate special-character password requirement | C53: 1. Enter a NEW PASSWORD with sufficient length, uppercase/lowercase and number, but no special character. 2. Observe validation. | D53: - FE complexity check fails. - Update Password remains disabled. - Handler validation provides Must contain at least 1 special character. if invoked. | E53: Change Password form is open. | F53: Passed | G53: 46264 | H53: TranPLH | I53: Passed | J53: 46286 | K53: TranPLH | L53: Passed | M53: 46308 | N53: TranPLH
A54: TC-PROFILE-PWD-09 | B54: Reject new password equal to current password on Customer UI | C54: 1. Enter CURRENT PASSWORD. 2. Enter the same value as NEW PASSWORD while satisfying strength requirements. 3. Observe form state. | D54: - FE compares NEW PASSWORD with current.trim(). - CONFIRM NEW PASSWORD is not shown when they are equal. - Update Password remains disabled. - Same-password guidance is displayed. | E54: Normal Customer; entered password can satisfy FE strength requirements. | F54: Failed | G54: 46265 | H54: TranPLH | I54: Failed | J54: 46287 | K54: TranPLH | L54: Passed | M54: 46309 | N54: TranPLH | O54: Same-password prevention passed after R3 retest
A55: TC-PROFILE-PWD-10 | B55: Require confirmation for a valid new password | C55: 1. Enter valid CURRENT PASSWORD. 2. Enter a strong NEW PASSWORD different from current. 3. Leave CONFIRM NEW PASSWORD empty. | D55: - Confirm field is displayed after strength and difference gates pass. - Update Password remains disabled. - Handler validation provides Please confirm your new password. if invoked. | E55: Normal Customer; NEW PASSWORD passes FE strength checks. | F55: Passed | G55: 46265 | H55: TranPLH | I55: Passed | J55: 46287 | K55: TranPLH | L55: Passed | M55: 46309 | N55: TranPLH
A56: TC-PROFILE-PWD-11 | B56: Reject mismatched new-password confirmation | C56: 1. Enter valid CURRENT PASSWORD. 2. Enter a strong NEW PASSWORD. 3. Enter a different value in CONFIRM NEW PASSWORD. | D56: - Confirmation equality check fails. - Update Password remains disabled. - Handler validation provides Passwords do not match. if invoked. | E56: Change Password form is open; NEW PASSWORD passes FE strength checks. | F56: Passed | G56: 46266 | H56: TranPLH | I56: Passed | J56: 46288 | K56: TranPLH | L56: Passed | M56: 46310 | N56: TranPLH
A57: TC-PROFILE-PWD-12 | B57: Reject incorrect current password | C57: 1. Enter an incorrect CURRENT PASSWORD. 2. Enter valid strong NEW PASSWORD and matching confirmation. 3. Click Update Password. | D57: - Backend bcrypt comparison fails. - HTTP 400 returns Current password is incorrect. - FE stops loading, keeps the form and inputs, and displays the response message in the current-password error area. | E57: Normal Customer has a local password; auth token is valid. | F57: Passed | G57: 46266 | H57: TranPLH | I57: Passed | J57: 46288 | K57: TranPLH | L57: Passed | M57: 46310 | N57: TranPLH
A58: TC-PROFILE-PWD-13 | B58: Change local password successfully | C58: 1. Enter the correct CURRENT PASSWORD. 2. Enter a strong NEW PASSWORD different from current. 3. Enter matching confirmation. 4. Click Update Password. | D58: - PUT /api/profile/change-password is sent with currentPassword, newPassword and confirmNewPassword. - Backend compares current password and saves the new password using bcrypt hashing. - HTTP 200 Password changed successfully. is returned. - FE shows Password updated ✓ and closes/resets the form. | E58: Normal active Customer; correct current password; valid access token. | F58: Passed | G58: 46266 | H58: TranPLH | I58: Passed | J58: 46289 | K58: TranPLH | L58: Passed | M58: 46310 | N58: TranPLH
A59: TC-PROFILE-PWD-14 | B59: Set a local password for Google Customer without existing local password | C59: 1. Open Change Password as a Google Customer with no local password. 2. Enter a strong NEW PASSWORD and matching confirmation. 3. Click Update Password. | D59: - FE payload omits currentPassword. - Backend skips current-password compare and same-password checks for this branch. - New password is bcrypt-hashed and saved. - HTTP 200 success is returned and FE resets the form. | E59: Customer has googleId and no local password in DB; profile.isGoogleUser is true. | F59: Failed | G59: 46266 | H59: TranPLH | I59: Failed | J59: 46289 | K59: TranPLH | L59: Passed | M59: 46310 | N59: TranPLH | O59: Google local-password flow passed after R3 retest
A60: TC-PROFILE-PWD-15 | B60: Verify backend minimum-length rule through direct password API | C60: 1. Send authenticated PUT /api/profile/change-password directly with correct CURRENT PASSWORD. 2. Use a 6–7 character NEW PASSWORD different from current. 3. Send matching confirmation. | D60: - Backend validator and User schema accept minimum length 6. - Backend does not enforce the Customer UI complexity checks. - Request can continue to controller save when other backend checks pass. | E60: Authenticated normal Customer; correct current password; direct API request. | F60: Passed | G60: 46267 | H60: TranPLH | I60: Passed | J60: 46290 | K60: TranPLH | L60: Passed | M60: 46311 | N60: TranPLH | O60: FE requires min 8 + complexity; backend requires min 6
A61: TC-PROFILE-PWD-16 | B61: Retry Change Password after expired access token | C61: 1. Submit valid Change Password values with an expired access token. 2. Allow the first request to return HTTP 401 TOKEN_EXPIRED. 3. Allow token refresh to succeed. | D61: - apiFetch refreshes the access token once. - New access token is stored. - PUT /api/profile/change-password is retried. - Password update proceeds if retried request passes backend validation and controller checks. | E61: Expired access token; valid refresh path; password inputs otherwise valid. | F61: Failed | G61: 46267 | H61: TranPLH | I61: Passed | J61: 46290 | K61: TranPLH | L61: Passed | M61: 46311 | N61: TranPLH | O61: Expired-token password update passed after R2 retest
A62: TC-PROFILE-PWD-17 | B62: Preserve Change Password form on network failure | C62: 1. Enter valid Change Password values. 2. Submit the request. 3. Cause a network/fetch failure. | D62: - cpLoading returns to false. - Form remains open and input values are retained. - Connection error message is assigned to the current error slot. | E62: Valid Change Password inputs; network request fails. | F62: Passed | G62: 46267 | H62: TranPLH | I62: Passed | J62: 46291 | K62: TranPLH | L62: Passed | M62: 46311 | N62: TranPLH
A63: TC-PROFILE-PWD-18 | B63: Handle backend compare/hash/save processing failure | C63: 1. Submit a valid Change Password request. 2. Cause backend DB, bcrypt, or user.save processing to throw. | D63: - Controller forwards error to the global error handler. - No HTTP 200 success response is returned. - FE exits loading state and keeps the form open with the returned message in the current error slot. | E63: Authenticated Customer; backend failure occurs during password processing. | F63: Failed | G63: 46267 | H63: TranPLH | I63: Passed | J63: 46291 | K63: TranPLH | L63: Passed | M63: 46311 | N63: TranPLH | O63: Password update server-error handling passed after R2 retest

Sheet 8. Account Management
A2: Feature | B2: Account Management | R2: Passed
A3: Test requirement | B3: To verify Staff/Admin Account Management including access control, account listing and viewing, search/filter/sort/pagination, account editing, block/unblock, Admin delete, authentication, validation, database behavior, and error handling. | R3: Failed
A4: Number of TCs | B4: =COUNTIF(A21:A65, "TC-*") -> 41 | R4: Pending
A5: Testing Round | B5: Passed | C5: Failed | D5: Pending | E5: N/A | R5: N/A
A6: Round 1 | B6: =COUNTIF(F11:F67, B5) -> 30 | C6: =COUNTIF(F11:F67, C5) -> 22 | D6: =COUNTIF(F11:F67, D5) -> 0 | E6: =COUNTIF(F11:F67, E5) -> 0
A7: Round 2 | B7: =COUNTIF(I11:I67, B5) -> 46 | C7: =COUNTIF(I11:I67, C5) -> 6 | D7: =COUNTIF(I11:I67, D5) -> 0 | E7: =COUNTIF(I11:I67, E5) -> 0
A8: Round 3 | B8: =COUNTIF(L11:L67, B5) -> 52 | C8: =COUNTIF(L11:L67, C5) -> 0 | D8: =COUNTIF(L11:L67, D5) -> 0 | E8: =COUNTIF(L11:L67, E5) -> 0
A10: Test Case ID | B10: Test Case Description | C10: Test Case Procedure | D10: Expected Results | E10: Pre-conditions | F10: Round 1 | G10: Test date | H10: Tester | I10: Round 2 | J10: Test date | K10: Tester | L10: Round 3 | M10: Test date | N10: Tester | O10: Note
A11: Function 1: Access & Load Accounts
A12: TC-ACCOUNT-ACCESS-01 | B12: Redirect unauthenticated actor without cached session | C12: 1. Remove the cached actor session. 2. Navigate to /staff/accounts or /admin/accounts. | D12: - ProtectedRoute redirects to login and preserves the return URL. - Account Management page is not rendered. | E12: No cached Staff/Admin actor exists. | F12: Passed | G12: 46255 | H12: TranPLH | I12: Passed | J12: 46273 | K12: TranPLH | L12: Passed | M12: 46297 | N12: TranPLH
A13: TC-ACCOUNT-ACCESS-02 | B13: Reject frontend access for cached actor with wrong role | C13: 1. Use a cached user whose role does not match the target Account Management route. 2. Navigate to the route. | D13: - Frontend redirects to /unauthorized. - Account Management content is not displayed. | E13: Cached user exists but role is not permitted for the selected route. | F13: Passed | G13: 46255 | H13: TranPLH | I13: Passed | J13: 46273 | K13: TranPLH | L13: Passed | M13: 46297 | N13: TranPLH
A14: TC-ACCOUNT-ACCESS-03 | B14: Reject Account Management API request with missing access token | C14: 1. Open Account Management with no usable access token. 2. Trigger list request. | D14: - Request reaches backend without a valid Bearer token. - Backend returns HTTP 401: Access denied. No token provided. - No protected account data is returned. | E14: Account Management page is reachable; localStorage access token is missing. | F14: Failed | G14: 46256 | H14: TranPLH | I14: Passed | J14: 46274 | K14: TranPLH | L14: Passed | M14: 46298 | N14: TranPLH | O14: Missing-token access handling passed after R2 retest
A15: TC-ACCOUNT-ACCESS-04 | B15: Handle invalid or expired access token | C15: 1. Trigger Account Management request with invalid JWT, then with expired JWT. 2. Observe apiFetch behavior. | D15: - Invalid token returns HTTP 401 Invalid token. - Expired token returns HTTP 401 with TOKEN_EXPIRED. - Shared API wrapper attempts refresh only on the configured 401 flow. | E15: Actor session exists; supplied access token is invalid or expired. | F15: Failed | G15: 46256 | H15: TranPLH | I15: Failed | J15: 46274 | K15: TranPLH | L15: Passed | M15: 46298 | N15: TranPLH | O15: Invalid/expired-token recovery passed after R3 retest
A16: TC-ACCOUNT-ACCESS-05 | B16: Reject token whose actor User record no longer exists | C16: 1. Use a valid JWT that references a deleted actor. 2. Request Account Management API. | D16: - Backend returns HTTP 401. - Response states that the User belonging to the token no longer exists. | E16: JWT verifies but referenced actor User record is missing. | F16: Passed | G16: 46257 | H16: TranPLH | I16: Passed | J16: 46275 | K16: TranPLH | L16: Passed | M16: 46299 | N16: TranPLH
A17: TC-ACCOUNT-ACCESS-06 | B17: Reject inactive Staff/Admin actor | C17: 1. Use valid credentials for an inactive actor. 2. Request Account Management API. | D17: - Backend returns HTTP 403. - Response states the account has been deactivated. - Protected data is not returned. | E17: Actor User exists but is inactive. | F17: Passed | G17: 46257 | H17: TranPLH | I17: Passed | J17: 46275 | K17: TranPLH | L17: Passed | M17: 46299 | N17: TranPLH
A18: TC-ACCOUNT-ACCESS-07 | B18: Reject authenticated actor without backend permission | C18: 1. Authenticate with a role not allowed by the target backend route. 2. Call the Account Management endpoint. | D18: - authorize middleware returns HTTP 403. - Message: Forbidden: You do not have permission to perform this action. | E18: Valid authenticated actor has an unauthorized role. | F18: Failed | G18: 46258 | H18: TranPLH | I18: Passed | J18: 46276 | K18: TranPLH | L18: Passed | M18: 46300 | N18: TranPLH | O18: Backend role authorization passed after R2 retest
A19: TC-ACCOUNT-ACCESS-08 | B19: Retry Account Management request after successful token refresh | C19: 1. Trigger an Account Management API request that returns 401 TOKEN_EXPIRED. 2. Allow refresh to return a new access token. | D19: - New access token is stored. - Original request is retried once. - If refresh fails, auth is cleared and browser returns to login. - A retried 401 does not start another refresh loop. | E19: Expired access token; refresh flow is available. | F19: Failed | G19: 46258 | H19: TranPLH | I19: Failed | J19: 46276 | K19: TranPLH | L19: Passed | M19: 46300 | N19: TranPLH | O19: Token refresh retry flow passed after R3 retest
A20: TC-ACCOUNT-ACCESS-09 | B20: Render loading state while account list is being fetched | C20: 1. Open Staff or Admin Account Management. 2. Keep the list request pending briefly. | D20: - Loading/skeleton state is rendered while request is pending. - Loading state ends when the request finishes. | E20: Authorized Staff/Admin actor; list request has not completed. | F20: Passed | G20: 46259 | H20: TranPLH | I20: Passed | J20: 46277 | K20: TranPLH | L20: Passed | M20: 46301 | N20: TranPLH
A21: TC-ACCOUNT-ACCESS-10 | B21: Load Admin account list successfully and preserve prior list on HTTP failure | C21: 1. As Admin, load GET /api/admin/users successfully. 2. Trigger Refresh and make a later HTTP load fail. | D21: - Successful load replaces Admin account list with response data. - On later HTTP failure, the previously loaded list remains available. - No dedicated Admin load-error panel is required by the page. | E21: Admin is authenticated; initial list can load successfully. | F21: Failed | G21: 46259 | H21: TranPLH | I21: Passed | J21: 46277 | K21: TranPLH | L21: Passed | M21: 46301 | N21: TranPLH | O21: Admin list failure handling passed after R2 retest
A22: TC-ACCOUNT-ACCESS-11 | B22: Load Staff customer list and handle unavailable customer data | C22: 1. As Staff, load GET /api/staff/users. 2. Repeat with request failure/unavailable response. | D22: - Success displays customer accounts only. - Failure clears customer list and open panel. - UI shows Customer data unavailable and an error state. | E22: Staff is authenticated. | F22: Failed | G22: 46260 | H22: TranPLH | I22: Failed | J22: 46278 | K22: TranPLH | L22: Passed | M22: 46302 | N22: TranPLH | O22: Staff unavailable-data handling passed after R3 retest
A23: TC-ACCOUNT-ACCESS-12 | B23: Keep account in list when UserDetail is missing | C23: 1. Prepare an account without UserDetail. 2. Load Staff/Admin Account Management list. | D23: - Aggregation keeps the account because preserveNullAndEmptyArrays is enabled. - UI uses display fallbacks for missing detail fields. | E23: User exists; UserDetail is missing. | F23: Passed | G23: 46260 | H23: TranPLH | I23: Passed | J23: 46278 | K23: TranPLH | L23: Passed | M23: 46302 | N23: TranPLH
A24: TC-ACCOUNT-ACCESS-13 | B24: Display fallback values for missing profile data | C24: 1. Load an account with missing name/avatar/phone/date values. 2. Observe the table/detail panel. | D24: - Name falls back to username, then email, then '-'. - Avatar uses initials fallback. - Phone shows '-' or Not provided. - Missing date shows N/A. | E24: Loaded account has one or more missing display fields. | F24: Passed | G24: 46261 | H24: TranPLH | I24: Passed | J24: 46279 | K24: TranPLH | L24: Passed | M24: 46303 | N24: TranPLH
A25: Function 2: Search / Filter / Sort / Pagination / View
A26: TC-ACCOUNT-VIEW-01 | B26: Show empty state when no accounts match current filters | C26: 1. Apply search/filter values that match no loaded rows. | D26: - Admin shows No accounts match your filters. - Staff shows No customers match your filters. - No row is rendered. | E26: Account list has loaded; local filters produce zero rows. | F26: Failed | G26: 46261 | H26: TranPLH | I26: Passed | J26: 46279 | K26: TranPLH | L26: Passed | M26: 46303 | N26: TranPLH | O26: Empty filtered-state rendering passed after R2 retest
A27: TC-ACCOUNT-VIEW-02 | B27: Search loaded accounts by name, email, or phone | C27: 1. Enter search text matching profile name, email, or phone. 2. Try a nonmatching value. | D27: - Search runs locally on loaded data. - Matching rows remain; nonmatching rows are hidden. - Name/email comparisons are case-normalized; username is not a search field. | E27: Account list is loaded. | F27: Passed | G27: 46262 | H27: TranPLH | I27: Passed | J27: 46280 | K27: TranPLH | L27: Passed | M27: 46304 | N27: TranPLH
A28: TC-ACCOUNT-VIEW-03 | B28: Filter Admin accounts by role | C28: 1. As Admin, choose All Roles, Customer, Staff, and Admin filters. | D28: - Role filter is applied locally. - Only rows matching the selected role remain when a specific role is selected. | E28: Admin Account Management list is loaded. | F28: Passed | G28: 46262 | H28: TranPLH | I28: Passed | J28: 46280 | K28: TranPLH | L28: Passed | M28: 46304 | N28: TranPLH
A29: TC-ACCOUNT-VIEW-04 | B29: Filter accounts by Active or Blocked status | C29: 1. Select Active. 2. Select Blocked. 3. Return to All Status. | D29: - Active matches status===true. - Blocked matches status===false. - All Status restores all loaded rows. | E29: Account list is loaded. | F29: Passed | G29: 46263 | H29: TranPLH | I29: Passed | J29: 46281 | K29: TranPLH | L29: Passed | M29: 46305 | N29: TranPLH
A30: TC-ACCOUNT-VIEW-05 | B30: Sort accounts by newest and oldest | C30: 1. Select newest sort. 2. Select oldest sort. | D30: - Local createdAt comparator changes row order. - Changing sort resets the current page to page 1. | E30: Account list contains multiple createdAt values. | F30: Failed | G30: 46263 | H30: TranPLH | I30: Passed | J30: 46281 | K30: TranPLH | L30: Passed | M30: 46305 | N30: TranPLH | O30: Sort and page-reset behavior passed after R2 retest
A31: TC-ACCOUNT-VIEW-06 | B31: Navigate account pagination boundaries | C31: 1. Load more than 10 filtered accounts. 2. Use Next and Prev. 3. Reach first and last pages. | D31: - Page size is 10 rows. - Prev is disabled on the first page. - Next is disabled on the last page. - totalPages never drops below 1. | E31: Loaded/filtered list contains more than 10 rows. | F31: Failed | G31: 46264 | H31: TranPLH | I31: Passed | J31: 46282 | K31: TranPLH | L31: Passed | M31: 46306 | N31: TranPLH | O31: Pagination boundary handling passed after R2 retest
A32: TC-ACCOUNT-VIEW-07 | B32: Open and close account detail panel from loaded row | C32: 1. Click/open an account row/detail action. 2. Close the detail panel. | D32: - Panel opens using the already loaded account object; no separate detail API is called. - Opening resets edit/confirmation state. - Closing clears the active panel. | E32: Account row exists in the loaded list. | F32: Passed | G32: 46264 | H32: TranPLH | I32: Passed | J32: 46282 | K32: TranPLH | L32: Passed | M32: 46306 | N32: TranPLH
A33: TC-ACCOUNT-VIEW-08 | B33: Open account panel using userId query parameter | C33: 1. Navigate to Account Management with ?userId=<loaded-id>. 2. Repeat with an id not present in loaded data. | D33: - Matching loaded id opens its panel and removes the query parameter. - Unmatched userId does not open a panel and query remains unchanged. | E33: Account list is loaded; target id may or may not be present. | F33: Failed | G33: 46265 | H33: TranPLH | I33: Passed | J33: 46283 | K33: TranPLH | L33: Passed | M33: 46307 | N33: TranPLH | O33: userId deep-link panel handling passed after R2 retest
A34: TC-ACCOUNT-VIEW-09 | B34: Calculate account statistic cards from loaded data | C34: 1. Load a known mix of accounts. 2. Observe total/current-month/blocked/pending statistic cards. | D34: - Total and blocked counts are derived locally. - Current-month count uses createdAt. - Pending count follows the page's emailVerified===false condition. | E34: Account list is loaded with known statuses and dates. | F34: Passed | G34: 46265 | H34: TranPLH | I34: Passed | J34: 46283 | K34: TranPLH | L34: Passed | M34: 46307 | N34: TranPLH
A35: TC-ACCOUNT-VIEW-10 | B35: Refresh Account Management list | C35: 1. Click Refresh. | D35: - Page invokes the same list loader again. - Success and failure behavior match the normal list-load path. | E35: Authorized actor is on Account Management. | F35: Passed | G35: 46266 | H35: TranPLH | I35: Passed | J35: 46284 | K35: TranPLH | L35: Passed | M35: 46308 | N35: TranPLH
A36: Function 3: Edit Account
A37: TC-ACCOUNT-EDIT-01 | B37: Prevent Staff from editing non-customer target | C37: 1. As Staff, attempt to open/edit a target whose role is not customer. | D37: - Staff frontend shows permission feedback and stops the action. - Backend update/status routes independently reject non-customer targets with HTTP 403. | E37: Staff is authenticated; non-customer target is available by crafted/direct request. | F37: Passed | G37: 46266 | H37: TranPLH | I37: Passed | J37: 46284 | K37: TranPLH | L37: Passed | M37: 46308 | N37: TranPLH
A38: TC-ACCOUNT-EDIT-02 | B38: Enter account edit mode with current values | C38: 1. Open an editable account. 2. Click Edit Customer/Edit User. | D38: - Edit form populates Full Name and Phone. - Admin also receives current role. - Staff role is fixed to customer. | E38: Authorized actor has opened a manageable target. | F38: Passed | G38: 46267 | H38: TranPLH | I38: Passed | J38: 46285 | K38: TranPLH | L38: Passed | M38: 46309 | N38: TranPLH
A39: TC-ACCOUNT-EDIT-03 | B39: Cancel account edit without sending update | C39: 1. Enter edit mode. 2. Change fields. 3. Click Cancel. 4. Re-enter edit mode. | D39: - No PUT request is sent. - Editing closes and save state resets. - Re-entering repopulates current persisted values. | E39: Edit mode is open with unsaved changes. | F39: Failed | G39: 46267 | H39: TranPLH | I39: Passed | J39: 46285 | K39: TranPLH | L39: Passed | M39: 46309 | N39: TranPLH | O39: Edit cancel/reset flow passed after R2 retest
A40: TC-ACCOUNT-EDIT-04 | B40: Validate required Full Name | C40: 1. Clear Full Name or enter whitespace only. 2. Click Save Changes. | D40: - Input is trimmed for validation. - UI shows Full Name is required. - PUT request is not sent. | E40: Edit mode is open. | F40: Passed | G40: 46267 | H40: TranPLH | I40: Passed | J40: 46286 | K40: TranPLH | L40: Passed | M40: 46310 | N40: TranPLH
A41: TC-ACCOUNT-EDIT-05 | B41: Validate Full Name maximum length boundary | C41: 1. Enter a valid 50-character name and save. 2. Enter a 51-character name and save. | D41: - 50-character name passes the length check when regex also passes. - 51-character name is rejected with Name cannot exceed 50 characters. - Rejected input sends no PUT. | E41: Edit mode is open; other fields are valid. | F41: Failed | G41: 46267 | H41: TranPLH | I41: Passed | J41: 46286 | K41: TranPLH | L41: Passed | M41: 46310 | N41: TranPLH | O41: Name length validation passed after R2 retest
A42: TC-ACCOUNT-EDIT-06 | B42: Reject Full Name containing digits or special characters | C42: 1. Enter Full Name containing numbers or special characters. 2. Save. | D42: - FE regex rejects the name. - UI shows Name cannot contain numbers or special characters. - No PUT request is sent. | E42: Edit mode is open. | F42: Passed | G42: 46267 | H42: TranPLH | I42: Passed | J42: 46287 | K42: TranPLH | L42: Passed | M42: 46311 | N42: TranPLH
A43: TC-ACCOUNT-EDIT-07 | B43: Allow empty phone and validate non-empty Vietnamese phone | C43: 1. Save with Phone empty. 2. Enter invalid non-empty phone and save. 3. Enter a valid 03/05/07/08/09 10-digit phone and save. | D43: - Empty phone is allowed. - Invalid truthy phone is rejected with Please enter a valid Vietnamese phone number. - Valid phone passes FE validation. - Validation removes spaces/hyphens only for checking; payload sends original phone string. | E43: Edit mode is open; Full Name is valid. | F43: Failed | G43: 46267 | H43: TranPLH | I43: Failed | J43: 46287 | K43: TranPLH | L43: Passed | M43: 46311 | N43: TranPLH | O43: Phone validation passed after R3 retest
A44: TC-ACCOUNT-EDIT-08 | B44: Require User Role in Admin edit form | C44: 1. As Admin, clear/omit the role selection in edit state. 2. Attempt Save Changes. | D44: - Admin UI shows User Role is required. - Update request is not sent. | E44: Admin edit form is open. | F44: Failed | G44: 46267 | H44: TranPLH | I44: Passed | J44: 46288 | K44: TranPLH | L44: Passed | M44: 46312 | N44: TranPLH | O44: Admin role required validation passed after R2 retest
A45: TC-ACCOUNT-EDIT-09 | B45: Show saving state during account update | C45: 1. Submit a valid account edit. 2. Keep response pending. | D45: - Save state becomes saving. - Button shows Saving... and is disabled. - Cancel remains available. | E45: Valid edit values; authorized actor. | F45: Passed | G45: 46267 | H45: TranPLH | I45: Passed | J45: 46288 | K45: TranPLH | L45: Passed | M45: 46312 | N45: TranPLH
A46: TC-ACCOUNT-EDIT-10 | B46: Return 404 when edited target no longer exists | C46: 1. Open edit for a target. 2. Remove the target before submission or call update/status/delete with a missing id. | D46: - Backend returns HTTP 404 User not found. - No later mutation executes for the missing target. | E46: Authorized actor; target id does not resolve. | F46: Passed | G46: 46267 | H46: TranPLH | I46: Passed | J46: 46289 | K46: TranPLH | L46: Passed | M46: 46313 | N46: TranPLH
A47: TC-ACCOUNT-EDIT-11 | B47: Ignore Staff role/status values submitted through update payload | C47: 1. As Staff, send PUT /api/staff/users/:id with firstName/lastName/phone plus role/status fields. | D47: - Staff controller only applies firstName, lastName and phone. - role/status values in update payload are ignored. - Target must already be a customer. | E47: Staff is authenticated; target role is customer. | F47: Passed | G47: 46267 | H47: TranPLH | I47: Passed | J47: 46289 | K47: TranPLH | L47: Passed | M47: 46313 | N47: TranPLH
A48: TC-ACCOUNT-EDIT-12 | B48: Apply or preserve Admin role/status through update API | C48: 1. As Admin, send update with role/status supplied. 2. Repeat while omitting one or both fields. | D48: - Supplied role/status are assigned to User. - Omitted fields remain unchanged. - User.save enforces User schema constraints. | E48: Admin is authenticated; target User exists. | F48: Passed | G48: 46267 | H48: TranPLH | I48: Passed | J48: 46290 | K48: TranPLH | L48: Passed | M48: 46313 | N48: TranPLH
A49: TC-ACCOUNT-EDIT-13 | B49: Reject invalid Admin role value through direct API | C49: 1. Send Admin update with role value outside allowed enum. | D49: - User schema validation fails. - Global error handler returns HTTP 400 Validation error/Cast-style validation response. - Normal UI cannot select guest even though schema enum includes guest. | E49: Admin is authenticated; direct API request targets existing User. | F49: Failed | G49: 46267 | H49: TranPLH | I49: Passed | J49: 46290 | K49: TranPLH | L49: Passed | M49: 46313 | N49: TranPLH | O49: Invalid Admin role handling passed after R2 retest
A50: TC-ACCOUNT-EDIT-14 | B50: Create UserDetail during account edit when detail is missing | C50: 1. Edit a target that has no UserDetail. 2. Submit valid detail values. | D50: - Controller creates missing UserDetail and returns refreshed account data. | E50: Target User exists; UserDetail is missing. | F50: Failed | G50: 46267 | H50: TranPLH | I50: Passed | J50: 46291 | K50: TranPLH | L50: Passed | M50: 46313 | N50: TranPLH | O50: Missing UserDetail creation flow passed after R2 retest
A51: TC-ACCOUNT-EDIT-15 | B51: Update existing UserDetail during account edit | C51: 1. Edit a target with existing UserDetail. 2. Save valid changed Full Name/Phone. | D51: - Existing UserDetail fields are updated. - Refreshed account object is returned. | E51: Target User and UserDetail exist. | F51: Passed | G51: 46267 | H51: TranPLH | I51: Passed | J51: 46291 | K51: TranPLH | L51: Passed | M51: 46313 | N51: TranPLH
A52: TC-ACCOUNT-EDIT-16 | B52: Preserve omitted detail fields and allow supplied empty strings | C52: 1. Call update while omitting one detail field. 2. Call again with an explicitly supplied empty string. | D52: - Omitted detail fields are preserved by controller behavior. - Supplied empty strings are allowed by detail schema. | E52: Authorized actor; target exists. | F52: Passed | G52: 46267 | H52: TranPLH | I52: Passed | J52: 46292 | K52: TranPLH | L52: Passed | M52: 46313 | N52: TranPLH
A53: TC-ACCOUNT-EDIT-17 | B53: Save unchanged values and allow duplicate phone by current backend rules | C53: 1. Save edit without changing values. 2. Save a phone already present on another account using direct API. | D53: - No dirty guard blocks unchanged save. - Account update still executes. - Account Management handlers have no duplicate-phone business rule or phone normalization helper. | E53: Authorized actor; target exists. | F53: Passed | G53: 46267 | H53: TranPLH | I53: Passed | J53: 46292 | K53: TranPLH | L53: Passed | M53: 46313 | N53: TranPLH
A54: TC-ACCOUNT-EDIT-18 | B54: Update account successfully | C54: 1. Submit valid account changes. | D54: - Backend returns HTTP 200 with updated account. - UI replaces list/panel object and closes edit. - Toast: Account updated successfully. - Banner: Changes saved successfully!. | E54: Authorized actor; valid edit data; target exists. | F54: Passed | G54: 46267 | H54: TranPLH | I54: Passed | J54: 46293 | K54: TranPLH | L54: Passed | M54: 46313 | N54: TranPLH
A55: TC-ACCOUNT-EDIT-19 | B55: Handle update HTTP or network failure | C55: 1. Submit valid account edit. 2. Return non-success HTTP or cause network failure. | D55: - Edit form and draft are retained. - UI shows Failed to update account and Failed to save changes. - Save state returns to idle after the page delay. | E55: Valid edit submitted; update fails. | F55: Failed | G55: 46267 | H55: TranPLH | I55: Passed | J55: 46293 | K55: TranPLH | L55: Passed | M55: 46313 | N55: TranPLH | O55: Update HTTP/network failure handling passed after R2 retest
A56: TC-ACCOUNT-EDIT-20 | B56: Handle unexpected update exception | C56: 1. Trigger an unexpected exception in update handler path. | D56: - Catch path sets error state. - UI shows An error occurred. - Edit is not reported as successful. | E56: Edit submission reaches unexpected exception path. | F56: Passed | G56: 46267 | H56: TranPLH | I56: Passed | J56: 46294 | K56: TranPLH | L56: Passed | M56: 46313 | N56: TranPLH
A57: TC-ACCOUNT-EDIT-21 | B57: Synchronize cached current actor after self-edit | C57: 1. As Admin, edit the currently signed-in Admin account. 2. Complete update successfully. | D57: - Updated current-user data is merged into session cache. - Auth-change event is dispatched so shared UI can refresh. | E57: Admin edits own account and update succeeds. | F57: Passed | G57: 46267 | H57: TranPLH | I57: Passed | J57: 46294 | K57: TranPLH | L57: Passed | M57: 46313 | N57: TranPLH
A58: Function 4: Block / Unblock Account
A59: TC-ACCOUNT-STATUS-01 | B59: Show block confirmation for active target and direct unblock for blocked target | C59: 1. Select an active target and choose Block. 2. Select a blocked target and choose Unblock. | D59: - Active target opens a confirmation step before request. - Blocked target triggers unblock request directly. | E59: Authorized actor; target is manageable. | F59: Passed | G59: 46267 | H59: TranPLH | I59: Passed | J59: 46295 | K59: TranPLH | L59: Passed | M59: 46313 | N59: TranPLH
A60: TC-ACCOUNT-STATUS-02 | B60: Cancel or confirm Block action | C60: 1. Open Block confirmation. 2. Click Cancel. 3. Repeat and click Confirm Block. | D60: - Cancel sends no status request. - Confirm sends PUT status request with status:false. - Confirmation closes immediately when request starts. | E60: Target account is active. | F60: Failed | G60: 46267 | H60: TranPLH | I60: Failed | J60: 46295 | K60: TranPLH | L60: Passed | M60: 46313 | N60: TranPLH | O60: Block confirmation flow passed after R3 retest
A61: TC-ACCOUNT-STATUS-03 | B61: Update account status successfully or handle failure | C61: 1. Block/unblock a manageable target successfully. 2. Repeat with backend failure. | D61: - Success updates local row/panel status and shows Account blocked successfully or Account unblocked successfully. - Failure leaves local status unchanged and shows Failed to update account status. | E61: Authorized actor; target exists. | F61: Passed | G61: 46267 | H61: TranPLH | I61: Passed | J61: 46295 | K61: TranPLH | L61: Passed | M61: 46313 | N61: TranPLH
A62: TC-ACCOUNT-STATUS-04 | B62: Allow Admin self role/status update according to current backend implementation | C62: 1. As Admin, update own role or status through supported Admin management endpoint. | D62: - No self-protection guard blocks update/status handlers. - Mutation can succeed subject to schema/auth rules. - Later access reflects current User role/status during authentication. | E62: Admin is authenticated and targets own User id. | F62: Failed | G62: 46267 | H62: TranPLH | I62: Passed | J62: 46295 | K62: TranPLH | L62: Passed | M62: 46313 | N62: TranPLH | O62: Admin self role/status update behavior passed after R2 retest
A63: Function 5: Delete Account (Admin)
A64: TC-ACCOUNT-DELETE-01 | B64: Cancel or confirm Admin Delete User action | C64: 1. As Admin, open Delete User confirmation. 2. Cancel. 3. Repeat and confirm delete. | D64: - Cancel sends no DELETE request. - Confirm sends DELETE /api/admin/users/:id. - Confirmation closes immediately as request begins. | E64: Admin is authenticated; target User exists. | F64: Passed | G64: 46267 | H64: TranPLH | I64: Passed | J64: 46295 | K64: TranPLH | L64: Passed | M64: 46313 | N64: TranPLH
A65: TC-ACCOUNT-DELETE-02 | B65: Prevent Admin from deleting own account | C65: 1. As Admin, attempt DELETE on own user id. | D65: - Backend rejects before cascade. - HTTP 400 message: You cannot delete your own admin account. - Own User record is not deleted. | E65: Admin is authenticated and targets own id. | F65: Failed | G65: 46267 | H65: TranPLH | I65: Passed | J65: 46295 | K65: TranPLH | L65: Passed | M65: 46313 | N65: TranPLH | O65: Admin self-delete protection passed after R2 retest
A66: TC-ACCOUNT-DELETE-03 | B66: Delete another account and associated data successfully | C66: 1. As Admin, confirm deletion of another target with linked records. | D66: - Backend performs configured cascade/unlink operations sequentially. - Sessions are retained with userId:null. - Reserved slot references are cleared as implemented. - Target User is deleted and AdminActionLog is created. - UI removes row, closes matching panel, and shows User deleted successfully. | E66: Admin is authenticated; target is not self and has linked data. | F66: Failed | G66: 46267 | H66: TranPLH | I66: Failed | J66: 46295 | K66: TranPLH | L66: Passed | M66: 46313 | N66: TranPLH | O66: Delete cascade behavior passed after R3 retest
A67: TC-ACCOUNT-DELETE-04 | B67: Handle delete/database failure without transaction rollback guarantee | C67: 1. Trigger a DB or audit-log failure after one or more delete cascade steps have already completed. | D67: - Backend returns an error instead of success. - No encompassing transaction guarantees rollback of earlier writes. - UI keeps the row unless success response was received and shows backend/fallback error. | E67: Admin deletion has started; a later cascade or audit operation fails. | F67: Failed | G67: 46267 | H67: TranPLH | I67: Passed | J67: 46295 | K67: TranPLH | L67: Passed | M67: 46313 | N67: TranPLH | O67: Partial-mutation error handling passed after R2 retest

Sheet 9. Parking Services
A2: Feature | B2: Parking Services | R2: Passed
A3: Test requirement | B3: Verify Admin Manage Parking Services: service catalog viewing, create, image upload/replacement, edit and active/inactive status, delete, validation, authorization, and error handling. | R3: Failed
A4: Number of TCs | B4: =COUNTIF(A21:A53, "TC-*") -> 29 | R4: Pending
A5: Testing Round | B5: Passed | C5: Failed | D5: Pending | E5: N/A | R5: N/A
A6: Round 1 | B6: =COUNTIF(F11:F53, B5) -> 24 | C6: =COUNTIF(F11:F53, C5) -> 14 | D6: =COUNTIF(F11:F53, D5) -> 0 | E6: =COUNTIF(F11:F53, E5) -> 0
A7: Round 2 | B7: =COUNTIF(I11:I53, B5) -> 34 | C7: =COUNTIF(I11:I53, C5) -> 4 | D7: =COUNTIF(I11:I53, D5) -> 0 | E7: =COUNTIF(I11:I53, E5) -> 0
A8: Round 3 | B8: =COUNTIF(L11:L53, B5) -> 38 | C8: =COUNTIF(L11:L53, C5) -> 0 | D8: =COUNTIF(L11:L53, D5) -> 0 | E8: =COUNTIF(L11:L53, E5) -> 0
A10: Test Case ID | B10: Test Case Description | C10: Test Case Procedure | D10: Expected Results | E10: Pre-conditions | F10: Round 1 | G10: Test date | H10: Tester | I10: Round 2 | J10: Test date | K10: Tester | L10: Round 3 | M10: Test date | N10: Tester | O10: Note
A11: Function 1: Service List, Search, Filter & Detail
A12: TC-SERVICE-VIEW-01 | B12: Access Manage Parking Services route with Admin/non-Admin/missing cached user | C12: 1. Open /admin/services as Admin. 2. Repeat with a cached non-Admin role. 3. Repeat with no cached user. | D12: - Admin can render AdminServiceManager. - Wrong cached role is redirected to /unauthorized. - Missing cached user is redirected to login with return URL. | E12: ProtectedRoute is configured for /admin/services. | F12: Passed | G12: 46255 | H12: TranPLH | I12: Passed | J12: 46273 | K12: TranPLH | L12: Passed | M12: 46297 | N12: TranPLH
A13: TC-SERVICE-VIEW-02 | B13: Reject Parking Service mutations from unauthorized Staff/Customer | C13: 1. Authenticate as Staff or Customer. 2. Call POST, PUT, or DELETE /api/admin/services endpoints. | D13: - Backend authorize(admin) returns HTTP 403. - Service mutation controller is not executed. | E13: Valid authenticated non-Admin account. | F13: Failed | G13: 46255 | H13: TranPLH | I13: Passed | J13: 46273 | K13: TranPLH | L13: Passed | M13: 46297 | N13: TranPLH | O13: Mutation role authorization passed after R2 retest
A14: TC-SERVICE-VIEW-03 | B14: Handle token/account failures for protected create/update/delete requests | C14: 1. Call protected service mutation with missing/invalid/expired token. 2. Repeat with missing or inactive actor account. 3. Compare create/update with delete request behavior. | D14: - Shared backend auth returns the corresponding 401/403 response. - Create/update use native fetch and do not automatically refresh expired token. - Delete uses apiFetch and can follow shared 401 refresh/retry behavior. | E14: Protected service mutation endpoint is called. | F14: Failed | G14: 46256 | H14: TranPLH | I14: Failed | J14: 46274 | K14: TranPLH | L14: Passed | M14: 46298 | N14: TranPLH | O14: Protected create/update token handling passed after R3 retest
A15: TC-SERVICE-VIEW-04 | B15: Return active-only or all services based on activeOnly query | C15: 1. Call GET /api/services without activeOnly=false. 2. Call GET /api/services?activeOnly=false. | D15: - Default/non-false query returns active services only. - Literal activeOnly=false returns both active and inactive services. - No Admin role is required for this read endpoint. | E15: Service records contain both active and inactive entries. | F15: Passed | G15: 46256 | H15: TranPLH | I15: Passed | J15: 46274 | K15: TranPLH | L15: Passed | M15: 46298 | N15: TranPLH
A16: TC-SERVICE-VIEW-05 | B16: Load management service list successfully with loading state | C16: 1. Open /admin/services. 2. Keep list request pending briefly. 3. Allow GET /api/services?activeOnly=false to succeed. | D16: - Loading state is shown while request is pending. - Successful response populates services. - Main spinner is used when loading and list is empty. | E16: Admin is authenticated and management page is mounted. | F16: Passed | G16: 46257 | H16: TranPLH | I16: Passed | J16: 46275 | K16: TranPLH | L16: Passed | M16: 46299 | N16: TranPLH
A17: TC-SERVICE-VIEW-06 | B17: Handle service list HTTP/network failure while preserving prior list | C17: 1. Load services successfully. 2. Trigger another list load that fails by HTTP/network/exception. | D17: - Error toast uses backend message or Failed to fetch services fallback. - Previously loaded services remain available. - Loading ends after failure. | E17: Admin page already has loaded services. | F17: Failed | G17: 46257 | H17: TranPLH | I17: Passed | J17: 46275 | K17: TranPLH | L17: Passed | M17: 46299 | N17: TranPLH | O17: Service-list failure handling passed after R2 retest
A18: TC-SERVICE-VIEW-07 | B18: Search services locally by name or description | C18: 1. Enter search text matching service name. 2. Enter text matching description. 3. Enter nonmatching text. | D18: - Search is performed locally using lowercase substring checks on name/description. - Matching services remain visible; nonmatching services are filtered out. - Search text is not trimmed before comparison. | E18: Service list is loaded. | F18: Passed | G18: 46258 | H18: TranPLH | I18: Passed | J18: 46276 | K18: TranPLH | L18: Passed | M18: 46300 | N18: TranPLH
A19: TC-SERVICE-VIEW-08 | B19: Filter services by Active/Inactive status | C19: 1. Select All Status. 2. Select Active Only. 3. Select Inactive Only. | D19: - Filtering is local. - Active Only keeps truthy isActive values. - Inactive Only keeps falsy isActive values. | E19: Service list is loaded. | F19: Passed | G19: 46258 | H19: TranPLH | I19: Passed | J19: 46276 | K19: TranPLH | L19: Passed | M19: 46300 | N19: TranPLH
A20: TC-SERVICE-VIEW-09 | B20: Sort services using all supported sort modes | C20: 1. Select Newest First, Oldest First, Price High to Low, Price Low to High, and Name A-Z. | D20: - Services are reordered locally according to created date, numeric price, or localeCompare name logic. | E20: Service list contains multiple services with different dates/prices/names. | F20: Passed | G20: 46259 | H20: TranPLH | I20: Passed | J20: 46277 | K20: TranPLH | L20: Passed | M20: 46301 | N20: TranPLH
A21: TC-SERVICE-VIEW-10 | B21: Show empty state when current search/filter returns no services | C21: 1. Apply search/filter combination with no matches. | D21: - Empty-state UI is displayed. - Add New Service action remains available. - UI does not distinguish zero catalog from zero filtered matches. | E21: Admin service page is loaded. | F21: Failed | G21: 46259 | H21: TranPLH | I21: Passed | J21: 46277 | K21: TranPLH | L21: Passed | M21: 46301 | N21: TranPLH | O21: Empty filtered-state rendering passed after R2 retest
A22: TC-SERVICE-VIEW-11 | B22: Switch grid/list view and open/close service detail using loaded object | C22: 1. Switch between grid and list view. 2. Open a service detail panel. 3. Close the detail panel. | D22: - View mode changes locally. - Detail renders name, description, image, price, timeCost, status and Added Date from loaded object. - No separate GET detail request is sent by the management panel. | E22: At least one service is loaded. | F22: Passed | G22: 46260 | H22: TranPLH | I22: Passed | J22: 46278 | K22: TranPLH | L22: Passed | M22: 46302 | N22: TranPLH
A23: TC-SERVICE-VIEW-12 | B23: Normalize legacy service with missing/null timeCost in API response | C23: 1. Load/detail a legacy Service record whose timeCost is null or undefined. | D23: - normalizeService returns timeCost=30 in the response. - No DB migration or write is performed by normalization. | E23: Legacy service record has null/undefined timeCost. | F23: Passed | G23: 46260 | H23: TranPLH | I23: Passed | J23: 46278 | K23: TranPLH | L23: Passed | M23: 46302 | N23: TranPLH
A24: Function 2: Create Parking Service
A25: TC-SERVICE-CREATE-01 | B25: Open Create and Edit modals with correct initial values | C25: 1. Click Add New Service. 2. Close and open Edit Settings on an existing service. | D25: - Create modal resets form to create defaults and clears file/errors. - Edit modal populates values from the selected service and clears file/errors. | E25: Admin service page is loaded. | F25: Passed | G25: 46261 | H25: TranPLH | I25: Passed | J25: 46279 | K25: TranPLH | L25: Passed | M25: 46303 | N25: TranPLH
A26: TC-SERVICE-CREATE-02 | B26: Cancel service form without saving | C26: 1. Open Create or Edit modal. 2. Change form fields. 3. Click Cancel. 4. Reopen the form. | D26: - Modal closes. - editingService and formError are cleared. - Reopened form is reset/repopulated from current data. - No create/update request is sent by Cancel. | E26: Create/Edit modal is open. | F26: Passed | G26: 46261 | H26: TranPLH | I26: Passed | J26: 46279 | K26: TranPLH | L26: Passed | M26: 46303 | N26: TranPLH
A27: TC-SERVICE-CREATE-03 | B27: Validate service name minimum length on frontend | C27: 1. Enter a raw service name shorter than 3 characters. 2. Attempt Save Service. 3. Repeat with raw length at least 3. | D27: - Raw length below 3 shows Service name must be at least 3 characters. - Save is blocked for invalid input. - validateForm does not trim before checking the length. | E27: Create/Edit modal is open; other fields are valid. | F27: Failed | G27: 46262 | H27: TranPLH | I27: Passed | J27: 46280 | K27: TranPLH | L27: Passed | M27: 46304 | N27: TranPLH | O27: Service-name validation passed after R2 retest
A28: TC-SERVICE-CREATE-04 | B28: Validate description minimum length on frontend | C28: 1. Enter description shorter than 5 characters. 2. Attempt Save Service. 3. Repeat with length at least 5. | D28: - Raw length below 5 shows Description must be at least 5 characters. - Save is blocked until the FE length condition passes. | E28: Create/Edit modal is open; other fields are valid. | F28: Failed | G28: 46262 | H28: TranPLH | I28: Passed | J28: 46280 | K28: TranPLH | L28: Passed | M28: 46304 | N28: TranPLH | O28: Description validation passed after R2 retest
A29: TC-SERVICE-CREATE-05 | B29: Validate service price on frontend | C29: 1. Leave price empty. 2. Enter 0 or a negative value. 3. Enter a positive value. | D29: - Empty, zero, or negative price triggers Price must be greater than 0. - Positive price passes custom FE price validation. - HTML min/step constraints remain a separate browser layer. | E29: Create/Edit modal is open; other fields are valid. | F29: Failed | G29: 46263 | H29: TranPLH | I29: Passed | J29: 46281 | K29: TranPLH | L29: Passed | M29: 46305 | N29: TranPLH | O29: Price validation passed after R2 retest
A30: TC-SERVICE-CREATE-06 | B30: Validate timeCost on frontend and backend boundary | C30: 1. Leave timeCost empty or enter nonpositive value in UI. 2. Submit a positive value. 3. Use direct API with fractional/<1 timeCost. | D30: - FE shows Time cost must be greater than 0 minutes for empty/nonpositive values. - Backend requires a whole number at least 1 minute. - Fractional or <1 direct API value is rejected. | E30: Create/Edit modal or authenticated direct API request is available. | F30: Failed | G30: 46263 | H30: TranPLH | I30: Passed | J30: 46281 | K30: TranPLH | L30: Passed | M30: 46305 | N30: TranPLH | O30: Time-cost validation passed after R2 retest
A31: TC-SERVICE-CREATE-07 | B31: Require image on create but allow edit without selecting a new image | C31: 1. Open Add New Service and leave image unselected. 2. Attempt save. 3. Open Edit Settings and save valid changes without a new image. | D31: - Create is blocked with Image is required for new services. - Edit can proceed without a new image and retains existing image data. | E31: Admin is authenticated; an existing service is available for edit. | F31: Passed | G31: 46264 | H31: TranPLH | I31: Passed | J31: 46282 | K31: TranPLH | L31: Passed | M31: 46306 | N31: TranPLH
A32: TC-SERVICE-CREATE-08 | B32: Submit valid Create/Edit form with loading state | C32: 1. Fill valid form values. 2. Click Save Service. 3. Keep request pending briefly. | D32: - FormData includes name, description, price, timeCost, isActive and optional image. - Correct create/update endpoint is selected. - Save shows loading/spinner and is disabled during shared loading. - Prior formError is reset before submission. | E32: Admin modal has valid input. | F32: Passed | G32: 46264 | H32: TranPLH | I32: Passed | J32: 46282 | K32: TranPLH | L32: Passed | M32: 46306 | N32: TranPLH
A33: TC-SERVICE-CREATE-09 | B33: Reject create request with missing required fields on backend | C33: 1. Send authenticated create request missing name, description, or price. | D33: - Backend returns HTTP 400 Please provide all required fields. - Cloudinary upload is not started by the missing-required-fields branch. | E33: Admin is authenticated; request reaches controller with upload middleware passed as needed. | F33: Passed | G33: 46265 | H33: TranPLH | I33: Passed | J33: 46283 | K33: TranPLH | L33: Passed | M33: 46307 | N33: TranPLH
A34: TC-SERVICE-CREATE-10 | B34: Verify backend price rules including zero-price mismatch with frontend | C34: 1. Send direct create/update with negative/non-finite price. 2. Send price=0. 3. Send update with empty price. | D34: - Invalid/negative price returns HTTP 400 Price must be a valid non-negative number. - Backend accepts price 0 although normal FE blocks it. - Empty update price returns HTTP 400 Price is required. | E34: Admin direct API access; target service exists for update path. | F34: Failed | G34: 46265 | H34: TranPLH | I34: Passed | J34: 46283 | K34: TranPLH | L34: Passed | M34: 46307 | N34: TranPLH | O34: Backend price-boundary behavior passed after R2 retest
A35: TC-SERVICE-CREATE-11 | B35: Verify backend timeCost default and update rules | C35: 1. Create service with timeCost missing/empty. 2. Update with timeCost omitted. 3. Update with empty, fractional, or <1 value. | D35: - Create missing/empty timeCost defaults to 30. - Update omitted timeCost preserves current value. - Update empty returns Time cost is required. - Fractional/<1 is rejected with whole-number minimum message. | E35: Admin is authenticated; required create fields/file are otherwise valid. | F35: Failed | G35: 46266 | H35: TranPLH | I35: Passed | J35: 46284 | K35: TranPLH | L35: Passed | M35: 46308 | N35: TranPLH | O35: Backend time-cost rules passed after R2 retest
A36: TC-SERVICE-CREATE-12 | B36: Verify isActive conversion on create request | C36: 1. Create with isActive omitted. 2. Create with true/'true'. 3. Create with false/other supplied value. | D36: - Only boolean true or string 'true' becomes active. - Other supplied values become false. - Omitted isActive follows controller conversion and becomes false even though schema default is true. | E36: Admin authenticated; create request otherwise valid. | F36: Passed | G36: 46266 | H36: TranPLH | I36: Passed | J36: 46284 | K36: TranPLH | L36: Passed | M36: 46308 | N36: TranPLH
A37: TC-SERVICE-CREATE-13 | B37: Create Parking Service successfully and handle post-upload failure risk | C37: 1. Submit valid create fields and valid image. 2. Allow Cloudinary upload and Service.create to succeed. 3. Repeat by causing DB failure after image upload. | D37: - Successful path returns HTTP 201 with service data. - Cloudinary/DB error follows error handler. - No compensating rollback is present for an image already uploaded before later DB failure. | E37: Admin authenticated; Cloudinary integration configured. | F37: Failed | G37: 46267 | H37: TranPLH | I37: Failed | J37: 46285 | K37: TranPLH | L37: Passed | M37: 46309 | N37: TranPLH | O37: Create/upload failure handling passed after R3 retest
A38: Function 3: Service Image Upload & Replacement
A39: TC-SERVICE-IMAGE-01 | B39: Validate selected image MIME type and file size on frontend | C39: 1. Select unsupported image MIME. 2. Select a JPEG/PNG/WebP file larger than 5 MiB. 3. Select a valid supported image within 5 MiB. | D39: - Invalid MIME shows Invalid file type. Please upload JPEG, PNG, or WebP. - Oversize file shows File size exceeds 5MB limit. - Valid image replaces the selected file/preview. | E39: Create/Edit modal is open. | F39: Failed | G39: 46267 | H39: TranPLH | I39: Passed | J39: 46285 | K39: TranPLH | L39: Passed | M39: 46309 | N39: TranPLH | O39: Image type/size validation passed after R2 retest
A40: TC-SERVICE-IMAGE-02 | B40: Reject invalid image upload in backend upload middleware | C40: 1. Send authenticated create/update multipart request with unsupported MIME. 2. Repeat with file exceeding configured upload limit. | D40: - Upload middleware rejects the request before service controller mutation. - Unsupported MIME error message is Only JPEG, PNG, and WebP images are allowed. - Error is handled by shared error handling path. | E40: Admin is authenticated; multipart request includes invalid file. | F40: Failed | G40: 46267 | H40: TranPLH | I40: Failed | J40: 46286 | K40: TranPLH | L40: Passed | M40: 46310 | N40: TranPLH | O40: Backend upload rejection handling passed after R3 retest
A41: TC-SERVICE-IMAGE-03 | B41: Replace service image on update | C41: 1. Edit an existing service and select a new valid image. 2. Repeat for a service with/without old cloudinary_id. | D41: - If old cloudinary_id is truthy, controller destroys old image before new upload. - New image is uploaded and image fields are updated. - Edit without file performs no external image replacement call. | E41: Existing service; Admin authenticated. | F41: Passed | G41: 46267 | H41: TranPLH | I41: Passed | J41: 46286 | K41: TranPLH | L41: Passed | M41: 46310 | N41: TranPLH
A42: TC-SERVICE-IMAGE-04 | B42: Handle external/DB failure after an earlier side effect | C42: 1. During create/update/delete, cause a later DB/Cloudinary step to fail after an earlier side effect succeeded. | D42: - Error response is returned. - No transaction/compensating rollback guarantees consistency between Cloudinary and DB state. | E42: Mutation has begun and one earlier side effect has completed. | F42: Passed | G42: 46267 | H42: TranPLH | I42: Passed | J42: 46287 | K42: TranPLH | L42: Passed | M42: 46311 | N42: TranPLH
A43: Function 4: Edit & Activate/Deactivate Parking Service
A44: TC-SERVICE-EDIT-01 | B44: Handle missing or malformed service id | C44: 1. Call GET detail/PUT/DELETE using a non-existing valid id. 2. Repeat with malformed ObjectId. | D44: - Non-existing service returns HTTP 404 Service not found. - Malformed ObjectId is mapped to HTTP 400 by shared error handler. | E44: API is reachable; Admin auth supplied for mutation paths. | F44: Passed | G44: 46267 | H44: TranPLH | I44: Passed | J44: 46287 | K44: TranPLH | L44: Passed | M44: 46311 | N44: TranPLH
A45: TC-SERVICE-EDIT-02 | B45: Partially edit service fields and toggle active/inactive using same PUT | C45: 1. Edit only selected service fields while omitting others. 2. Toggle Active Service/Inactive Service and save. | D45: - Supplied fields are updated; omitted fields are preserved by update behavior. - isActive status change uses the same PUT /api/admin/services/:id endpoint. - No separate status endpoint is called. | E45: Existing service; Admin authenticated. | F45: Passed | G45: 46267 | H45: TranPLH | I45: Passed | J45: 46288 | K45: TranPLH | L45: Passed | M45: 46312 | N45: TranPLH
A46: TC-SERVICE-EDIT-03 | B46: Handle schema-level field validation errors | C46: 1. Use direct update/create values that pass controller checks but fail Service schema, such as trim-to-empty required text or invalid schema field value. | D46: - Shared error handler returns HTTP 400 Validation error with errors. - FE surfaces a top-level form message and does not map schema errors to individual fields. | E46: Admin authenticated; request reaches schema validation. | F46: Failed | G46: 46267 | H46: TranPLH | I46: Failed | J46: 46288 | K46: TranPLH | L46: Passed | M46: 46312 | N46: TranPLH | O46: Schema validation error handling passed after R3 retest
A47: TC-SERVICE-EDIT-04 | B47: Handle successful and failed Save Service response | C47: 1. Submit valid create/edit and allow success. 2. Repeat with backend non-success response. | D47: - Success shows Service created successfully or Service updated successfully, reloads list, and closes modal. - Failure keeps modal/draft and sets formError using backend message or Action failed. | E47: Create/Edit request is pending. | F47: Passed | G47: 46267 | H47: TranPLH | I47: Passed | J47: 46289 | K47: TranPLH | L47: Passed | M47: 46313 | N47: TranPLH
A48: TC-SERVICE-EDIT-05 | B48: Handle native-fetch network or JSON parsing failure on create/update | C48: 1. Submit create/update. 2. Cause fetch or response JSON handling to throw. | D48: - Catch displays err.message in form error path. - Loading returns false. - Native create/update fetch does not invoke automatic token refresh/retry. | E48: Admin form submission is pending. | F48: Passed | G48: 46267 | H48: TranPLH | I48: Passed | J48: 46289 | K48: TranPLH | L48: Passed | M48: 46313 | N48: TranPLH
A49: Function 5: Delete Parking Service
A50: TC-SERVICE-DELETE-01 | B50: Open and cancel Delete Service confirmation | C50: 1. Select a service and open Delete confirmation. 2. Click Cancel. | D50: - Confirmation stores selected service for delete. - Cancel closes confirmation without DELETE. - Delete action is disabled while shared loading is true. | E50: Existing service is selected. | F50: Passed | G50: 46267 | H50: TranPLH | I50: Passed | J50: 46290 | K50: TranPLH | L50: Passed | M50: 46313 | N50: TranPLH
A51: TC-SERVICE-DELETE-02 | B51: Delete service record and Cloudinary image successfully | C51: 1. Confirm delete for an existing service with cloudinary_id. 2. Repeat for service without cloudinary_id. | D51: - With cloudinary_id, controller calls Cloudinary destroy before service.deleteOne. - Without id, delete proceeds without destroy call. - Successful backend response is HTTP 200 Service deleted successfully. | E51: Admin authenticated; target service exists. | F51: Passed | G51: 46267 | H51: TranPLH | I51: Passed | J51: 46290 | K51: TranPLH | L51: Passed | M51: 46313 | N51: TranPLH
A52: TC-SERVICE-DELETE-03 | B52: Handle Delete Service success and failure in frontend | C52: 1. Confirm delete and allow success. 2. Repeat with backend failure. | D52: - Success shows success toast, reloads list, closes confirmation and matching detail panel. - Failure shows backend/fallback Failed to delete service toast and keeps confirmation open. | E52: Delete confirmation is open. | F52: Passed | G52: 46267 | H52: TranPLH | I52: Passed | J52: 46291 | K52: TranPLH | L52: Passed | M52: 46313 | N52: TranPLH
A53: TC-SERVICE-DELETE-04 | B53: Refresh expired token once for Delete Service request | C53: 1. Trigger DELETE through apiFetch with expired/invalid access token. 2. Allow refresh success, then test refresh failure. | D53: - apiFetch can refresh and retry delete once. - Refresh failure clears auth/session and redirects to login according to shared API behavior. | E53: Delete request is using apiFetch; refresh path available. | F53: Passed | G53: 46267 | H53: TranPLH | I53: Passed | J53: 46291 | K53: TranPLH | L53: Passed | M53: 46313 | N53: TranPLH

Sheet 10. Ticket Package
A2: Feature | B2: Ticket Package | R2: Passed
A3: Test requirement | B3: Verify Ticket Package behavior for the four verified roles (guest, customer, staff, admin), including public/customer catalog, Staff/Admin catalog access, Admin Ticket Package management, Customer slot selection, eligibility/policy validation, Wallet purchase, PayOS purchase/verification, membership entitlement activation, and error/auth recovery. | R3: Failed
A4: Number of TCs | B4: =COUNTIF(A21:A83, "TC-*") -> 55 | R4: Pending
A5: Testing Round | B5: Passed | C5: Failed | D5: Pending | E5: N/A | R5: N/A
A6: Round 1 | B6: =COUNTIF(F11:F83, B5) -> 40 | C6: =COUNTIF(F11:F83, C5) -> 24 | D6: =COUNTIF(F11:F83, D5) -> 0 | E6: =COUNTIF(F11:F83, E5) -> 0
A7: Round 2 | B7: =COUNTIF(I11:I83, B5) -> 57 | C7: =COUNTIF(I11:I83, C5) -> 7 | D7: =COUNTIF(I11:I83, D5) -> 0 | E7: =COUNTIF(I11:I83, E5) -> 0
A8: Round 3 | B8: =COUNTIF(L11:L83, B5) -> 64 | C8: =COUNTIF(L11:L83, C5) -> 0 | D8: =COUNTIF(L11:L83, D5) -> 0 | E8: =COUNTIF(L11:L83, E5) -> 0
A10: Test Case ID | B10: Test Case Description | C10: Test Case Procedure | D10: Expected Results | E10: Pre-conditions | F10: Round 1 | G10: Test date | H10: Tester | I10: Round 2 | J10: Test date | K10: Tester | L10: Round 3 | M10: Test date | N10: Tester | O10: Note
A11: Function 1: Ticket Package Access & Role Permissions
A12: TC-TICKET-ACCESS-01 | B12: Redirect unauthenticated user from protected Ticket Package routes | C12: 1. Remove cached user session. 2. Open /membership, /staff/tickets, or /admin/tickets. | D12: - ProtectedRoute redirects to login with the return URL. - Protected Ticket Package page is not rendered. | E12: No cached user session exists. | F12: Passed | G12: 46255 | H12: TranPLH | I12: Passed | J12: 46273 | K12: TranPLH | L12: Passed | M12: 46297 | N12: TranPLH
A13: TC-TICKET-ACCESS-02 | B13: Reject cached user whose role does not match protected Ticket Package route | C13: 1. Use a cached role that does not match the target protected route. 2. Open the route. | D13: - Frontend redirects to /unauthorized. - Target Ticket Package page is not displayed. | E13: Cached user exists with a role not allowed by the selected route. | F13: Failed | G13: 46255 | H13: TranPLH | I13: Passed | J13: 46273 | K13: TranPLH | L13: Passed | M13: 46297 | N13: TranPLH | O13: Protected-route role handling passed after R2 retest
A14: TC-TICKET-ACCESS-03 | B14: Allow anonymous access to active Ticket Package catalog | C14: 1. Call GET /api/ticket-packages/active without a token. | D14: - Public endpoint runs without authentication. - Response contains active monthly/yearly packages only. | E14: Backend is reachable; active catalog contains package data. | F14: Passed | G14: 46256 | H14: TranPLH | I14: Passed | J14: 46274 | K14: TranPLH | L14: Passed | M14: 46298 | N14: TranPLH
A15: TC-TICKET-ACCESS-04 | B15: Reject protected Ticket Package API request with missing token | C15: 1. Call a protected catalog or mutation endpoint without Authorization token. | D15: - Backend returns HTTP 401. - Message: Access denied. No token provided. | E15: Protected Ticket Package endpoint is called without a token. | F15: Failed | G15: 46256 | H15: TranPLH | I15: Passed | J15: 46274 | K15: TranPLH | L15: Passed | M15: 46298 | N15: TranPLH | O15: Missing-token API handling passed after R2 retest
A16: TC-TICKET-ACCESS-05 | B16: Reject Ticket Package request with invalid JWT | C16: 1. Call a protected Ticket Package endpoint using an invalid JWT. | D16: - Backend returns HTTP 401 Invalid token. | E16: Authorization header contains an invalid JWT. | F16: Passed | G16: 46257 | H16: TranPLH | I16: Passed | J16: 46275 | K16: TranPLH | L16: Passed | M16: 46299 | N16: TranPLH
